Workbook

Sheet CONFIG
A1: PARAMETRO | B1: VALOR | C1: NOTA
A2: TC_EUR_USD | B2: 1.17 | C2: Tipo de cambio EUR a USD
A3: TC_USD_RD | B3: 63 | C3: Tipo de cambio USD a RD$
A4: MONEDA | B4: USD | C4: Moneda visible al cliente
A5: INCOTERM | B5: EXW | C5: Incoterm por defecto
A6: MARGEN_ARIAS_BASE | B6: 0.2 | C6: Referencia orientativa. El margen real se define por proyecto en INPUT.
A7: MERMA_OBRA | B7: 0.05 | C7: Merma estandar en obra (5%)
A8: DIAS_VALIDEZ | B8: 15 | C8: Dias de validez comercial
A9: LOGISTICA_FOB | C9: Pendiente tarifa Amura Cargo
A10: LOGISTICA_CIF | C10: Pendiente tarifa Amura Cargo
A11: FECHA_ACTUALIZACION_TC | B11: 2026-04-09 | C11: Fecha de actualizacion

Sheet PRODUCT
A1: ARIAS GROUP CARIBE — MAESTRO DE PRODUCTOS GYPSOTECH · Tarifa Abril 2026 · EXW Tarancón
A2: FAMILIA | B2: SUBFAMILIA | C2: NOMBRE | D2: CÓDIGO | E2: NORMA | F2: ANCHO MM | G2: ESPESOR MM | H2: LONGITUD MM | I2: M2 PLACA | J2: PESO KG M2 | K2: PESO PLACA KG | L2: UD PALE | M2: M2 PALE | N2: PESO PALE KG | O2: UD VENTA | P2: UD LOGISTICA | Q2: PVP ORIGEN EUR | R2: UNIDAD PRECIO | S2: DESCUENTO DISTRIBUIDOR | T2: PRECIO ARIAS EUR | U2: HS CODE | V2: RENDIMIENTO_M2 (solo cotización por sistemas) | W2: USO | X2: ACTIVO | Y2: DISPO TARANCON | Z2: NOTAS
A3: PLACAS | B3: STD | C3: STD BA 6mm 1200×2500 | D3: P00A006250AI | E3: EN 520 | F3: 1200 | G3: 6 | H3: 2500 | I3: =F3*H3/1000000 | J3: 5.3 | K3: =I3*J3 | O3: Placa | P3: Palé | Q3: 5.99 | R3: €/m² | S3: 0.5 | T3: =Q3*S3 | U3: 6809.11.00 | W3: Tabiques, trasdosados y techos continuos interiores | X3: SI | Y3: Solo Calliano | Z3: Solo disponible desde Calliano — no en Tarancón
A4: PLACAS | B4: STD | C4: STD BA 6mm 1200×3000 | D4: P00A006300A1 | E4: EN 520 | F4: 1200 | G4: 6 | H4: 3000 | I4: =F4*H4/1000000 | J4: 5.3 | K4: =I4*J4 | O4: Placa | P4: Palé | Q4: 5.99 | R4: €/m² | S4: 0.5 | T4: =Q4*S4 | U4: 6809.11.00 | W4: Tabiques, trasdosados y techos continuos interiores | X4: SI | Y4: Solo Calliano | Z4: Solo disponible desde Calliano — no en Tarancón
A5: PLACAS | B5: STD | C5: STD BA 10mm 1200×2000 | D5: P00A000200A0 | E5: EN 520 | F5: 1200 | G5: 9.5 | H5: 2000 | I5: =F5*H5/1000000 | J5: 7.7 | K5: =I5*J5 | L5: 60 | M5: =I5*L5 | N5: =K5*L5+32 | O5: Placa | P5: Palé | Q5: 4.96 | R5: €/m² | S5: 0.5 | T5: =Q5*S5 | U5: 6809.11.00 | W5: Tabiques, trasdosados y techos continuos interiores | X5: SI | Y5: SI
A6: PLACAS | B6: STD | C6: STD BA 10mm 1200×2500 | D6: P00A000250A0 | E6: EN 520 | F6: 1200 | G6: 9.5 | H6: 2500 | I6: =F6*H6/1000000 | J6: 7.7 | K6: =I6*J6 | L6: 48 | M6: =I6*L6 | N6: =K6*L6+32 | O6: Placa | P6: Palé | Q6: 4.96 | R6: €/m² | S6: 0.5 | T6: =Q6*S6 | U6: 6809.11.00 | W6: Tabiques, trasdosados y techos continuos interiores | X6: SI | Y6: SI
A7: PLACAS | B7: STD | C7: STD BA 10mm 1200×2600 | D7: P00A000260A0 | E7: EN 520 | F7: 1200 | G7: 9.5 | H7: 2600 | I7: =F7*H7/1000000 | J7: 7.7 | K7: =I7*J7 | L7: 48 | M7: =I7*L7 | N7: =K7*L7+32 | O7: Placa | P7: Palé | Q7: 4.96 | R7: €/m² | S7: 0.5 | T7: =Q7*S7 | U7: 6809.11.00 | W7: Tabiques, trasdosados y techos continuos interiores | X7: SI | Y7: SI
A8: PLACAS | B8: STD | C8: STD BA 10mm 1200×2700 | D8: P00A000270A0 | E8: EN 520 | F8: 1200 | G8: 9.5 | H8: 2700 | I8: =F8*H8/1000000 | J8: 7.7 | K8: =I8*J8 | L8: 48 | M8: =I8*L8 | N8: =K8*L8+32 | O8: Placa | P8: Palé | Q8: 4.96 | R8: €/m² | S8: 0.5 | T8: =Q8*S8 | U8: 6809.11.00 | W8: Tabiques, trasdosados y techos continuos interiores | X8: SI | Y8: SI
A9: PLACAS | B9: STD | C9: STD BA 10mm 1200×3000 | D9: P00A000300A0 | E9: EN 520 | F9: 1200 | G9: 9.5 | H9: 3000 | I9: =F9*H9/1000000 | J9: 7.7 | K9: =I9*J9 | L9: 48 | M9: =I9*L9 | N9: =K9*L9+32 | O9: Placa | P9: Palé | Q9: 4.96 | R9: €/m² | S9: 0.5 | T9: =Q9*S9 | U9: 6809.11.00 | W9: Tabiques, trasdosados y techos continuos interiores | X9: SI | Y9: SI
A10: PLACAS | B10: STD | C10: STD BA 13mm 1200×2000 | D10: P00A003200A0 | E10: EN 520 | F10: 1200 | G10: 12.5 | H10: 2000 | I10: =F10*H10/1000000 | J10: 8.7 | K10: =I10*J10 | L10: 60 | M10: =I10*L10 | N10: =K10*L10+32 | O10: Placa | P10: Palé | Q10: 4.03 | R10: €/m² | S10: 0.5 | T10: =Q10*S10 | U10: 6809.11.00 | W10: Tabiques, trasdosados y techos continuos interiores | X10: SI | Y10: SI
A11: PLACAS | B11: STD | C11: STD BA 13mm 1200×2400 | D11: P00A003240A0 | E11: EN 520 | F11: 1200 | G11: 12.5 | H11: 2400 | I11: =F11*H11/1000000 | J11: 8.7 | K11: =I11*J11 | L11: 48 | M11: =I11*L11 | N11: =K11*L11+32 | O11: Placa | P11: Palé | Q11: 4.03 | R11: €/m² | S11: 0.5 | T11: =Q11*S11 | U11: 6809.11.00 | W11: Tabiques, trasdosados y techos continuos interiores | X11: SI | Y11: SI
A12: PLACAS | B12: STD | C12: STD BA 13mm 1200×2500 | D12: P00A003250A0 | E12: EN 520 | F12: 1200 | G12: 12.5 | H12: 2500 | I12: =F12*H12/1000000 | J12: 8.7 | K12: =I12*J12 | L12: 48 | M12: =I12*L12 | N12: =K12*L12+32 | O12: Placa | P12: Palé | Q12: 4.03 | R12: €/m² | S12: 0.5 | T12: =Q12*S12 | U12: 6809.11.00 | W12: Tabiques, trasdosados y techos continuos interiores | X12: SI | Y12: SI
A13: PLACAS | B13: STD | C13: STD BA 13mm 1200×2600 | D13: P00A003260A0 | E13: EN 520 | F13: 1200 | G13: 12.5 | H13: 2600 | I13: =F13*H13/1000000 | J13: 8.7 | K13: =I13*J13 | L13: 48 | M13: =I13*L13 | N13: =K13*L13+32 | O13: Placa | P13: Palé | Q13: 4.03 | R13: €/m² | S13: 0.5 | T13: =Q13*S13 | U13: 6809.11.00 | W13: Tabiques, trasdosados y techos continuos interiores | X13: SI | Y13: SI
A14: PLACAS | B14: STD | C14: STD BA 13mm 1200×2700 | D14: P00A003270A0 | E14: EN 520 | F14: 1200 | G14: 12.5 | H14: 2700 | I14: =F14*H14/1000000 | J14: 8.7 | K14: =I14*J14 | L14: 48 | M14: =I14*L14 | N14: =K14*L14+32 | O14: Placa | P14: Palé | Q14: 4.03 | R14: €/m² | S14: 0.5 | T14: =Q14*S14 | U14: 6809.11.00 | W14: Tabiques, trasdosados y techos continuos interiores | X14: SI | Y14: SI
A15: PLACAS | B15: STD | C15: STD BA 13mm 1200×2800 | D15: P00A003280A0 | E15: EN 520 | F15: 1200 | G15: 12.5 | H15: 2800 | I15: =F15*H15/1000000 | J15: 8.7 | K15: =I15*J15 | L15: 48 | M15: =I15*L15 | N15: =K15*L15+32 | O15: Placa | P15: Palé | Q15: 4.03 | R15: €/m² | S15: 0.5 | T15: =Q15*S15 | U15: 6809.11.00 | W15: Tabiques, trasdosados y techos continuos interiores | X15: SI | Y15: SI
A16: PLACAS | B16: STD | C16: STD BA 13mm 1200×3000 | D16: P00A003300A0 | E16: EN 520 | F16: 1200 | G16: 12.5 | H16: 3000 | I16: =F16*H16/1000000 | J16: 8.7 | K16: =I16*J16 | L16: 36 | M16: =I16*L16 | N16: =K16*L16+32 | O16: Placa | P16: Palé | Q16: 4.03 | R16: €/m² | S16: 0.5 | T16: =Q16*S16 | U16: 6809.11.00 | W16: Tabiques, trasdosados y techos continuos interiores | X16: SI | Y16: SI
... A25: PLACAS | B25: STD | C25: STD BA 18mm 1200×3000 | D25: P00A008300A0 | E25: EN 520 | F25: 1200 | G25: 18 | H25: 3000 | I25: =F25*H25/1000000 | J25: 14.2 | K25: =I25*J25 | L25: 24 | M25: =I25*L25 | N25: =K25*L25+32 | O25: Placa | P25: Palé | Q25: 5.99 | R25: €/m² | S25: 0.5 | T25: =Q25*S25 | U25: 6809.11.00 | W25: Tabiques, trasdosados y techos continuos interiores | X25: SI | Y25: SI
A26: PLACAS | B26: STD Zero | C26: STD Zero BA 13mm 1200×2000 | D26: P00AZ03200A0 | E26: EN 520 | F26: 1200 | G26: 12.5 | H26: 2000 | I26: =F26*H26/1000000 | J26: 8.7 | K26: =I26*J26 | O26: Placa | P26: Palé | Q26: 17.6 | R26: €/m² | S26: 0.5 | T26: =Q26*S26 | U26: 6809.11.00 | W26: Tabiques trasdosados techos — Euroclase A1 reacción al fuego | X26: SI | Y26: Solo Calliano | Z26: Solo disponible desde Calliano — no en Tarancón
A27: PLACAS | B27: STD Zero | C27: STD Zero BA 13mm 1200×3000 | D27: P00AZ03300A2 | E27: EN 520 | F27: 1200 | G27: 12.5 | H27: 3000 | I27: =F27*H27/1000000 | J27: 8.7 | K27: =I27*J27 | O27: Placa | P27: Palé | Q27: 17.6 | R27: €/m² | S27: 0.5 | T27: =Q27*S27 | U27: 6809.11.00 | W27: Tabiques trasdosados techos — Euroclase A1 reacción al fuego | X27: SI | Y27: Solo Calliano | Z27: Solo disponible desde Calliano — no en Tarancón
A28: PLACAS | B28: STD Zero | C28: STD Zero BA 15mm 1200×3000 | D28: P00AZ05300A2 | E28: EN 520 | F28: 1200 | G28: 15 | H28: 3000 | I28: =F28*H28/1000000 | J28: 11.6 | K28: =I28*J28 | O28: Placa | P28: Palé | Q28: 20.5 | R28: €/m² | S28: 0.5 | T28: =Q28*S28 | U28: 6809.11.00 | W28: Tabiques trasdosados techos — Euroclase A1 reacción al fuego | X28: SI | Y28: Solo Calliano | Z28: Solo disponible desde Calliano — no en Tarancón
A29: PLACAS | B29: SIMPLY | C29: GypsoSIMPLY BA 13mm 1200×2000 | D29: P00Y003200A0 | E29: EN 520 | F29: 1200 | G29: 12.5 | H29: 2000 | I29: =F29*H29/1000000 | J29: 7.8 | K29: =I29*J29 | L29: 72 | M29: =I29*L29 | N29: =K29*L29+32 | O29: Placa | P29: Palé | Q29: 4.63 | R29: €/m² | S29: 0.5 | T29: =Q29*S29 | U29: 6809.11.00 | W29: Placa aligerada — mismas prestaciones que STD con menor peso | X29: SI | Y29: SI
A30: PLACAS | B30: SIMPLY | C30: GypsoSIMPLY BA 13mm 1200×2500 | D30: P00Y003250A0 | E30: EN 520 | F30: 1200 | G30: 12.5 | H30: 2500 | I30: =F30*H30/1000000 | J30: 7.8 | K30: =I30*J30 | L30: 48 | M30: =I30*L30 | N30: =K30*L30+32 | O30: Placa | P30: Palé | Q30: 4.63 | R30: €/m² | S30: 0.5 | T30: =Q30*S30 | U30: 6809.11.00 | W30: Placa aligerada — mismas prestaciones que STD con menor peso | X30: SI | Y30: SI
A31: PLACAS | B31: SIMPLY | C31: GypsoSIMPLY BA 13mm 1200×2800 | D31: P00Y003280A0 | E31: EN 520 | F31: 1200 | G31: 12.5 | H31: 2800 | I31: =F31*H31/1000000 | J31: 7.8 | K31: =I31*J31 | L31: 48 | M31: =I31*L31 | N31: =K31*L31+32 | O31: Placa | P31: Palé | Q31: 4.63 | R31: €/m² | S31: 0.5 | T31: =Q31*S31 | U31: 6809.11.00 | W31: Placa aligerada — mismas prestaciones que STD con menor peso | X31: SI | Y31: SI
A32: PLACAS | B32: SIMPLY | C32: GypsoSIMPLY BA 13mm 1200×3000 | D32: P00Y003300A0 | E32: EN 520 | F32: 1200 | G32: 12.5 | H32: 3000 | I32: =F32*H32/1000000 | J32: 7.8 | K32: =I32*J32 | L32: 48 | M32: =I32*L32 | N32: =K32*L32+32 | O32: Placa | P32: Palé | Q32: 4.63 | R32: €/m² | S32: 0.5 | T32: =Q32*S32 | U32: 6809.11.00 | W32: Placa aligerada — mismas prestaciones que STD con menor peso | X32: SI | Y32: SI
A33: PLACAS | B33: AQUA H2 | C33: AQUA H2 BA 13mm 1200×2000 | D33: P00H003200A0 | E33: EN 520 | F33: 1200 | G33: 12.5 | H33: 2000 | I33: =F33*H33/1000000 | J33: 8.7 | K33: =I33*J33 | L33: 60 | M33: =I33*L33 | N33: =K33*L33+32 | O33: Placa | P33: Palé | Q33: 6.71 | R33: €/m² | S33: 0.5 | T33: =Q33*S33 | U33: 6809.11.00 | W33: Humedad <10% — zonas húmedas interiores | X33: SI | Y33: SI
A34: PLACAS | B34: AQUA H2 | C34: AQUA H2 BA 13mm 1200×2500 | D34: P00H003250A0 | E34: EN 520 | F34: 1200 | G34: 12.5 | H34: 2500 | I34: =F34*H34/1000000 | J34: 8.7 | K34: =I34*J34 | L34: 48 | M34: =I34*L34 | N34: =K34*L34+32 | O34: Placa | P34: Palé | Q34: 6.71 | R34: €/m² | S34: 0.5 | T34: =Q34*S34 | U34: 6809.11.00 | W34: Humedad <10% — zonas húmedas interiores | X34: SI | Y34: SI
A35: PLACAS | B35: AQUA H2 | C35: AQUA H2 BA 13mm 1200×2600 | D35: P00H003260A0 | E35: EN 520 | F35: 1200 | G35: 12.5 | H35: 2600 | I35: =F35*H35/1000000 | J35: 8.7 | K35: =I35*J35 | L35: 48 | M35: =I35*L35 | N35: =K35*L35+32 | O35: Placa | P35: Palé | Q35: 6.71 | R35: €/m² | S35: 0.5 | T35: =Q35*S35 | U35: 6809.11.00 | W35: Humedad <10% — zonas húmedas interiores | X35: SI | Y35: SI
A36: PLACAS | B36: AQUA H2 | C36: AQUA H2 BA 13mm 1200×2800 | D36: P00H003280A0 | E36: EN 520 | F36: 1200 | G36: 12.5 | H36: 2800 | I36: =F36*H36/1000000 | J36: 8.7 | K36: =I36*J36 | L36: 36 | M36: =I36*L36 | N36: =K36*L36+32 | O36: Placa | P36: Palé | Q36: 6.71 | R36: €/m² | S36: 0.5 | T36: =Q36*S36 | U36: 6809.11.00 | W36: Humedad <10% — zonas húmedas interiores | X36: SI | Y36: SI
A37: PLACAS | B37: AQUA H2 | C37: AQUA H2 BA 13mm 1200×3000 | D37: P00H003300A0 | E37: EN 520 | F37: 1200 | G37: 12.5 | H37: 3000 | I37: =F37*H37/1000000 | J37: 8.7 | K37: =I37*J37 | L37: 36 | M37: =I37*L37 | N37: =K37*L37+32 | O37: Placa | P37: Palé | Q37: 6.71 | R37: €/m² | S37: 0.5 | T37: =Q37*S37 | U37: 6809.11.00 | W37: Humedad <10% — zonas húmedas interiores | X37: SI | Y37: SI
A38: PLACAS | B38: AQUA H2 | C38: AQUA H2 BA 15mm 1200×2000 | D38: P00H005200A0 | E38: EN 520 | F38: 1200 | G38: 15 | H38: 2000 | I38: =F38*H38/1000000 | J38: 8.7 | K38: =I38*J38 | L38: 36 | M38: =I38*L38 | N38: =K38*L38+32 | O38: Placa | P38: Palé | Q38: 7.73 | R38: €/m² | S38: 0.5 | T38: =Q38*S38 | U38: 6809.11.00 | W38: Humedad <10% — zonas húmedas interiores | X38: SI | Y38: SI
A39: PLACAS | B39: AQUA H2 | C39: AQUA H2 BA 15mm 1200×2600 | D39: P00H005260A0 | E39: EN 520 | F39: 1200 | G39: 15 | H39: 2600 | I39: =F39*H39/1000000 | J39: 8.7 | K39: =I39*J39 | L39: 24 | M39: =I39*L39 | N39: =K39*L39+32 | O39: Placa | P39: Palé | Q39: 7.73 | R39: €/m² | S39: 0.5 | T39: =Q39*S39 | U39: 6809.11.00 | W39: Humedad <10% — zonas húmedas interiores | X39: SI | Y39: SI
A40: PLACAS | B40: AQUA H2 | C40: AQUA H2 BA 15mm 1200×3000 | D40: P00H005300A0 | E40: EN 520 | F40: 1200 | G40: 15 | H40: 3000 | I40: =F40*H40/1000000 | J40: 8.7 | K40: =I40*J40 | L40: 24 | M40: =I40*L40 | N40: =K40*L40+32 | O40: Placa | P40: Palé | Q40: 7.73 | R40: €/m² | S40: 0.5 | T40: =Q40*S40 | U40: 6809.11.00 | W40: Humedad <10% — zonas húmedas interiores | X40: SI | Y40: SI
... A60: PLACAS | B60: FOCUS Ultra | C60: FOCUS ULTRA BA 25mm 1200×2000 | D60: P00F004200A0 | E60: EN 520 | F60: 1200 | G60: 25 | H60: 2000 | I60: =F60*H60/1000000 | J60: 22 | K60: =I60*J60 | L60: 24 | M60: =I60*L60 | N60: =K60*L60+32 | O60: Placa | P60: Palé | Q60: 13.57 | R60: €/m² | S60: 0.5 | T60: =Q60*S60 | U60: 6809.11.00 | W60: Protección pasiva al fuego — fibra de vidrio y vermiculita | X60: SI | Y60: SI
A61: PLACAS | B61: FOCUS Zero | C61: FOCUS ZERO BA 13mm 1200×2500 | D61: P00FZ03250A0 | E61: EN 520 | F61: 1200 | G61: 12.5 | H61: 2500 | I61: =F61*H61/1000000 | J61: 10.8 | K61: =I61*J61 | O61: Placa | P61: Palé | Q61: 22.05 | R61: €/m² | S61: 0.5 | T61: =Q61*S61 | U61: 6809.11.00 | W61: Protección pasiva al fuego — fibra de vidrio y vermiculita | X61: SI | Y61: Solo Calliano | Z61: Solo disponible desde Calliano — no en Tarancón
A62: PLACAS | B62: FOCUS Zero | C62: FOCUS ZERO BA 13mm 1200×3000 | D62: P00FZ03300A2 | E62: EN 520 | F62: 1200 | G62: 12.5 | H62: 3000 | I62: =F62*H62/1000000 | J62: 10.8 | K62: =I62*J62 | O62: Placa | P62: Palé | Q62: 22.05 | R62: €/m² | S62: 0.5 | T62: =Q62*S62 | U62: 6809.11.00 | W62: Protección pasiva al fuego — fibra de vidrio y vermiculita | X62: SI | Y62: Solo Calliano | Z62: Solo disponible desde Calliano — no en Tarancón
A63: PLACAS | B63: FOCUS Zero | C63: FOCUS ZERO BA 15mm 1200×3000 | D63: P00FZ05300A2 | E63: EN 520 | F63: 1200 | G63: 15 | H63: 3000 | I63: =F63*H63/1000000 | J63: 13.6 | K63: =I63*J63 | O63: Placa | P63: Palé | Q63: 23.88 | R63: €/m² | S63: 0.5 | T63: =Q63*S63 | U63: 6809.11.00 | W63: Protección pasiva al fuego — fibra de vidrio y vermiculita | X63: SI | Y63: Solo Calliano | Z63: Solo disponible desde Calliano — no en Tarancón
A64: PLACAS | B64: SILENS | C64: GypsoSILENS BA 13mm 1200×2500 | D64: P00GS03250A0 | E64: EN 520 | F64: 1200 | G64: 13 | H64: 2500 | I64: =F64*H64/1000000 | J64: 11.9 | K64: =I64*J64 | L64: 36 | M64: =I64*L64 | N64: =K64*L64+32 | O64: Placa | P64: Palé | Q64: 7.42 | R64: €/m² | S64: 0.5 | T64: =Q64*S64 | U64: 6809.11.00 | W64: Densidad >800 kg/m³ — alto aislamiento acústico | X64: SI | Y64: SI
A65: PLACAS | B65: SILENS | C65: GypsoSILENS BA 13mm 1200×2600 | D65: P00GS03260A0 | E65: EN 520 | F65: 1200 | G65: 13 | H65: 2600 | I65: =F65*H65/1000000 | J65: 11.9 | K65: =I65*J65 | L65: 36 | M65: =I65*L65 | N65: =K65*L65+32 | O65: Placa | P65: Palé | Q65: 7.42 | R65: €/m² | S65: 0.5 | T65: =Q65*S65 | U65: 6809.11.00 | W65: Densidad >800 kg/m³ — alto aislamiento acústico | X65: SI | Y65: SI
A66: PLACAS | B66: SILENS | C66: GypsoSILENS BA 13mm 1200×3000 | D66: P00GS03300A0 | E66: EN 520 | F66: 1200 | G66: 13 | H66: 3000 | I66: =F66*H66/1000000 | J66: 11.9 | K66: =I66*J66 | L66: 24 | M66: =I66*L66 | N66: =K66*L66+32 | O66: Placa | P66: Palé | Q66: 7.42 | R66: €/m² | S66: 0.5 | T66: =Q66*S66 | U66: 6809.11.00 | W66: Densidad >800 kg/m³ — alto aislamiento acústico | X66: SI | Y66: SI
A67: PLACAS | B67: LIGNUM | C67: GypsoLIGNUM BA 13mm 1200×2000 | D67: P00LB03200AC | E67: EN 520 | F67: 1200 | G67: 12.5 | H67: 2000 | I67: =F67*H67/1000000 | J67: 12.8 | K67: =I67*J67 | L67: 36 | M67: =I67*L67 | N67: =K67*L67+32 | O67: Placa | P67: Palé | Q67: 11.73 | R67: €/m² | S67: 0.5 | T67: =Q67*S67 | U67: 6809.11.00 | W67: Densidad >1000 kg/m³ — fuego impacto humedad prestaciones acústicas | X67: SI | Y67: SI
A68: PLACAS | B68: LIGNUM | C68: GypsoLIGNUM BA 13mm 1200×2500 | D68: P00LB03250AC | E68: EN 520 | F68: 1200 | G68: 12.5 | H68: 2500 | I68: =F68*H68/1000000 | J68: 12.8 | K68: =I68*J68 | L68: 24 | M68: =I68*L68 | N68: =K68*L68+32 | O68: Placa | P68: Palé | Q68: 11.73 | R68: €/m² | S68: 0.5 | T68: =Q68*S68 | U68: 6809.11.00 | W68: Densidad >1000 kg/m³ — fuego impacto humedad prestaciones acústicas | X68: SI | Y68: SI
A69: PLACAS | B69: LIGNUM | C69: GypsoLIGNUM BA 13mm 1200×2600 | D69: P00LB03260AC | E69: EN 520 | F69: 1200 | G69: 12.5 | H69: 2600 | I69: =F69*H69/1000000 | J69: 12.8 | K69: =I69*J69 | L69: 24 | M69: =I69*L69 | N69: =K69*L69+32 | O69: Placa | P69: Palé | Q69: 11.73 | R69: €/m² | S69: 0.5 | T69: =Q69*S69 | U69: 6809.11.00 | W69: Densidad >1000 kg/m³ — fuego impacto humedad prestaciones acústicas | X69: SI | Y69: SI
A70: PLACAS | B70: LIGNUM | C70: GypsoLIGNUM BA 13mm 1200×3000 | D70: P00LB03300AC | E70: EN 520 | F70: 1200 | G70: 12.5 | H70: 3000 | I70: =F70*H70/1000000 | J70: 12.8 | K70: =I70*J70 | L70: 24 | M70: =I70*L70 | N70: =K70*L70+32 | O70: Placa | P70: Palé | Q70: 11.73 | R70: €/m² | S70: 0.5 | T70: =Q70*S70 | U70: 6809.11.00 | W70: Densidad >1000 kg/m³ — fuego impacto humedad prestaciones acústicas | X70: SI | Y70: SI
A71: PLACAS | B71: LIGNUM | C71: GypsoLIGNUM BA 15mm 1200×2000 | D71: P00LB05200AC | E71: EN 520 | F71: 1200 | G71: 15 | H71: 2000 | I71: =F71*H71/1000000 | J71: 15.4 | K71: =I71*J71 | L71: 36 | M71: =I71*L71 | N71: =K71*L71+32 | O71: Placa | P71: Palé | Q71: 13.98 | R71: €/m² | S71: 0.5 | T71: =Q71*S71 | U71: 6809.11.00 | W71: Densidad >1000 kg/m³ — fuego impacto humedad prestaciones acústicas | X71: SI | Y71: SI
A72: PLACAS | B72: LIGNUM Zero | C72: GypsoLIGNUM Zero BA 13mm 1200×3000 | D72: P00GZ03300AC | E72: EN 520 | F72: 1200 | G72: 12.5 | H72: 3000 | I72: =F72*H72/1000000 | J72: 12.8 | K72: =I72*J72 | O72: Placa | P72: Palé | Q72: 31.89 | R72: €/m² | S72: 0.5 | T72: =Q72*S72 | U72: 6809.11.00 | W72: Densidad >1000 kg/m³ — fuego impacto humedad prestaciones acústicas | X72: SI | Y72: Solo Calliano | Z72: Solo disponible desde Calliano — no en Tarancón
A73: PLACAS | B73: EXTERNA | C73: EXTERNA LIGHT BR 13mm 1200×2000 | D73: P00XL03200EI | E73: EN 520 | F73: 1200 | G73: 12.5 | H73: 2000 | I73: =F73*H73/1000000 | J73: 12 | K73: =I73*J73 | O73: Placa | P73: Palé | Q73: 25.57 | R73: €/m² | S73: 0.5 | T73: =Q73*S73 | U73: 6809.11.00 | W73: Placa cementosa interior/exterior — alta humedad y semiintemperie | X73: SI | Y73: Solo Calliano | Z73: Solo disponible desde Calliano — no en Tarancón
A74: PLACAS | B74: VAPOR | C74: VAPOR BA 13mm 1200×3000 | D74: P00V003300AI | E74: EN 520 | F74: 1200 | G74: 12.5 | H74: 3000 | I74: =F74*H74/1000000 | J74: 8.7 | K74: =I74*J74 | O74: Placa | P74: Palé | Q74: 9.78 | R74: €/m² | S74: 0.5 | T74: =Q74*S74 | U74: 6809.11.00 | W74: Barrera de vapor — lámina aluminio 15μm en cara posterior | X74: SI | Y74: Solo Calliano | Z74: Solo disponible desde Calliano — no en Tarancón
A75: PLACAS | B75: POCKET STD | C75: GypsoPOCKET STD BA 13mm 1200×900 | D75: P00A003090A0 | E75: EN 520 | F75: 1200 | G75: 12.5 | H75: 900 | I75: =F75*H75/1000000 | J75: 8.7 | K75: =I75*J75 | O75: Placa | P75: Palé | Q75: 6.49 | R75: €/m² | S75: 0.5 | T75: =Q75*S75 | U75: 6809.11.00 | W75: Placa reforma — fácil transporte 900mm longitud | X75: SI | Y75: Solo Calliano | Z75: Solo disponible desde Calliano — no en Tarancón
A76: PLACAS | B76: POCKET AQUA H2 | C76: GypsoPOCKET AQUA H2 BA 13mm 1200×900 | D76: P00H003090A0 | E76: EN 520 | F76: 1200 | G76: 12.5 | H76: 900 | I76: =F76*H76/1000000 | J76: 8.7 | K76: =I76*J76 | O76: Placa | P76: Palé | Q76: 10.16 | R76: €/m² | S76: 0.5 | T76: =Q76*S76 | U76: 6809.11.00 | W76: Placa reforma — fácil transporte 900mm longitud | X76: SI | Y76: Solo Calliano | Z76: Solo disponible desde Calliano — no en Tarancón
A77: PLACAS | B77: POCKET AQUASUPER | C77: GypsoPOCKET AQUASUPER BA 13mm 1200×900 | D77: P00W003090A0 | E77: EN 520 | F77: 1200 | G77: 12.5 | H77: 900 | I77: =F77*H77/1000000 | J77: 8.7 | K77: =I77*J77 | O77: Placa | P77: Palé | Q77: 10.71 | R77: €/m² | S77: 0.5 | T77: =Q77*S77 | U77: 6809.11.00 | W77: Placa reforma — fácil transporte 900mm longitud | X77: SI | Y77: Solo Calliano | Z77: Solo disponible desde Calliano — no en Tarancón
A78: PERFILES | B78: Montante | C78: Montante 48/35 Z1 | D78: C344836299A | E78: EN 14195 | F78: 48 | G78: 35 | H78: 2990 | I78: =F78*H78/1000000 | J78: 0.57 | K78: =I78*J78 | L78: 480 | M78: =I78*L78 | N78: =K78*L78+32 | O78: ml | P78: Palé | Q78: 1.4 | R78: €/ml | S78: 0.5 | T78: =Q78*S78 | U78: 7216.61.10 | W78: Estructura tabiques trasdosados techos — interior | X78: SI | Y78: SI | Z78: UD mín venta: 10 barras
A79: PERFILES | B79: Montante | C79: Montante 70/37 Z1 | D79: C367038269A | E79: EN 14195 | F79: 70 | G79: 37 | H79: 2690 | I79: =F79*H79/1000000 | J79: 0.7 | K79: =I79*J79 | L79: 250 | M79: =I79*L79 | N79: =K79*L79+32 | O79: ml | P79: Palé | Q79: 1.78 | R79: €/ml | S79: 0.5 | T79: =Q79*S79 | U79: 7216.61.10 | W79: Estructura tabiques trasdosados techos — interior | X79: SI | Y79: SI | Z79: UD mín venta: 10 barras
A80: PERFILES | B80: Montante | C80: Montante 90/40 Z1 | D80: C399041299A | E80: EN 14195 | F80: 90 | G80: 40 | H80: 2990 | I80: =F80*H80/1000000 | J80: 0.82 | K80: =I80*J80 | L80: 200 | M80: =I80*L80 | N80: =K80*L80+32 | O80: ml | P80: Palé | Q80: 2.23 | R80: €/ml | S80: 0.5 | T80: =Q80*S80 | U80: 7216.61.10 | W80: Estructura tabiques trasdosados techos — interior | X80: SI | Y80: SI | Z80: UD mín venta: 10 barras
A81: PERFILES | B81: Montante | C81: Montante 100/40 Z1 | D81: C3910041299A | E81: EN 14195 | F81: 100 | G81: 40 | H81: 2990 | I81: =F81*H81/1000000 | J81: 0.87 | K81: =I81*J81 | L81: 160 | M81: =I81*L81 | N81: =K81*L81+32 | O81: ml | P81: Palé | Q81: 2.5 | R81: €/ml | S81: 0.5 | T81: =Q81*S81 | U81: 7216.61.10 | W81: Estructura tabiques trasdosados techos — interior | X81: SI | Y81: SI | Z81: UD mín venta: 8 barras
A82: PERFILES | B82: Montante | C82: Montante 125/47 Z1 | D82: C4612548399A | E82: EN 14195 | F82: 125 | G82: 47 | H82: 3990 | I82: =F82*H82/1000000 | J82: 0.98 | K82: =I82*J82 | L82: 120 | M82: =I82*L82 | N82: =K82*L82+32 | O82: ml | P82: Palé | Q82: 3.13 | R82: €/ml | S82: 0.5 | T82: =Q82*S82 | U82: 7216.61.10 | W82: Estructura tabiques trasdosados techos — interior | X82: SI | Y82: SI | Z82: UD mín venta: 4 barras
A83: PERFILES | B83: Montante | C83: Montante 150/47 Z1 | D83: C4615048399A | E83: EN 14195 | F83: 150 | G83: 47 | H83: 3990 | I83: =F83*H83/1000000 | J83: 1.1 | K83: =I83*J83 | L83: 120 | M83: =I83*L83 | N83: =K83*L83+32 | O83: ml | P83: Palé | Q83: 3.69 | R83: €/ml | S83: 0.5 | T83: =Q83*S83 | U83: 7216.61.10 | W83: Estructura tabiques trasdosados techos — interior | X83: SI | Y83: SI | Z83: UD mín venta: 4 barras
A84: PERFILES | B84: Rail | C84: Rail 48 Z1 | D84: U304830300A | E84: EN 14195 | F84: 48 | G84: 30 | H84: 3000 | I84: =F84*H84/1000000 | J84: 0.45 | K84: =I84*J84 | L84: 560 | M84: =I84*L84 | N84: =K84*L84+32 | O84: ml | P84: Palé | Q84: 1.18 | R84: €/ml | S84: 0.5 | T84: =Q84*S84 | U84: 7216.61.10 | W84: Guía perimetral para montantes — interior | X84: SI | Y84: SI | Z84: UD mín venta: 10 barras
A85: PERFILES | B85: Rail | C85: Rail 70 Z1 | D85: U307030300A | E85: EN 14195 | F85: 70 | G85: 30 | H85: 3000 | I85: =F85*H85/1000000 | J85: 0.55 | K85: =I85*J85 | L85: 350 | M85: =I85*L85 | N85: =K85*L85+32 | O85: ml | P85: Palé | Q85: 1.43 | R85: €/ml | S85: 0.5 | T85: =Q85*S85 | U85: 7216.61.10 | W85: Guía perimetral para montantes — interior | X85: SI | Y85: SI | Z85: UD mín venta: 10 barras
A86: PERFILES | B86: Rail | C86: Rail 90 Z1 | D86: U309030300A | E86: EN 14195 | F86: 90 | G86: 30 | H86: 3000 | I86: =F86*H86/1000000 | J86: 0.64 | K86: =I86*J86 | L86: 280 | M86: =I86*L86 | N86: =K86*L86+32 | O86: ml | P86: Palé | Q86: 1.75 | R86: €/ml | S86: 0.5 | T86: =Q86*S86 | U86: 7216.61.10 | W86: Guía perimetral para montantes — interior | X86: SI | Y86: SI | Z86: UD mín venta: 10 barras
A87: PERFILES | B87: Rail | C87: Rail 100 Z1 | D87: U3010030300A | E87: EN 14195 | F87: 100 | G87: 30 | H87: 3000 | I87: =F87*H87/1000000 | J87: 0.7 | K87: =I87*J87 | L87: 160 | M87: =I87*L87 | N87: =K87*L87+32 | O87: ml | P87: Palé | Q87: 2.13 | R87: €/ml | S87: 0.5 | T87: =Q87*S87 | U87: 7216.61.10 | W87: Guía perimetral para montantes — interior | X87: SI | Y87: SI | Z87: UD mín venta: 8 barras
A88: PERFILES | B88: Rail | C88: Rail 125 Z1 | D88: U3512535300A | E88: EN 14195 | F88: 125 | G88: 35 | H88: 3000 | I88: =F88*H88/1000000 | J88: 0.81 | K88: =I88*J88 | L88: 120 | M88: =I88*L88 | N88: =K88*L88+32 | O88: ml | P88: Palé | Q88: 2.75 | R88: €/ml | S88: 0.5 | T88: =Q88*S88 | U88: 7216.61.10 | W88: Guía perimetral para montantes — interior | X88: SI | Y88: SI | Z88: UD mín venta: 4 barras
A89: PERFILES | B89: Rail | C89: Rail 150 Z1 | D89: U4015040300A | E89: EN 14195 | F89: 150 | G89: 40 | H89: 3000 | I89: =F89*H89/1000000 | J89: 0.91 | K89: =I89*J89 | L89: 120 | M89: =I89*L89 | N89: =K89*L89+32 | O89: ml | P89: Palé | Q89: 3 | R89: €/ml | S89: 0.5 | T89: =Q89*S89 | U89: 7216.61.10 | W89: Guía perimetral para montantes — interior | X89: SI | Y89: SI | Z89: UD mín venta: 4 barras
... A96: PERFILES | B96: U | C96: Perfil U 30 Z1 | D96: U193019300A | E96: EN 14195 | F96: 30 | G96: 19 | H96: 3000 | I96: =F96*H96/1000000 | J96: 0.33 | K96: =I96*J96 | L96: 1280 | M96: =I96*L96 | N96: =K96*L96+32 | O96: ml | P96: Palé | Q96: 1.1 | R96: €/ml | S96: 0.5 | T96: =Q96*S96 | U96: 7216.61.10 | W96: Perimetral techos suspendidos | X96: SI | Y96: SI | Z96: UD mín venta: 10 barras
A97: PERFILES | B97: Omega | C97: Omega | D97: E168218300Z1 | E97: EN 14195 | F97: 82 | G97: 18 | L97: 720 | M97: =I97*L97 | N97: =K97*L97+32 | O97: ml | P97: Palé | R97: €/ml | S97: 0.5 | U97: 7216.61.10 | W97: Trasdosados y techos continuos | X97: SI | Y97: SI | Z97: UD mín venta: 10 barras
A98: TORNILLOS | B98: PM PC | C98: Tornillo PM Punta Clavo Ø3,5×25 — 500ud | D98: 304100 | E98: EN 14566 | O98: Caja | P98: Caja | Q98: 9.21 | R98: €/caja | S98: 0.5 | T98: =Q98*S98 | U98: 6907.90.20 | W98: Fijación placa de yeso a estructura metálica | X98: SI | Y98: SI | Z98: Ø3,5×25 — 500 ud/caja
A99: TORNILLOS | B99: PM PC | C99: Tornillo PM Punta Clavo Ø3,5×25 — 1.000ud | D99: 304101 | E99: EN 14566 | O99: Caja | P99: Caja | Q99: 14 | R99: €/caja | S99: 0.5 | T99: =Q99*S99 | U99: 6907.90.20 | W99: Fijación placa de yeso a estructura metálica | X99: SI | Y99: SI | Z99: Ø3,5×25 — 1000 ud/caja
A100: TORNILLOS | B100: PM PC | C100: Tornillo PM Punta Clavo Ø3,5×25 — 5.000ud | D100: 304102 | E100: EN 14566 | O100: Caja | P100: Caja | Q100: 62.5 | R100: €/caja | S100: 0.5 | T100: =Q100*S100 | U100: 6907.90.20 | W100: Fijación placa de yeso a estructura metálica | X100: SI | Y100: SI | Z100: Ø3,5×25 — 5000 ud/caja
A101: TORNILLOS | B101: PM PC | C101: Tornillo PM Punta Clavo Ø3,5×35 — 500ud | D101: 304103 | E101: EN 14566 | O101: Caja | P101: Caja | Q101: 11.29 | R101: €/caja | S101: 0.5 | T101: =Q101*S101 | U101: 6907.90.20 | W101: Fijación placa de yeso a estructura metálica | X101: SI | Y101: SI | Z101: Ø3,5×35 — 500 ud/caja
A102: TORNILLOS | B102: PM PC | C102: Tornillo PM Punta Clavo Ø3,5×35 — 1.000ud | D102: 304104 | E102: EN 14566 | O102: Caja | P102: Caja | Q102: 17.28 | R102: €/caja | S102: 0.5 | T102: =Q102*S102 | U102: 6907.90.20 | W102: Fijación placa de yeso a estructura metálica | X102: SI | Y102: SI | Z102: Ø3,5×35 — 1000 ud/caja
A103: TORNILLOS | B103: PM PC | C103: Tornillo PM Punta Clavo Ø3,5×35 — 3.000ud | D103: 304105 | E103: EN 14566 | O103: Caja | P103: Caja | Q103: 46.23 | R103: €/caja | S103: 0.5 | T103: =Q103*S103 | U103: 6907.90.20 | W103: Fijación placa de yeso a estructura metálica | X103: SI | Y103: SI | Z103: Ø3,5×35 — 3000 ud/caja
A104: TORNILLOS | B104: PM PC | C104: Tornillo PM Punta Clavo Ø3,5×45 — 1.000ud | D104: 304106 | E104: EN 14566 | O104: Caja | P104: Caja | Q104: 23.08 | R104: €/caja | S104: 0.5 | T104: =Q104*S104 | U104: 6907.90.20 | W104: Fijación placa de yeso a estructura metálica | X104: SI | Y104: SI | Z104: Ø3,5×45 — 1000 ud/caja
A105: TORNILLOS | B105: PM PC | C105: Tornillo PM Punta Clavo Ø3,5×55 — 1.000ud | D105: 304107 | E105: EN 14566 | O105: Caja | P105: Caja | Q105: 29.35 | R105: €/caja | S105: 0.5 | T105: =Q105*S105 | U105: 6907.90.20 | W105: Fijación placa de yeso a estructura metálica | X105: SI | Y105: SI | Z105: Ø3,5×55 — 1000 ud/caja
A106: TORNILLOS | B106: PM PC | C106: Tornillo PM Punta Clavo Ø4,2×70 — 500ud | D106: 304108 | E106: EN 14566 | O106: Caja | P106: Caja | Q106: 24.03 | R106: €/caja | S106: 0.5 | T106: =Q106*S106 | U106: 6907.90.20 | W106: Fijación placa de yeso a estructura metálica | X106: SI | Y106: SI | Z106: Ø4,2×70 — 500 ud/caja
A107: TORNILLOS | B107: PM PC | C107: Tornillo PM Punta Clavo Ø4,8×90 — 250ud | D107: 304109 | E107: EN 14566 | O107: Caja | P107: Caja | Q107: 27.65 | R107: €/caja | S107: 0.5 | T107: =Q107*S107 | U107: 6907.90.20 | W107: Fijación placa de yeso a estructura metálica | X107: SI | Y107: SI | Z107: Ø4,8×90 — 250 ud/caja
A108: TORNILLOS | B108: PM PB | C108: Tornillo PM Punta Broca Ø3,5×25 — 1.000ud | D108: 304115 | E108: EN 14566 | O108: Caja | P108: Caja | Q108: 22.33 | R108: €/caja | S108: 0.5 | T108: =Q108*S108 | U108: 6907.90.20 | W108: Fijación placa de yeso a estructura metálica | X108: SI | Y108: SI | Z108: Ø3,5×25 — 1000 ud/caja
A109: TORNILLOS | B109: PM PB | C109: Tornillo PM Punta Broca Ø3,5×35 — 1.000ud | D109: 304116 | E109: EN 14566 | O109: Caja | P109: Caja | Q109: 27.6 | R109: €/caja | S109: 0.5 | T109: =Q109*S109 | U109: 6907.90.20 | W109: Fijación placa de yeso a estructura metálica | X109: SI | Y109: SI | Z109: Ø3,5×35 — 1000 ud/caja
... A122: TORNILLOS | B122: EL PB | C122: Tornillo Exterior Ø4,0×41 — 1.000ud | D122: 301241 | E122: EN 14566 | O122: Caja | P122: Caja | Q122: 87.23 | R122: €/caja | S122: 0.5 | T122: =Q122*S122 | U122: 6907.90.20 | W122: Fijación placa de yeso a estructura metálica | X122: SI | Y122: SI | Z122: Ø4,0×41 — 1000 ud/caja
A123: PASTAS | B123: Fassajoint 3h | C123: Fassajoint 3h — 25kg | D123: 356 | E123: EN 13963 | L123: 50 | O123: Saco/Bote | P123: Palé | Q123: 22.06 | R123: €/ud | S123: 0.5 | T123: =Q123*S123 | U123: 3214.10.00 | W123: Pasta junta placas PYL — trabajabilidad 3h | X123: SI | Y123: SI | Z123: 25kg/ud — 50 ud/palé
A124: PASTAS | B124: Fassajoint 8h | C124: Fassajoint 8h — 25kg | D124: 358U3 | E124: EN 13963 | L124: 60 | O124: Saco/Bote | P124: Palé | Q124: 22.06 | R124: €/ud | S124: 0.5 | T124: =Q124*S124 | U124: 3214.10.00 | W124: Pasta junta placas PYL — trabajabilidad 8h | X124: SI | Y124: SI | Z124: 25kg/ud — 60 ud/palé
A125: PASTAS | B125: Fassajoint Ideal | C125: Fassajoint Ideal 3.5 — 25kg | D125: 1312T1 | E125: EN 13963 | L125: 50 | O125: Saco/Bote | P125: Palé | Q125: 30.9 | R125: €/ud | S125: 0.5 | T125: =Q125*S125 | U125: 3214.10.00 | W125: Pasta junta placas PYL — trabajabilidad 3h30 | X125: SI | Y125: SI | Z125: 25kg/ud — 50 ud/palé
A126: PASTAS | B126: Gypsofiller | C126: Gypsofiller 10kg | D126: 372 | E126: EN 13963 | L126: 40 | O126: Saco/Bote | P126: Palé | Q126: 23.59 | R126: €/ud | S126: 0.5 | T126: =Q126*S126 | U126: 3214.10.00 | W126: Pasta acabado y emplastecer placas PYL | X126: SI | Y126: SI | Z126: 10kg/ud — 40 ud/palé
A127: PASTAS | B127: Gypsofiller | C127: Gypsofiller 25kg | D127: 370 | E127: EN 13963 | L127: 33 | O127: Saco/Bote | P127: Palé | Q127: 47.16 | R127: €/ud | S127: 0.5 | T127: =Q127*S127 | U127: 3214.10.00 | W127: Pasta acabado y emplastecer placas PYL | X127: SI | Y127: SI | Z127: 25kg/ud — 33 ud/palé
A128: PASTAS | B128: Gypsomaf | C128: Gypsomaf 10kg | D128: 360E1 | E128: EN 13963 | L128: 90 | O128: Saco/Bote | P128: Palé | Q128: 7.72 | R128: €/ud | S128: 0.5 | T128: =Q128*S128 | U128: 3214.10.00 | W128: Pasta encolado placas sobre soportes secos | X128: SI | Y128: SI | Z128: 10kg/ud — 90 ud/palé
A129: PASTAS | B129: Gypsomaf | C129: Gypsomaf 25kg | D129: 359 | E129: EN 13963 | L129: 50 | O129: Saco/Bote | P129: Palé | Q129: 15.44 | R129: €/ud | S129: 0.5 | T129: =Q129*S129 | U129: 3214.10.00 | W129: Pasta encolado placas sobre soportes secos | X129: SI | Y129: SI | Z129: 25kg/ud — 50 ud/palé
A130: PASTAS | B130: Fast 299 | C130: Fast 299 — 20kg | D130: 2990NEUTRO0 | E130: EN 13963 | L130: 33 | O130: Saco/Bote | P130: Palé | Q130: 62 | R130: €/ud | S130: 0.5 | T130: =Q130*S130 | U130: 3214.10.00 | W130: Pasta alisado interiores lista para usar | X130: SI | Y130: SI | Z130: 20kg/ud — 33 ud/palé
A131: CINTAS | B131: Juntas | C131: Cinta Juntas 50mm×23m — 24 rollos/caja | D131: 304056 | E131: EN 13963 | L131: 24 | O131: Rollo | P131: Caja | Q131: 2.48 | R131: €/rollo | S131: 0.5 | T131: =Q131*S131 | U131: 4811.59.00 | W131: Tratamiento juntas placas de yeso laminado | X131: SI | Y131: SI | Z131: 23m×50mm — 24 ud/caja
A132: CINTAS | B132: Juntas | C132: Cinta Juntas 50mm×75m — 20 rollos/caja | D132: 304057 | E132: EN 13963 | L132: 20 | O132: Rollo | P132: Caja | Q132: 5.63 | R132: €/rollo | S132: 0.5 | T132: =Q132*S132 | U132: 4811.59.00 | W132: Tratamiento juntas placas de yeso laminado | X132: SI | Y132: SI | Z132: 75m×50mm — 20 ud/caja
A133: CINTAS | B133: Juntas | C133: Cinta Juntas 50mm×150m — 10 rollos/caja | D133: 304058 | E133: EN 13963 | L133: 10 | O133: Rollo | P133: Caja | Q133: 8.38 | R133: €/rollo | S133: 0.5 | T133: =Q133*S133 | U133: 4811.59.00 | W133: Tratamiento juntas placas de yeso laminado | X133: SI | Y133: SI | Z133: 150m×50mm — 10 ud/caja
A134: CINTAS | B134: FV Autoadhesiva | C134: Malla FV Autoadhesiva 50mm×45m — 54 rollos/caja | D134: 304078 | E134: EN 15283 | L134: 54 | O134: Rollo | P134: Caja | Q134: 4.75 | R134: €/rollo | S134: 0.5 | T134: =Q134*S134 | U134: 7019.39.00 | W134: Tratamiento juntas placas de yeso laminado | X134: SI | Y134: SI | Z134: 45m×50mm — 54 ud/caja
... A140: CINTAS | B140: Externa Light | C140: Malla Externa Light 50m — 6 rollos/caja | D140: 301121 | E140: EN 15283 | L140: 6 | O140: Rollo | P140: Caja | Q140: 33.6 | R140: €/rollo | S140: 0.5 | T140: =Q140*S140 | U140: 7019.39.00 | W140: Tratamiento juntas placas de yeso laminado | X140: SI | Y140: SI | Z140: 50m — 6 ud/caja
A141: ACCESORIOS | B141: Suspensión | C141: Suspensión TC 47 90mm — 100ud/caja | D141: 304021 | E141: — | O141: ud | P141: Caja | Q141: 13.63 | R141: €/caja | S141: 0.5 | T141: =Q141*S141 | U141: 7318.15.90 | W141: Suspensión y anclaje de techos continuos | X141: SI | Y141: SI | Z141: 90mm — 100 ud/caja
A142: ACCESORIOS | B142: Suspensión | C142: Suspensión TC 47 180mm — 100ud/caja | D142: 304022 | E142: — | O142: ud | P142: Caja | Q142: 20.73 | R142: €/caja | S142: 0.5 | T142: =Q142*S142 | U142: 7318.15.90 | W142: Suspensión y anclaje de techos continuos | X142: SI | Y142: SI | Z142: 180mm — 100 ud/caja
A143: ACCESORIOS | B143: Suspensión | C143: Suspensión TC 47 240mm — 50ud/caja | D143: 304023 | E143: — | O143: ud | P143: Caja | Q143: 24.19 | R143: €/caja | S143: 0.5 | T143: =Q143*S143 | U143: 7318.15.90 | W143: Suspensión y anclaje de techos continuos | X143: SI | Y143: SI | Z143: 240mm — 50 ud/caja
A144: ACCESORIOS | B144: Anclaje | C144: Anclaje Directo 47×120 — 100ud/caja | D144: 304029 | E144: — | O144: ud | P144: Caja | Q144: 33.95 | R144: €/caja | S144: 0.5 | T144: =Q144*S144 | U144: 7318.15.90 | W144: Suspensión y anclaje de techos continuos | X144: SI | Y144: SI | Z144: 47×120mm — 100 ud/caja
A145: ACCESORIOS | B145: Anclaje | C145: Anclaje Directo 60×120 — 100ud/caja | D145: 304030 | E145: — | O145: ud | P145: Caja | Q145: 38.6 | R145: €/caja | S145: 0.5 | T145: =Q145*S145 | U145: 7318.15.90 | W145: Suspensión y anclaje de techos continuos | X145: SI | Y145: SI | Z145: 60×120mm — 100 ud/caja
A146: ACCESORIOS | B146: Anclaje | C146: Anclaje Universal Omega M6 — 100ud/caja | D146: 304036 | E146: — | O146: ud | P146: Caja | Q146: 39.38 | R146: €/caja | S146: 0.5 | T146: =Q146*S146 | U146: 7318.15.90 | W146: Suspensión y anclaje de techos continuos | X146: SI | Y146: SI | Z146: 20mm — 100 ud/caja
A147: ACCESORIOS | B147: Aislador | C147: Aislador Acústico TC 47 — 20ud/caja | D147: 304049 | E147: — | O147: ud | P147: Caja | Q147: 66.96 | R147: €/caja | S147: 0.5 | T147: =Q147*S147 | U147: 3926.90.97 | W147: Aislamiento acústico en estructuras TC 47 y trasdosados | X147: SI | Y147: SI | Z147: 47mm — 20 ud/caja
A148: ACCESORIOS | B148: Aislador | C148: Aislador Acústico Trasdosado — 25ud/caja | D148: 304050 | E148: — | O148: ud | P148: Caja | Q148: 171.43 | R148: €/caja | S148: 0.5 | T148: =Q148*S148 | U148: 3926.90.97 | W148: Aislamiento acústico en estructuras TC 47 y trasdosados | X148: SI | Y148: SI | Z148: — — 25 ud/caja
A149: TRAMPILLAS | B149: Metálica | C149: Trampilla Metálica 200×200mm | D149: TM200200 | E149: — | O149: ud | P149: ud | Q149: 21.45 | R149: €/ud | S149: 0.5 | T149: =Q149*S149 | U149: 8308.90.00 | W149: Acceso mantenimiento — techos continuos | X149: SI | Y149: SI | Z149: Dimensiones: 200×200mm
A150: TRAMPILLAS | B150: Metálica | C150: Trampilla Metálica 300×300mm | D150: TM300300 | E150: — | O150: ud | P150: ud | Q150: 24.7 | R150: €/ud | S150: 0.5 | T150: =Q150*S150 | U150: 8308.90.00 | W150: Acceso mantenimiento — techos continuos | X150: SI | Y150: SI | Z150: Dimensiones: 300×300mm
...

Sheet SYSTEM
A1: FAM | B1: PRODUCTO | C1: CÓDIGO | D1: CONTENIDO UNIDAD LOGÍSTICA | E1: PRECIO ARIAS €/unidad logística | F1: PRECIO ARIAS €/ud o €/ml real | G1: RENDIMIENTO / m² sistema | H1: UNIDAD RENDIMIENTO | I1: COSTE €/m² sistema
A2: SISTEMA 1 — TRASDOSADO SEMI-DIRECTO STD | Omega 82/16 · STD BA 12,5 mm - 1200x2500 · Sep. Omega 600 mm
A3: 2 | B3: Perfil Omega 82/16 - 3000 mm | C3: E168218300Z1 | D3: Barra 3000 mm | E3: 2,00 €/barra | F3: 0,665 €/ml | G3: 1.67 | H3: ml/m² | I3: 1.11
A4: 1 | B4: Gypsotech STD BA 12,5 mm - 1200x2500 | C4: P00A003250A0 | D4: Palé 48 ud / 144 m² | E4: 2,02 €/m² | F4: 2,015 €/m² | G4: 1.05 | H4: m²/m² | I4: 2.12
A5: 3 | B5: Tornillo Fosfatado PM PC Ø3,5x25 mm - 1000 ud | C5: 304101 | D5: Caja 1000 ud | E5: 7,00 €/caja | F5: 0,007 €/ud | G5: 15 | H5: ud/m² | I5: 0.1
A6: 4 | B6: Fassajoint 1H - Saco 10 kg | C6: 351E1 | D6: Saco 10 kg | E6: 6,63 €/saco | F6: 0,663 €/kg | G6: 0.35 | H6: kg/m² | I6: 0.23
A7: 5 | B7: Cinta de Juntas 50 mm - Rollo 150 ml | C7: 304058 | D7: Rollo 150 ml | E7: 4,19 €/rollo | F7: 0,028 €/ml | G7: 1.1 | H7: ml/m² | I7: 0.03
A8: 5 | B8: Banda Estanca Monoadhesiva 70 mm - Rollo 30 ml | C8: 304076 | D8: Rollo 30 ml | E8: 8,71 €/rollo | F8: 0,290 €/ml | G8: 1.72 | H8: ml/m² | I8: 0.5
A9: TOTAL COSTE MATERIAL / m² sistema | I9: 4.09 €
A12: SISTEMA 2 — TRASDOSADO SEMI-DIRECTO AQUA H2 | Omega 82/16 · AQUA H2 BA 12,5 mm - 1200x2500 · Sep. Omega 600 mm
A13: 2
A14: 1 | B14: Gypsotech AQUA H2 BA 12,5 mm - 1200x2500 | C14: P00H003250A0 | D14: Palé 48 ud / 144 m² | E14: 3,35 €/m² | F14: 3,355 €/m² | G14: 1.05 | H14: m²/m² | I14: 3.52
A15: 3 | B15: Tornillo Fosfatado PM PC Ø3,5x25 mm - 1000 ud | C15: 304101 | D15: Caja 1000 ud | E15: 7,00 €/caja | F15: 0,007 €/ud | G15: 15 | H15: ud/m² | I15: 0.1
A16: 4 | B16: Fassajoint 1H - Saco 10 kg | C16: 351E1 | D16: Saco 10 kg | E16: 6,63 €/saco | F16: 0,663 €/kg | G16: 0.35 | H16: kg/m² | I16: 0.23
A17: 5 | B17: Cinta de Juntas 50 mm - Rollo 150 ml | C17: 304058 | D17: Rollo 150 ml | E17: 4,19 €/rollo | F17: 0,028 €/ml | G17: 1.1 | H17: ml/m² | I17: 0.03
A18: 5 | B18: Banda Estanca Monoadhesiva 70 mm - Rollo 30 ml | C18: 304076 | D18: Rollo 30 ml | E18: 8,71 €/rollo | F18: 0,290 €/ml | G18: 1.72 | H18: ml/m² | I18: 0.5
A19: TOTAL COSTE MATERIAL / m² sistema | I19: 5.49 €
A22: SISTEMA 3A — TRASDOSADO STD | Mont.48 + Rail 48 · STD BA 12,5 mm - 1200x2500 · Sep. 400 mm
A23: 2 | B23: Montante 48/35 Z1 - 2990 mm | C23: C344836299A | D23: Barra 2990 mm | E23: 2,09 €/barra | F23: 0,700 €/ml | G23: 2.5 | H23: ml/m² | I23: 1.75
A24: 2
A25: 1 | B25: Gypsotech STD BA 12,5 mm - 1200x2500 | C25: P00A003250A0 | D25: Palé 48 ud / 144 m² | E25: 2,02 €/m² | F25: 2,015 €/m² | G25: 1.05 | H25: m²/m² | I25: 2.12
A26: 3 | B26: Tornillo Fosfatado PM PC Ø3,5x25 mm - 1000 ud | C26: 304101 | D26: Caja 1000 ud | E26: 7,00 €/caja | F26: 0,007 €/ud | G26: 15 | H26: ud/m² | I26: 0.1
A27: 3 | B27: Tornillo Cincado Metal-Metal PB Ø3,5x9,5 mm - 1000 ud | C27: 304134 | D27: Caja 1000 ud | E27: 7,19 €/caja | F27: 0,007 €/ud | G27: 3 | H27: ud/m² | I27: 0.02
A28: 4 | B28: Fassajoint 1H - Saco 10 kg | C28: 351E1 | D28: Saco 10 kg | E28: 6,63 €/saco | F28: 0,663 €/kg | G28: 0.35 | H28: kg/m² | I28: 0.23
A29: 5 | B29: Cinta de Juntas 50 mm - Rollo 150 ml | C29: 304058 | D29: Rollo 150 ml | E29: 4,19 €/rollo | F29: 0,028 €/ml | G29: 1.1 | H29: ml/m² | I29: 0.03
A30: 5 | B30: Banda Estanca Monoadhesiva 50 mm - Rollo 30 ml | C30: 304075 | D30: Rollo 30 ml | E30: 5,79 €/rollo | F30: 0,193 €/ml | G30: 1.72 | H30: ml/m² | I30: 0.33
A31: 2 | B31: Perfil Angular Z1 23x34 - 3000 mm | C31: L2334300A | D31: Barra 3000 mm | E31: 1,26 €/barra | F31: 0,420 €/ml | G31: 0.4 | H31: ml/m² | I31: 0.17
A32: TOTAL COSTE MATERIAL / m² sistema | I32: 5.31 €
A35: SISTEMA 3B — TRASDOSADO STD | Mont.48 + Rail 48 · STD BA 12,5 mm - 1200x2500 · Sep. 600 mm
A36: 2
A37: 2 | B37: Rail 48 Z1 - 3000 mm | C37: U304830300A | D37: Barra 3000 mm | E37: 1,77 €/barra | F37: 0,590 €/ml | G37: 0.95 | H37: ml/m² | I37: 0.56
A38: 1 | B38: Gypsotech STD BA 12,5 mm - 1200x2500 | C38: P00A003250A0 | D38: Palé 48 ud / 144 m² | E38: 2,02 €/m² | F38: 2,015 €/m² | G38: 1.05 | H38: m²/m² | I38: 2.12
A39: 3 | B39: Tornillo Fosfatado PM PC Ø3,5x25 mm - 1000 ud | C39: 304101 | D39: Caja 1000 ud | E39: 7,00 €/caja | F39: 0,007 €/ud | G39: 15 | H39: ud/m² | I39: 0.1
A40: 3 | B40: Tornillo Cincado Metal-Metal PB Ø3,5x9,5 mm - 1000 ud | C40: 304134 | D40: Caja 1000 ud | E40: 7,19 €/caja | F40: 0,007 €/ud | G40: 3 | H40: ud/m² | I40: 0.02
A41: 4 | B41: Fassajoint 1H - Saco 10 kg | C41: 351E1 | D41: Saco 10 kg | E41: 6,63 €/saco | F41: 0,663 €/kg | G41: 0.35 | H41: kg/m² | I41: 0.23
A42: 5 | B42: Cinta de Juntas 50 mm - Rollo 150 ml | C42: 304058 | D42: Rollo 150 ml | E42: 4,19 €/rollo | F42: 0,028 €/ml | G42: 1.1 | H42: ml/m² | I42: 0.03
A43: 5 | B43: Banda Estanca Monoadhesiva 50 mm - Rollo 30 ml | C43: 304075 | D43: Rollo 30 ml | E43: 5,79 €/rollo | F43: 0,193 €/ml | G43: 1.72 | H43: ml/m² | I43: 0.33
A44: 2 | B44: Perfil Angular Z1 23x34 - 3000 mm | C44: L2334300A | D44: Barra 3000 mm | E44: 1,26 €/barra | F44: 0,420 €/ml | G44: 0.4 | H44: ml/m² | I44: 0.17
A45: TOTAL COSTE MATERIAL / m² sistema | I45: 4.73 €
A48: SISTEMA 4A — TRASDOSADO AQUA H2 | Mont.48 + Rail 48 · AQUA H2 BA 12,5 mm - 1200x2500 · Sep. 400 mm
A49: 2 | B49: Montante 48/35 Z1 - 2990 mm | C49: C344836299A | D49: Barra 2990 mm | E49: 2,09 €/barra | F49: 0,700 €/ml | G49: 2.5 | H49: ml/m² | I49: 1.75
A50: 2 | B50: Rail 48 Z1 - 3000 mm | C50: U304830300A | D50: Barra 3000 mm | E50: 1,77 €/barra | F50: 0,590 €/ml | G50: 0.95 | H50: ml/m² | I50: 0.56
A51: 1 | B51: Gypsotech AQUA H2 BA 12,5 mm - 1200x2500 | C51: P00H003250A0 | D51: Palé 48 ud / 144 m² | E51: 3,35 €/m² | F51: 3,355 €/m² | G51: 1.05 | H51: m²/m² | I51: 3.52
A52: 3 | B52: Tornillo Fosfatado PM PC Ø3,5x25 mm - 1000 ud | C52: 304101 | D52: Caja 1000 ud | E52: 7,00 €/caja | F52: 0,007 €/ud | G52: 15 | H52: ud/m² | I52: 0.1
A53: 3 | B53: Tornillo Cincado Metal-Metal PB Ø3,5x9,5 mm - 1000 ud | C53: 304134 | D53: Caja 1000 ud | E53: 7,19 €/caja | F53: 0,007 €/ud | G53: 3 | H53: ud/m² | I53: 0.02
A54: 4 | B54: Fassajoint 1H - Saco 10 kg | C54: 351E1 | D54: Saco 10 kg | E54: 6,63 €/saco | F54: 0,663 €/kg | G54: 0.35 | H54: kg/m² | I54: 0.23
A55: 5 | B55: Cinta de Juntas 50 mm - Rollo 150 ml | C55: 304058 | D55: Rollo 150 ml | E55: 4,19 €/rollo | F55: 0,028 €/ml | G55: 1.1 | H55: ml/m² | I55: 0.03
A56: 5 | B56: Banda Estanca Monoadhesiva 50 mm - Rollo 30 ml | C56: 304075 | D56: Rollo 30 ml | E56: 5,79 €/rollo | F56: 0,193 €/ml | G56: 1.72 | H56: ml/m² | I56: 0.33
A57: 2 | I57: 0.17
A58: TOTAL COSTE MATERIAL / m² sistema | I58: 6.71 €
A61: SISTEMA 4B — TRASDOSADO AQUA H2 | Mont.48 + Rail 48 · AQUA H2 BA 12,5 mm - 1200x2500 · Sep. 600 mm
A62: 2 | B62: Montante 48/35 Z1 - 2990 mm | C62: C344836299A | D62: Barra 2990 mm | E62: 2,09 €/barra | F62: 0,700 €/ml | G62: 1.67 | H62: ml/m² | I62: 1.17
A63: 2 | B63: Rail 48 Z1 - 3000 mm | C63: U304830300A | D63: Barra 3000 mm | E63: 1,77 €/barra | F63: 0,590 €/ml | G63: 0.95 | H63: ml/m² | I63: 0.56
A64: 1 | B64: Gypsotech AQUA H2 BA 12,5 mm - 1200x2500 | C64: P00H003250A0 | D64: Palé 48 ud / 144 m² | E64: 3,35 €/m² | F64: 3,355 €/m² | G64: 1.05 | H64: m²/m² | I64: 3.52
A65: 3 | B65: Tornillo Fosfatado PM PC Ø3,5x25 mm - 1000 ud | C65: 304101 | D65: Caja 1000 ud | E65: 7,00 €/caja | F65: 0,007 €/ud | G65: 15 | H65: ud/m² | I65: 0.1
A66: 3 | B66: Tornillo Cincado Metal-Metal PB Ø3,5x9,5 mm - 1000 ud | C66: 304134 | D66: Caja 1000 ud | E66: 7,19 €/caja | F66: 0,007 €/ud | G66: 3 | H66: ud/m² | I66: 0.02
A67: 4 | B67: Fassajoint 1H - Saco 10 kg | C67: 351E1 | D67: Saco 10 kg | E67: 6,63 €/saco | F67: 0,663 €/kg | G67: 0.35 | H67: kg/m² | I67: 0.23
A68: 5 | B68: Cinta de Juntas 50 mm - Rollo 150 ml | C68: 304058 | D68: Rollo 150 ml | E68: 4,19 €/rollo | F68: 0,028 €/ml | G68: 1.1 | H68: ml/m² | I68: 0.03
A69: 5 | I69: 0.33
A70: 2 | B70: Perfil Angular Z1 23x34 - 3000 mm | C70: L2334300A | D70: Barra 3000 mm | E70: 1,26 €/barra | F70: 0,420 €/ml | G70: 0.4 | H70: ml/m² | I70: 0.17
A71: TOTAL COSTE MATERIAL / m² sistema | I71: 6.13 €
A74: SISTEMA 5A — MURO SENCILLO STD | Mont.70 + Rail 70 · STD BA 12,5 mm - 1200x2500 · Sep. 400 mm
A75: 2 | B75: Montante 70/37 Z1 - 2990 mm | C75: C367038299A | D75: Barra 2990 mm | E75: 2,67 €/barra | F75: 0,890 €/ml | G75: 2.5 | H75: ml/m² | I75: 2.23
A76: 2 | B76: Rail 70 Z1 - 3000 mm | C76: U307030300A | D76: Barra 3000 mm | E76: 2,15 €/barra | F76: 0,715 €/ml | G76: 0.95 | H76: ml/m² | I76: 0.68
A77: 1 | B77: Gypsotech STD BA 12,5 mm - 1200x2500 | C77: P00A003250A0 | D77: Palé 48 ud / 144 m² | E77: 2,02 €/m² | F77: 2,015 €/m² | G77: 2.1 | H77: m²/m² | I77: 4.23
A78: 3 | B78: Tornillo Fosfatado PM PC Ø3,5x25 mm - 1000 ud | C78: 304101 | D78: Caja 1000 ud | E78: 7,00 €/caja | F78: 0,007 €/ud | G78: 30 | H78: ud/m² | I78: 0.21
A79: 3 | B79: Tornillo Cincado Metal-Metal PB Ø3,5x9,5 mm - 1000 ud | C79: 304134 | D79: Caja 1000 ud | E79: 7,19 €/caja | F79: 0,007 €/ud | G79: 3 | H79: ud/m² | I79: 0.02
A80: 4 | B80: Fassajoint 1H - Saco 10 kg | C80: 351E1 | D80: Saco 10 kg | E80: 6,63 €/saco | F80: 0,663 €/kg | G80: 0.7 | H80: kg/m² | I80: 0.46
A81: 5 | I81: 0.06
A82: 5 | B82: Banda Estanca Monoadhesiva 70 mm - Rollo 30 ml | C82: 304076 | D82: Rollo 30 ml | E82: 8,71 €/rollo | F82: 0,290 €/ml | G82: 1.72 | H82: ml/m² | I82: 0.5
A83: 2 | B83: Perfil Angular Z1 23x34 - 3000 mm | C83: L2334300A | D83: Barra 3000 mm | E83: 1,26 €/barra | F83: 0,420 €/ml | G83: 0.4 | H83: ml/m² | I83: 0.17
A84: TOTAL COSTE MATERIAL / m² sistema
A87: SISTEMA 5B — MURO SENCILLO STD | Mont.70 + Rail 70 · STD BA 12,5 mm - 1200x2500 · Sep. 600 mm
A88: 2 | B88: Montante 70/37 Z1 - 2990 mm | C88: C367038299A | D88: Barra 2990 mm | E88: 2,67 €/barra | F88: 0,890 €/ml | G88: 1.67 | H88: ml/m² | I88: 1.49
A89: 2 | B89: Rail 70 Z1 - 3000 mm | C89: U307030300A | D89: Barra 3000 mm | E89: 2,15 €/barra | F89: 0,715 €/ml | G89: 0.95 | H89: ml/m² | I89: 0.68
A90: 1 | B90: Gypsotech STD BA 12,5 mm - 1200x2500 | C90: P00A003250A0 | D90: Palé 48 ud / 144 m² | E90: 2,02 €/m² | F90: 2,015 €/m² | G90: 2.1 | H90: m²/m² | I90: 4.23
A91: 3 | B91: Tornillo Fosfatado PM PC Ø3,5x25 mm - 1000 ud | C91: 304101 | D91: Caja 1000 ud | E91: 7,00 €/caja | F91: 0,007 €/ud | G91: 30 | H91: ud/m² | I91: 0.21
A92: 3 | B92: Tornillo Cincado Metal-Metal PB Ø3,5x9,5 mm - 1000 ud | C92: 304134 | D92: Caja 1000 ud | E92: 7,19 €/caja | F92: 0,007 €/ud | G92: 3 | H92: ud/m² | I92: 0.02
A93: 4 | I93: 0.46
A94: 5 | B94: Cinta de Juntas 50 mm - Rollo 150 ml | C94: 304058 | D94: Rollo 150 ml | E94: 4,19 €/rollo | F94: 0,028 €/ml | G94: 2.2 | H94: ml/m² | I94: 0.06
A95: 5 | B95: Banda Estanca Monoadhesiva 70 mm - Rollo 30 ml | C95: 304076 | D95: Rollo 30 ml | E95: 8,71 €/rollo | F95: 0,290 €/ml | G95: 1.72 | H95: ml/m² | I95: 0.5
A96: 2
A97: TOTAL COSTE MATERIAL / m² sistema | I97: 7.82 €
A100: SISTEMA 6A — MURO SENCILLO AQUA H2 | Mont.70 + Rail 70 · AQUA H2 BA 12,5 mm - 1200x2500 · Sep. 400 mm
A101: 2 | B101: Montante 70/37 Z1 - 2990 mm | C101: C367038299A | D101: Barra 2990 mm | E101: 2,67 €/barra | F101: 0,890 €/ml | G101: 2.5 | H101: ml/m² | I101: 2.23
A102: 2 | B102: Rail 70 Z1 - 3000 mm | C102: U307030300A | D102: Barra 3000 mm | E102: 2,15 €/barra | F102: 0,715 €/ml | G102: 0.95 | H102: ml/m² | I102: 0.68
A103: 1 | B103: Gypsotech AQUA H2 BA 12,5 mm - 1200x2500 | C103: P00H003250A0 | D103: Palé 48 ud / 144 m² | E103: 3,35 €/m² | F103: 3,355 €/m² | G103: 2.1 | H103: m²/m² | I103: 7.05
A104: 3 | B104: Tornillo Fosfatado PM PC Ø3,5x25 mm - 1000 ud | C104: 304101 | D104: Caja 1000 ud | E104: 7,00 €/caja | F104: 0,007 €/ud | G104: 30 | H104: ud/m² | I104: 0.21
A105: 3 | I105: 0.02
A106: 4 | B106: Fassajoint 1H - Saco 10 kg | C106: 351E1 | D106: Saco 10 kg | E106: 6,63 €/saco | F106: 0,663 €/kg | G106: 0.7 | H106: kg/m² | I106: 0.46
A107: 5 | B107: Cinta de Juntas 50 mm - Rollo 150 ml | C107: 304058 | D107: Rollo 150 ml | E107: 4,19 €/rollo | F107: 0,028 €/ml | G107: 2.2 | H107: ml/m² | I107: 0.06
A108: 5
A109: 2 | B109: Perfil Angular Z1 23x34 - 3000 mm | C109: L2334300A | D109: Barra 3000 mm | E109: 1,26 €/barra | F109: 0,420 €/ml | G109: 0.4 | H109: ml/m² | I109: 0.17
A110: TOTAL COSTE MATERIAL / m² sistema | I110: 11.38 €
A113: SISTEMA 6B — MURO SENCILLO AQUA H2 | Mont.70 + Rail 70 · AQUA H2 BA 12,5 mm - 1200x2500 · Sep. 600 mm
A114: 2 | B114: Montante 70/37 Z1 - 2990 mm | C114: C367038299A | D114: Barra 2990 mm | E114: 2,67 €/barra | F114: 0,890 €/ml | G114: 1.67 | H114: ml/m² | I114: 1.49
A115: 2 | B115: Rail 70 Z1 - 3000 mm | C115: U307030300A | D115: Barra 3000 mm | E115: 2,15 €/barra | F115: 0,715 €/ml | G115: 0.95 | H115: ml/m² | I115: 0.68
A116: 1 | B116: Gypsotech AQUA H2 BA 12,5 mm - 1200x2500 | C116: P00H003250A0 | D116: Palé 48 ud / 144 m² | E116: 3,35 €/m² | F116: 3,355 €/m² | G116: 2.1 | H116: m²/m² | I116: 7.05
A117: 3 | I117: 0.21
A118: 3 | B118: Tornillo Cincado Metal-Metal PB Ø3,5x9,5 mm - 1000 ud | C118: 304134 | D118: Caja 1000 ud | E118: 7,19 €/caja | F118: 0,007 €/ud | G118: 3 | H118: ud/m² | I118: 0.02
...

Sheet INPUT_SYSTEM
A1: Cliente | B1: Francisco Flores
A2: Proyecto | B2: Palmira
A3: SRL | B3: xxxxxx
A4: Responsable | B4: Ana Mar Pérez
A5: Fecha | B5: 46120.802
A6: N_COTIZACION
A7: Incoterm | B7: =CONFIG!B7
A8: Condiciones_Pago
A9: Validez (días) | B9: =CONFIG!B6
A10: Plazo Entrega (semanas)
A11: Moneda | B11: =CONFIG!B8
A12: AREA_TOTAL_REFERENCIAL_M2 | B12: 100
A13: Observaciones_Generales
A15: ITEM | B15: GRUPO_COMPOSICION | C15: INCLUIR | D15: SKU_FASSA | E15: FAMILIA | F15: NOMBRE_PRODUCTO | G15: AREA_APLICADA_M2 | H15: RENDIMIENTO_APLICADO | I15: UNIDAD_RENDIMIENTO | J15: MERMA_% | K15: FACTOR_AJUSTE | L15: CANTIDAD_MANUAL_OVERRIDE | M15: MARGEN_%_APLICADO | N15: OBSERVACION_ITEM
A16: 1 | B16: Placa | C16: SI | D16: C344836299B | E16: {=IFERROR(INDEX(PRODUCT!$A:$A,MATCH(D16,PRODUCT!$B:$B,0)),"")} | F16: {=IFERROR(INDEX(PRODUCT!$C:$C,MATCH(D16,PRODUCT!$B:$B,0)),"")} | G16: =$B$12 | H16: {=IFERROR(INDEX(PRODUCT!$L:$L,MATCH(D16,PRODUCT!$B:$B,0)),"")} | I16: {=IFERROR(INDEX(PRODUCT!$M:$M,MATCH(D16,PRODUCT!$B:$B,0)),"")} | J16: 0.05 | K16: 1 | L16: 105 | M16: =CONFIG!$B$4 | N16: Base muro seco
A17: 2 | B17: Perfilería | C17: SI | D17: C344836299B | E17: {=IFERROR(INDEX(PRODUCT!$A:$A,MATCH(D17,PRODUCT!$B:$B,0)),"")} | F17: {=IFERROR(INDEX(PRODUCT!$C:$C,MATCH(D17,PRODUCT!$B:$B,0)),"")} | G17: =$B$12 | H17: {=IFERROR(INDEX(PRODUCT!$L:$L,MATCH(D17,PRODUCT!$B:$B,0)),"")} | I17: {=IFERROR(INDEX(PRODUCT!$M:$M,MATCH(D17,PRODUCT!$B:$B,0)),"")} | J17: 0.05 | K17: 1 | L17: 105 | M17: =CONFIG!$B$4 | N17: Editable según cliente
A18: 3 | B18: Perfilería | C18: SI | D18: U307030300A | E18: {=IFERROR(INDEX(PRODUCT!$A:$A,MATCH(D18,PRODUCT!$B:$B,0)),"")} | F18: {=IFERROR(INDEX(PRODUCT!$C:$C,MATCH(D18,PRODUCT!$B:$B,0)),"")} | G18: =$B$12 | H18: {=IFERROR(INDEX(PRODUCT!$L:$L,MATCH(D18,PRODUCT!$B:$B,0)),"")} | I18: {=IFERROR(INDEX(PRODUCT!$M:$M,MATCH(D18,PRODUCT!$B:$B,0)),"")} | J18: 0.05 | K18: 1 | L18: 105 | M18: =CONFIG!$B$4 | N18: Editable según cliente
A19: 4 | B19: Accesorio | C19: SI | D19: 304058 | E19: {=IFERROR(INDEX(PRODUCT!$A:$A,MATCH(D19,PRODUCT!$B:$B,0)),"")} | F19: {=IFERROR(INDEX(PRODUCT!$C:$C,MATCH(D19,PRODUCT!$B:$B,0)),"")} | G19: =$B$12 | H19: {=IFERROR(INDEX(PRODUCT!$L:$L,MATCH(D19,PRODUCT!$B:$B,0)),"")} | I19: {=IFERROR(INDEX(PRODUCT!$M:$M,MATCH(D19,PRODUCT!$B:$B,0)),"")} | J19: 0.05 | K19: 1 | L19: 105 | M19: =CONFIG!$B$4 | N19: Juntas
A20: 5 | B20: Masillas | C20: SI | D20: 351E1 | E20: {=IFERROR(INDEX(PRODUCT!$A:$A,MATCH(D20,PRODUCT!$B:$B,0)),"")} | F20: {=IFERROR(INDEX(PRODUCT!$C:$C,MATCH(D20,PRODUCT!$B:$B,0)),"")} | G20: =$B$12 | H20: {=IFERROR(INDEX(PRODUCT!$L:$L,MATCH(D20,PRODUCT!$B:$B,0)),"")} | I20: {=IFERROR(INDEX(PRODUCT!$M:$M,MATCH(D20,PRODUCT!$B:$B,0)),"")} | J20: 0.05 | K20: 1 | L20: 105 | M20: =CONFIG!$B$4 | N20: Tratamiento juntas
A21: 6 | B21: Accesorio | C21: SI | D21: 304076 | E21: {=IFERROR(INDEX(PRODUCT!$A:$A,MATCH(D21,PRODUCT!$B:$B,0)),"")} | F21: {=IFERROR(INDEX(PRODUCT!$C:$C,MATCH(D21,PRODUCT!$B:$B,0)),"")} | G21: =$B$12 | H21: {=IFERROR(INDEX(PRODUCT!$L:$L,MATCH(D21,PRODUCT!$B:$B,0)),"")} | I21: {=IFERROR(INDEX(PRODUCT!$M:$M,MATCH(D21,PRODUCT!$B:$B,0)),"")} | J21: 0.05 | K21: 1 | L21: 105 | M21: =CONFIG!$B$4 | N21: Perímetro
A22: 7 | B22: Accesorio | C22: SI | D22: 1091001Y | E22: {=IFERROR(INDEX(PRODUCT!$A:$A,MATCH(D22,PRODUCT!$B:$B,0)),"")} | F22: {=IFERROR(INDEX(PRODUCT!$C:$C,MATCH(D22,PRODUCT!$B:$B,0)),"")} | G22: =$B$12 | H22: {=IFERROR(INDEX(PRODUCT!$L:$L,MATCH(D22,PRODUCT!$B:$B,0)),"")} | I22: {=IFERROR(INDEX(PRODUCT!$M:$M,MATCH(D22,PRODUCT!$B:$B,0)),"")} | J22: 0.05 | K22: 1 | L22: 105 | M22: =CONFIG!$B$4 | N22: Esquinas
E23: {=IF($D23="","",xlookup($D23,PRODUCT!$B:$B,PRODUCT!$A:$A,""))} | F23: {=IF($D23="","",xlookup($D23,PRODUCT!$B:$B,PRODUCT!$C:$C,""))} | H23: {=IF($D23="","",xlookup($D23,PRODUCT!$B:$B,PRODUCT!$L:$L,""))} | I23: {=IF($D23="","",xlookup($D23,PRODUCT!$B:$B,PRODUCT!$M:$M,""))}
E24: {=IF($D24="","",xlookup($D24,PRODUCT!$B:$B,PRODUCT!$A:$A,""))} | F24: {=IF($D24="","",xlookup($D24,PRODUCT!$B:$B,PRODUCT!$C:$C,""))} | H24: {=IF($D24="","",xlookup($D24,PRODUCT!$B:$B,PRODUCT!$L:$L,""))} | I24: {=IF($D24="","",xlookup($D24,PRODUCT!$B:$B,PRODUCT!$M:$M,""))}
E25: {=IF($D25="","",xlookup($D25,PRODUCT!$B:$B,PRODUCT!$A:$A,""))} | F25: {=IF($D25="","",xlookup($D25,PRODUCT!$B:$B,PRODUCT!$C:$C,""))} | H25: {=IF($D25="","",xlookup($D25,PRODUCT!$B:$B,PRODUCT!$L:$L,""))} | I25: {=IF($D25="","",xlookup($D25,PRODUCT!$B:$B,PRODUCT!$M:$M,""))}
E26: {=IF($D26="","",xlookup($D26,PRODUCT!$B:$B,PRODUCT!$A:$A,""))} | F26: {=IF($D26="","",xlookup($D26,PRODUCT!$B:$B,PRODUCT!$C:$C,""))} | H26: {=IF($D26="","",xlookup($D26,PRODUCT!$B:$B,PRODUCT!$L:$L,""))} | I26: {=IF($D26="","",xlookup($D26,PRODUCT!$B:$B,PRODUCT!$M:$M,""))}
E27: {=IF($D27="","",xlookup($D27,PRODUCT!$B:$B,PRODUCT!$A:$A,""))} | F27: {=IF($D27="","",xlookup($D27,PRODUCT!$B:$B,PRODUCT!$C:$C,""))} | H27: {=IF($D27="","",xlookup($D27,PRODUCT!$B:$B,PRODUCT!$L:$L,""))} | I27: {=IF($D27="","",xlookup($D27,PRODUCT!$B:$B,PRODUCT!$M:$M,""))}
E28: {=IF($D28="","",xlookup($D28,PRODUCT!$B:$B,PRODUCT!$A:$A,""))} | F28: {=IF($D28="","",xlookup($D28,PRODUCT!$B:$B,PRODUCT!$C:$C,""))} | H28: {=IF($D28="","",xlookup($D28,PRODUCT!$B:$B,PRODUCT!$L:$L,""))} | I28: {=IF($D28="","",xlookup($D28,PRODUCT!$B:$B,PRODUCT!$M:$M,""))}
E29: {=IF($D29="","",xlookup($D29,PRODUCT!$B:$B,PRODUCT!$A:$A,""))} | F29: {=IF($D29="","",xlookup($D29,PRODUCT!$B:$B,PRODUCT!$C:$C,""))} | H29: {=IF($D29="","",xlookup($D29,PRODUCT!$B:$B,PRODUCT!$L:$L,""))} | I29: {=IF($D29="","",xlookup($D29,PRODUCT!$B:$B,PRODUCT!$M:$M,""))}
E30: {=IF($D30="","",xlookup($D30,PRODUCT!$B:$B,PRODUCT!$A:$A,""))} | F30: {=IF($D30="","",xlookup($D30,PRODUCT!$B:$B,PRODUCT!$C:$C,""))} | H30: {=IF($D30="","",xlookup($D30,PRODUCT!$B:$B,PRODUCT!$L:$L,""))} | I30: {=IF($D30="","",xlookup($D30,PRODUCT!$B:$B,PRODUCT!$M:$M,""))}
E31: {=IF($D31="","",xlookup($D31,PRODUCT!$B:$B,PRODUCT!$A:$A,""))} | F31: {=IF($D31="","",xlookup($D31,PRODUCT!$B:$B,PRODUCT!$C:$C,""))} | H31: {=IF($D31="","",xlookup($D31,PRODUCT!$B:$B,PRODUCT!$L:$L,""))} | I31: {=IF($D31="","",xlookup($D31,PRODUCT!$B:$B,PRODUCT!$M:$M,""))}
E32: {=IF($D32="","",xlookup($D32,PRODUCT!$B:$B,PRODUCT!$A:$A,""))} | F32: {=IF($D32="","",xlookup($D32,PRODUCT!$B:$B,PRODUCT!$C:$C,""))} | H32: {=IF($D32="","",xlookup($D32,PRODUCT!$B:$B,PRODUCT!$L:$L,""))} | I32: {=IF($D32="","",xlookup($D32,PRODUCT!$B:$B,PRODUCT!$M:$M,""))}
E33: {=IF($D33="","",xlookup($D33,PRODUCT!$B:$B,PRODUCT!$A:$A,""))} | F33: {=IF($D33="","",xlookup($D33,PRODUCT!$B:$B,PRODUCT!$C:$C,""))} | H33: {=IF($D33="","",xlookup($D33,PRODUCT!$B:$B,PRODUCT!$L:$L,""))} | I33: {=IF($D33="","",xlookup($D33,PRODUCT!$B:$B,PRODUCT!$M:$M,""))}
E34: {=IF($D34="","",xlookup($D34,PRODUCT!$B:$B,PRODUCT!$A:$A,""))} | F34: {=IF($D34="","",xlookup($D34,PRODUCT!$B:$B,PRODUCT!$C:$C,""))} | H34: {=IF($D34="","",xlookup($D34,PRODUCT!$B:$B,PRODUCT!$L:$L,""))} | I34: {=IF($D34="","",xlookup($D34,PRODUCT!$B:$B,PRODUCT!$M:$M,""))}
... E500: {=IF($D500="","",xlookup($D500,PRODUCT!$B:$B,PRODUCT!$A:$A,""))} | F500: {=IF($D500="","",xlookup($D500,PRODUCT!$B:$B,PRODUCT!$C:$C,""))} | H500: {=IF($D500="","",xlookup($D500,PRODUCT!$B:$B,PRODUCT!$L:$L,""))} | I500: {=IF($D500="","",xlookup($D500,PRODUCT!$B:$B,PRODUCT!$M:$M,""))}

Sheet INPUT_PRODUCT
A1: Cliente | B1: Francisco Flores
A2: Proyecto | B2: Palmira
A3: SRL | B3: xxxxxx
A4: Responsable | B4: Ana Mar Pérez
A5: Fecha | B5: 46120.802
A6: N_COTIZACION
A7: Incoterm | B7: =CONFIG!B7
A8: Condiciones_Pago
A9: Validez (días) | B9: =CONFIG!B6
A10: Plazo Entrega (semanas)
A11: Moneda | B11: =CONFIG!B8
A12: AREA_TOTAL_REFERENCIAL_M2 | B12: 100
A13: Observaciones_Generales
A14: ITEM | B14: INCLUIR | C14: SKU_FASSA | D14: FAMILIA | E14: NOMBRE_PRODUCTO | F14: CANTIDAD_BASE | G14: UNIDAD_INPUT | H14: FACTOR_AJUSTE | I14: CANTIDAD_MANUAL_OVERRIDE | J14: CANTIDAD_FINAL_INPUT | K14: MARGEN_%_APLICADO | L14: OBSERVACION_ITEM
A15: 1 | B15: SI | D15: =IF(C15="";"";INDEX(PRODUCT!A:A;MATCH(C15;PRODUCT!B:B;0))) | E15: =IF(C15="";"";VLOOKUP(C15;PRODUCT!B:C;2;FALSE)) | H15: 1 | J15: =IF(I15<>"";I15;F15*H15) | K15: =CONFIG!$B$6
A16: 2 | B16: SI | D16: =IF(C16="";"";INDEX(PRODUCT!A:A;MATCH(C16;PRODUCT!B:B;0))) | E16: =IF(C16="";"";VLOOKUP(C16;PRODUCT!B:C;2;FALSE)) | H16: 1 | J16: =IF(I16<>"";I16;F16*H16) | K16: =CONFIG!$B$6
A17: 3 | B17: SI | D17: =IF(C17="";"";INDEX(PRODUCT!A:A;MATCH(C17;PRODUCT!B:B;0))) | E17: =IF(C17="";"";VLOOKUP(C17;PRODUCT!B:C;2;FALSE)) | H17: 1 | J17: =IF(I17<>"";I17;F17*H17) | K17: =CONFIG!$B$6
A18: 4 | B18: SI | D18: =IF(C18="";"";INDEX(PRODUCT!A:A;MATCH(C18;PRODUCT!B:B;0))) | E18: =IF(C18="";"";VLOOKUP(C18;PRODUCT!B:C;2;FALSE)) | H18: 1 | J18: =IF(I18<>"";I18;F18*H18) | K18: =CONFIG!$B$6
A19: 5 | B19: SI | D19: =IF(C19="";"";INDEX(PRODUCT!A:A;MATCH(C19;PRODUCT!B:B;0))) | E19: =IF(C19="";"";VLOOKUP(C19;PRODUCT!B:C;2;FALSE)) | H19: 1 | J19: =IF(I19<>"";I19;F19*H19) | K19: =CONFIG!$B$6
A20: 6 | B20: SI | D20: =IF(C20="";"";INDEX(PRODUCT!A:A;MATCH(C20;PRODUCT!B:B;0))) | E20: =IF(C20="";"";VLOOKUP(C20;PRODUCT!B:C;2;FALSE)) | H20: 1 | J20: =IF(I20<>"";I20;F20*H20) | K20: =CONFIG!$B$6
A21: 7 | B21: SI | D21: =IF(C21="";"";INDEX(PRODUCT!A:A;MATCH(C21;PRODUCT!B:B;0))) | E21: =IF(C21="";"";VLOOKUP(C21;PRODUCT!B:C;2;FALSE)) | H21: 1 | J21: =IF(I21<>"";I21;F21*H21) | K21: =CONFIG!$B$6
A22: 8 | B22: SI | D22: =IF(C22="";"";INDEX(PRODUCT!A:A;MATCH(C22;PRODUCT!B:B;0))) | E22: =IF(C22="";"";VLOOKUP(C22;PRODUCT!B:C;2;FALSE)) | H22: 1 | J22: =IF(I22<>"";I22;F22*H22) | K22: =CONFIG!$B$6
A23: 9 | B23: SI | D23: =IF(C23="";"";INDEX(PRODUCT!A:A;MATCH(C23;PRODUCT!B:B;0))) | E23: =IF(C23="";"";VLOOKUP(C23;PRODUCT!B:C;2;FALSE)) | H23: 1 | J23: =IF(I23<>"";I23;F23*H23) | K23: =CONFIG!$B$6
A24: 10 | B24: SI | D24: =IF(C24="";"";INDEX(PRODUCT!A:A;MATCH(C24;PRODUCT!B:B;0))) | E24: =IF(C24="";"";VLOOKUP(C24;PRODUCT!B:C;2;FALSE)) | H24: 1 | J24: =IF(I24<>"";I24;F24*H24) | K24: =CONFIG!$B$6
A25: 11 | B25: SI | D25: =IF(C25="";"";INDEX(PRODUCT!A:A;MATCH(C25;PRODUCT!B:B;0))) | E25: =IF(C25="";"";VLOOKUP(C25;PRODUCT!B:C;2;FALSE)) | H25: 1 | J25: =IF(I25<>"";I25;F25*H25) | K25: =CONFIG!$B$6
A26: 12 | B26: SI | D26: =IF(C26="";"";INDEX(PRODUCT!A:A;MATCH(C26;PRODUCT!B:B;0))) | E26: =IF(C26="";"";VLOOKUP(C26;PRODUCT!B:C;2;FALSE)) | H26: 1 | J26: =IF(I26<>"";I26;F26*H26) | K26: =CONFIG!$B$6
... A200: 186 | B200: SI | D200: =IF(C200="";"";INDEX(PRODUCT!A:A;MATCH(C200;PRODUCT!B:B;0))) | E200: =IF(C200="";"";VLOOKUP(C200;PRODUCT!B:C;2;FALSE)) | H200: 1 | J200: =IF(I200<>"";I200;F200*H200) | K200: =CONFIG!$B$6

Sheet SYSTEM_CALCULATION
A1: ITEM | B1: GRUPO_COMPOSICION | C1: SKU_FASSA | D1: FAMILIA | E1: NOMBRE_PRODUCTO | F1: UNIDAD_PRECIO | G1: UDS_POR_PALE | H1: M2_POR_PALE_O_EQUIVALENTE | I1: AREA_APLICADA_M2 | J1: RENDIMIENTO_APLICADO | K1: MERMA_% | L1: FACTOR_AJUSTE | M1: CANTIDAD_MANUAL_OVERRIDE | N1: CANTIDAD_TECNICA | O1: UNIDADES_SUMINISTRO | P1: PRECIO_BASE_ARIAS_EUR | Q1: MARGEN_%_APLICADO | R1: PRECIO_UNITARIO_CLIENTE_EUR | S1: SUBTOTAL_INTERNO_EUR | T1: SUBTOTAL_CLIENTE_EUR | U1: INCLUIR | V1: OBSERVACION_ITEM
A2: =INPUT_SYSTEM!A2 | B2: =INPUT_SYSTEM!B2 | C2: =INPUT_SYSTEM!D2 | D2: {=IFERROR(XLOOKUP($C2,PRODUCT!B:B,PRODUCT!A:A),"")} | E2: =IF(C2="","",INPUT_SYSTEM!F16) | F2: {=IFERROR(INDEX(PRODUCT!$D:$D,MATCH(C2,PRODUCT!$B:$B,0)),"")} | G2: {=IFERROR(INDEX(PRODUCT!$E:$E,MATCH(C2,PRODUCT!$B:$B,0)),"")} | H2: {=IFERROR(INDEX(PRODUCT!$F:$F,MATCH(C2,PRODUCT!$B:$B,0)),"")} | I2: =IF(C2="","",INPUT_SYSTEM!G16) | J2: =IF(C2="","",INPUT_SYSTEM!H16) | K2: =IF(C2="","",INPUT_SYSTEM!J16) | L2: =IF(C2="","",INPUT_SYSTEM!K16) | M2: =IF(C2="","",INPUT_SYSTEM!L16) | N2: =IF(U2<>"SI","",IF(M2<>"",M2,IFERROR(I2*J2*(1+K2)*L2,""))) | O2: =IF(N2="","",IF(OR(H2="",H2=0),N2,ROUNDUP(N2/H2,0))) | P2: {=IFERROR(INDEX(PRODUCT!$I:$I,MATCH(C2,PRODUCT!$B:$B,0)),"")} | Q2: =IF(C2="","",INPUT_SYSTEM!M16) | R2: =IF(P2="","",P2*(1+Q2)) | S2: =IF(O2="","",IF(OR(H2="",H2=0),O2*P2,O2*H2*P2)) | T2: =IF(O2="","",IF(OR(H2="",H2=0),O2*R2,O2*H2*R2)) | U2: =IF(C2="","",INPUT_SYSTEM!C16) | V2: =IF(C2="","",INPUT_SYSTEM!N16)
A3: =IF(INPUT_SYSTEM!D17="","",INPUT_SYSTEM!A17) | B3: =IF(INPUT_SYSTEM!D17="","",INPUT_SYSTEM!B17) | C3: =IF(INPUT_SYSTEM!D17="","",INPUT_SYSTEM!D17) | D3: =IF(C3="","",INPUT_SYSTEM!E17) | E3: =IF(C3="","",INPUT_SYSTEM!F17) | F3: {=IFERROR(INDEX(PRODUCT!$D:$D,MATCH(C3,PRODUCT!$B:$B,0)),"")} | G3: {=IFERROR(INDEX(PRODUCT!$E:$E,MATCH(C3,PRODUCT!$B:$B,0)),"")} | H3: {=IFERROR(INDEX(PRODUCT!$F:$F,MATCH(C3,PRODUCT!$B:$B,0)),"")} | I3: =IF(C3="","",INPUT_SYSTEM!G17) | J3: =IF(C3="","",INPUT_SYSTEM!H17) | K3: =IF(C3="","",INPUT_SYSTEM!J17) | L3: =IF(C3="","",INPUT_SYSTEM!K17) | M3: =IF(C3="","",INPUT_SYSTEM!L17) | N3: =IF(U3<>"SI","",IF(M3<>"",M3,IFERROR(I3*J3*(1+K3)*L3,""))) | O3: =IF(N3="","",IF(OR(H3="",H3=0),N3,ROUNDUP(N3/H3,0))) | P3: {=IFERROR(INDEX(PRODUCT!$I:$I,MATCH(C3,PRODUCT!$B:$B,0)),"")} | Q3: =IF(C3="","",INPUT_SYSTEM!M17) | R3: =IF(P3="","",P3*(1+Q3)) | S3: =IF(O3="","",IF(OR(H3="",H3=0),O3*P3,O3*H3*P3)) | T3: =IF(O3="","",IF(OR(H3="",H3=0),O3*R3,O3*H3*R3)) | U3: =IF(C3="","",INPUT_SYSTEM!C17) | V3: =IF(C3="","",INPUT_SYSTEM!N17)
A4: =IF(INPUT_SYSTEM!D18="","",INPUT_SYSTEM!A18) | B4: =IF(INPUT_SYSTEM!D18="","",INPUT_SYSTEM!B18) | C4: =IF(INPUT_SYSTEM!D18="","",INPUT_SYSTEM!D18) | D4: =IF(C4="","",INPUT_SYSTEM!E18) | E4: =IF(C4="","",INPUT_SYSTEM!F18) | F4: {=IFERROR(INDEX(PRODUCT!$D:$D,MATCH(C4,PRODUCT!$B:$B,0)),"")} | G4: {=IFERROR(INDEX(PRODUCT!$E:$E,MATCH(C4,PRODUCT!$B:$B,0)),"")} | H4: {=IFERROR(INDEX(PRODUCT!$F:$F,MATCH(C4,PRODUCT!$B:$B,0)),"")} | I4: =IF(C4="","",INPUT_SYSTEM!G18) | J4: =IF(C4="","",INPUT_SYSTEM!H18) | K4: =IF(C4="","",INPUT_SYSTEM!J18) | L4: =IF(C4="","",INPUT_SYSTEM!K18) | M4: =IF(C4="","",INPUT_SYSTEM!L18) | N4: =IF(U4<>"SI","",IF(M4<>"",M4,IFERROR(I4*J4*(1+K4)*L4,""))) | O4: =IF(N4="","",IF(OR(H4="",H4=0),N4,ROUNDUP(N4/H4,0))) | P4: {=IFERROR(INDEX(PRODUCT!$I:$I,MATCH(C4,PRODUCT!$B:$B,0)),"")} | Q4: =IF(C4="","",INPUT_SYSTEM!M18) | R4: =IF(P4="","",P4*(1+Q4)) | S4: =IF(O4="","",IF(OR(H4="",H4=0),O4*P4,O4*H4*P4)) | T4: =IF(O4="","",IF(OR(H4="",H4=0),O4*R4,O4*H4*R4)) | U4: =IF(C4="","",INPUT_SYSTEM!C18) | V4: =IF(C4="","",INPUT_SYSTEM!N18)
A5: =IF(INPUT_SYSTEM!D19="","",INPUT_SYSTEM!A19) | B5: =IF(INPUT_SYSTEM!D19="","",INPUT_SYSTEM!B19) | C5: =IF(INPUT_SYSTEM!D19="","",INPUT_SYSTEM!D19) | D5: =IF(C5="","",INPUT_SYSTEM!E19) | E5: =IF(C5="","",INPUT_SYSTEM!F19) | F5: {=IFERROR(INDEX(PRODUCT!$D:$D,MATCH(C5,PRODUCT!$B:$B,0)),"")} | G5: {=IFERROR(INDEX(PRODUCT!$E:$E,MATCH(C5,PRODUCT!$B:$B,0)),"")} | H5: {=IFERROR(INDEX(PRODUCT!$F:$F,MATCH(C5,PRODUCT!$B:$B,0)),"")} | I5: =IF(C5="","",INPUT_SYSTEM!G19) | J5: =IF(C5="","",INPUT_SYSTEM!H19) | K5: =IF(C5="","",INPUT_SYSTEM!J19) | L5: =IF(C5="","",INPUT_SYSTEM!K19) | M5: =IF(C5="","",INPUT_SYSTEM!L19) | N5: =IF(U5<>"SI","",IF(M5<>"",M5,IFERROR(I5*J5*(1+K5)*L5,""))) | O5: =IF(N5="","",IF(OR(H5="",H5=0),N5,ROUNDUP(N5/H5,0))) | P5: {=IFERROR(INDEX(PRODUCT!$I:$I,MATCH(C5,PRODUCT!$B:$B,0)),"")} | Q5: =IF(C5="","",INPUT_SYSTEM!M19) | R5: =IF(P5="","",P5*(1+Q5)) | S5: =IF(O5="","",IF(OR(H5="",H5=0),O5*P5,O5*H5*P5)) | T5: =IF(O5="","",IF(OR(H5="",H5=0),O5*R5,O5*H5*R5)) | U5: =IF(C5="","",INPUT_SYSTEM!C19) | V5: =IF(C5="","",INPUT_SYSTEM!N19)
A6: =IF(INPUT_SYSTEM!D20="","",INPUT_SYSTEM!A20) | B6: =IF(INPUT_SYSTEM!D20="","",INPUT_SYSTEM!B20) | C6: =IF(INPUT_SYSTEM!D20="","",INPUT_SYSTEM!D20) | D6: =IF(C6="","",INPUT_SYSTEM!E20) | E6: =IF(C6="","",INPUT_SYSTEM!F20) | F6: {=IFERROR(INDEX(PRODUCT!$D:$D,MATCH(C6,PRODUCT!$B:$B,0)),"")} | G6: {=IFERROR(INDEX(PRODUCT!$E:$E,MATCH(C6,PRODUCT!$B:$B,0)),"")} | H6: {=IFERROR(INDEX(PRODUCT!$F:$F,MATCH(C6,PRODUCT!$B:$B,0)),"")} | I6: =IF(C6="","",INPUT_SYSTEM!G20) | J6: =IF(C6="","",INPUT_SYSTEM!H20) | K6: =IF(C6="","",INPUT_SYSTEM!J20) | L6: =IF(C6="","",INPUT_SYSTEM!K20) | M6: =IF(C6="","",INPUT_SYSTEM!L20) | N6: =IF(U6<>"SI","",IF(M6<>"",M6,IFERROR(I6*J6*(1+K6)*L6,""))) | O6: =IF(N6="","",IF(OR(H6="",H6=0),N6,ROUNDUP(N6/H6,0))) | P6: {=IFERROR(INDEX(PRODUCT!$I:$I,MATCH(C6,PRODUCT!$B:$B,0)),"")} | Q6: =IF(C6="","",INPUT_SYSTEM!M20) | R6: =IF(P6="","",P6*(1+Q6)) | S6: =IF(O6="","",IF(OR(H6="",H6=0),O6*P6,O6*H6*P6)) | T6: =IF(O6="","",IF(OR(H6="",H6=0),O6*R6,O6*H6*R6)) | U6: =IF(C6="","",INPUT_SYSTEM!C20) | V6: =IF(C6="","",INPUT_SYSTEM!N20)
A7: =IF(INPUT_SYSTEM!D21="","",INPUT_SYSTEM!A21) | B7: =IF(INPUT_SYSTEM!D21="","",INPUT_SYSTEM!B21) | C7: =IF(INPUT_SYSTEM!D21="","",INPUT_SYSTEM!D21) | D7: =IF(C7="","",INPUT_SYSTEM!E21) | E7: =IF(C7="","",INPUT_SYSTEM!F21) | F7: {=IFERROR(INDEX(PRODUCT!$D:$D,MATCH(C7,PRODUCT!$B:$B,0)),"")} | G7: {=IFERROR(INDEX(PRODUCT!$E:$E,MATCH(C7,PRODUCT!$B:$B,0)),"")} | H7: {=IFERROR(INDEX(PRODUCT!$F:$F,MATCH(C7,PRODUCT!$B:$B,0)),"")} | I7: =IF(C7="","",INPUT_SYSTEM!G21) | J7: =IF(C7="","",INPUT_SYSTEM!H21) | K7: =IF(C7="","",INPUT_SYSTEM!J21) | L7: =IF(C7="","",INPUT_SYSTEM!K21) | M7: =IF(C7="","",INPUT_SYSTEM!L21) | N7: =IF(U7<>"SI","",IF(M7<>"",M7,IFERROR(I7*J7*(1+K7)*L7,""))) | O7: =IF(N7="","",IF(OR(H7="",H7=0),N7,ROUNDUP(N7/H7,0))) | P7: {=IFERROR(INDEX(PRODUCT!$I:$I,MATCH(C7,PRODUCT!$B:$B,0)),"")} | Q7: =IF(C7="","",INPUT_SYSTEM!M21) | R7: =IF(P7="","",P7*(1+Q7)) | S7: =IF(O7="","",IF(OR(H7="",H7=0),O7*P7,O7*H7*P7)) | T7: =IF(O7="","",IF(OR(H7="",H7=0),O7*R7,O7*H7*R7)) | U7: =IF(C7="","",INPUT_SYSTEM!C21) | V7: =IF(C7="","",INPUT_SYSTEM!N21)
A8: =IF(INPUT_SYSTEM!D22="","",INPUT_SYSTEM!A22) | B8: =IF(INPUT_SYSTEM!D22="","",INPUT_SYSTEM!B22) | C8: =IF(INPUT_SYSTEM!D22="","",INPUT_SYSTEM!D22) | D8: =IF(C8="","",INPUT_SYSTEM!E22) | E8: =IF(C8="","",INPUT_SYSTEM!F22) | F8: {=IFERROR(INDEX(PRODUCT!$D:$D,MATCH(C8,PRODUCT!$B:$B,0)),"")} | G8: {=IFERROR(INDEX(PRODUCT!$E:$E,MATCH(C8,PRODUCT!$B:$B,0)),"")} | H8: {=IFERROR(INDEX(PRODUCT!$F:$F,MATCH(C8,PRODUCT!$B:$B,0)),"")} | I8: =IF(C8="","",INPUT_SYSTEM!G22) | J8: =IF(C8="","",INPUT_SYSTEM!H22) | K8: =IF(C8="","",INPUT_SYSTEM!J22) | L8: =IF(C8="","",INPUT_SYSTEM!K22) | M8: =IF(C8="","",INPUT_SYSTEM!L22) | N8: =IF(U8<>"SI","",IF(M8<>"",M8,IFERROR(I8*J8*(1+K8)*L8,""))) | O8: =IF(N8="","",IF(OR(H8="",H8=0),N8,ROUNDUP(N8/H8,0))) | P8: {=IFERROR(INDEX(PRODUCT!$I:$I,MATCH(C8,PRODUCT!$B:$B,0)),"")} | Q8: =IF(C8="","",INPUT_SYSTEM!M22) | R8: =IF(P8="","",P8*(1+Q8)) | S8: =IF(O8="","",IF(OR(H8="",H8=0),O8*P8,O8*H8*P8)) | T8: =IF(O8="","",IF(OR(H8="",H8=0),O8*R8,O8*H8*R8)) | U8: =IF(C8="","",INPUT_SYSTEM!C22) | V8: =IF(C8="","",INPUT_SYSTEM!N22)
A9: =IF(INPUT_SYSTEM!D23="","",INPUT_SYSTEM!A23) | B9: =IF(INPUT_SYSTEM!D23="","",INPUT_SYSTEM!B23) | C9: =IF(INPUT_SYSTEM!D23="","",INPUT_SYSTEM!D23) | D9: =IF(C9="","",INPUT_SYSTEM!E23) | E9: =IF(C9="","",INPUT_SYSTEM!F23) | F9: {=IFERROR(INDEX(PRODUCT!$D:$D,MATCH(C9,PRODUCT!$B:$B,0)),"")} | G9: {=IFERROR(INDEX(PRODUCT!$E:$E,MATCH(C9,PRODUCT!$B:$B,0)),"")} | H9: {=IFERROR(INDEX(PRODUCT!$F:$F,MATCH(C9,PRODUCT!$B:$B,0)),"")} | I9: =IF(C9="","",INPUT_SYSTEM!G23) | J9: =IF(C9="","",INPUT_SYSTEM!H23) | K9: =IF(C9="","",INPUT_SYSTEM!J23) | L9: =IF(C9="","",INPUT_SYSTEM!K23) | M9: =IF(C9="","",INPUT_SYSTEM!L23) | N9: =IF(U9<>"SI","",IF(M9<>"",M9,IFERROR(I9*J9*(1+K9)*L9,""))) | O9: =IF(N9="","",IF(OR(H9="",H9=0),N9,ROUNDUP(N9/H9,0))) | P9: {=IFERROR(INDEX(PRODUCT!$I:$I,MATCH(C9,PRODUCT!$B:$B,0)),"")} | Q9: =IF(C9="","",INPUT_SYSTEM!M23) | R9: =IF(P9="","",P9*(1+Q9)) | S9: =IF(O9="","",IF(OR(H9="",H9=0),O9*P9,O9*H9*P9)) | T9: =IF(O9="","",IF(OR(H9="",H9=0),O9*R9,O9*H9*R9)) | U9: =IF(C9="","",INPUT_SYSTEM!C23) | V9: =IF(C9="","",INPUT_SYSTEM!N23)
A10: =IF(INPUT_SYSTEM!D24="","",INPUT_SYSTEM!A24) | B10: =IF(INPUT_SYSTEM!D24="","",INPUT_SYSTEM!B24) | C10: =IF(INPUT_SYSTEM!D24="","",INPUT_SYSTEM!D24) | D10: =IF(C10="","",INPUT_SYSTEM!E24) | E10: =IF(C10="","",INPUT_SYSTEM!F24) | F10: {=IFERROR(INDEX(PRODUCT!$D:$D,MATCH(C10,PRODUCT!$B:$B,0)),"")} | G10: {=IFERROR(INDEX(PRODUCT!$E:$E,MATCH(C10,PRODUCT!$B:$B,0)),"")} | H10: {=IFERROR(INDEX(PRODUCT!$F:$F,MATCH(C10,PRODUCT!$B:$B,0)),"")} | I10: =IF(C10="","",INPUT_SYSTEM!G24) | J10: =IF(C10="","",INPUT_SYSTEM!H24) | K10: =IF(C10="","",INPUT_SYSTEM!J24) | L10: =IF(C10="","",INPUT_SYSTEM!K24) | M10: =IF(C10="","",INPUT_SYSTEM!L24) | N10: =IF(U10<>"SI","",IF(M10<>"",M10,IFERROR(I10*J10*(1+K10)*L10,""))) | O10: =IF(N10="","",IF(OR(H10="",H10=0),N10,ROUNDUP(N10/H10,0))) | P10: {=IFERROR(INDEX(PRODUCT!$I:$I,MATCH(C10,PRODUCT!$B:$B,0)),"")} | Q10: =IF(C10="","",INPUT_SYSTEM!M24) | R10: =IF(P10="","",P10*(1+Q10)) | S10: =IF(O10="","",IF(OR(H10="",H10=0),O10*P10,O10*H10*P10)) | T10: =IF(O10="","",IF(OR(H10="",H10=0),O10*R10,O10*H10*R10)) | U10: =IF(C10="","",INPUT_SYSTEM!C24) | V10: =IF(C10="","",INPUT_SYSTEM!N24)
A11: =IF(INPUT_SYSTEM!D25="","",INPUT_SYSTEM!A25) | B11: =IF(INPUT_SYSTEM!D25="","",INPUT_SYSTEM!B25) | C11: =IF(INPUT_SYSTEM!D25="","",INPUT_SYSTEM!D25) | D11: =IF(C11="","",INPUT_SYSTEM!E25) | E11: =IF(C11="","",INPUT_SYSTEM!F25) | F11: {=IFERROR(INDEX(PRODUCT!$D:$D,MATCH(C11,PRODUCT!$B:$B,0)),"")} | G11: {=IFERROR(INDEX(PRODUCT!$E:$E,MATCH(C11,PRODUCT!$B:$B,0)),"")} | H11: {=IFERROR(INDEX(PRODUCT!$F:$F,MATCH(C11,PRODUCT!$B:$B,0)),"")} | I11: =IF(C11="","",INPUT_SYSTEM!G25) | J11: =IF(C11="","",INPUT_SYSTEM!H25) | K11: =IF(C11="","",INPUT_SYSTEM!J25) | L11: =IF(C11="","",INPUT_SYSTEM!K25) | M11: =IF(C11="","",INPUT_SYSTEM!L25) | N11: =IF(U11<>"SI","",IF(M11<>"",M11,IFERROR(I11*J11*(1+K11)*L11,""))) | O11: =IF(N11="","",IF(OR(H11="",H11=0),N11,ROUNDUP(N11/H11,0))) | P11: {=IFERROR(INDEX(PRODUCT!$I:$I,MATCH(C11,PRODUCT!$B:$B,0)),"")} | Q11: =IF(C11="","",INPUT_SYSTEM!M25) | R11: =IF(P11="","",P11*(1+Q11)) | S11: =IF(O11="","",IF(OR(H11="",H11=0),O11*P11,O11*H11*P11)) | T11: =IF(O11="","",IF(OR(H11="",H11=0),O11*R11,O11*H11*R11)) | U11: =IF(C11="","",INPUT_SYSTEM!C25) | V11: =IF(C11="","",INPUT_SYSTEM!N25)
A12: =IF(INPUT_SYSTEM!D26="","",INPUT_SYSTEM!A26) | B12: =IF(INPUT_SYSTEM!D26="","",INPUT_SYSTEM!B26) | C12: =IF(INPUT_SYSTEM!D26="","",INPUT_SYSTEM!D26) | D12: =IF(C12="","",INPUT_SYSTEM!E26) | E12: =IF(C12="","",INPUT_SYSTEM!F26) | F12: {=IFERROR(INDEX(PRODUCT!$D:$D,MATCH(C12,PRODUCT!$B:$B,0)),"")} | G12: {=IFERROR(INDEX(PRODUCT!$E:$E,MATCH(C12,PRODUCT!$B:$B,0)),"")} | H12: {=IFERROR(INDEX(PRODUCT!$F:$F,MATCH(C12,PRODUCT!$B:$B,0)),"")} | I12: =IF(C12="","",INPUT_SYSTEM!G26) | J12: =IF(C12="","",INPUT_SYSTEM!H26) | K12: =IF(C12="","",INPUT_SYSTEM!J26) | L12: =IF(C12="","",INPUT_SYSTEM!K26) | M12: =IF(C12="","",INPUT_SYSTEM!L26) | N12: =IF(U12<>"SI","",IF(M12<>"",M12,IFERROR(I12*J12*(1+K12)*L12,""))) | O12: =IF(N12="","",IF(OR(H12="",H12=0),N12,ROUNDUP(N12/H12,0))) | P12: {=IFERROR(INDEX(PRODUCT!$I:$I,MATCH(C12,PRODUCT!$B:$B,0)),"")} | Q12: =IF(C12="","",INPUT_SYSTEM!M26) | R12: =IF(P12="","",P12*(1+Q12)) | S12: =IF(O12="","",IF(OR(H12="",H12=0),O12*P12,O12*H12*P12)) | T12: =IF(O12="","",IF(OR(H12="",H12=0),O12*R12,O12*H12*R12)) | U12: =IF(C12="","",INPUT_SYSTEM!C26) | V12: =IF(C12="","",INPUT_SYSTEM!N26)
A13: =IF(INPUT_SYSTEM!D27="","",INPUT_SYSTEM!A27) | B13: =IF(INPUT_SYSTEM!D27="","",INPUT_SYSTEM!B27) | C13: =IF(INPUT_SYSTEM!D27="","",INPUT_SYSTEM!D27) | D13: =IF(C13="","",INPUT_SYSTEM!E27) | E13: =IF(C13="","",INPUT_SYSTEM!F27) | F13: {=IFERROR(INDEX(PRODUCT!$D:$D,MATCH(C13,PRODUCT!$B:$B,0)),"")} | G13: {=IFERROR(INDEX(PRODUCT!$E:$E,MATCH(C13,PRODUCT!$B:$B,0)),"")} | H13: {=IFERROR(INDEX(PRODUCT!$F:$F,MATCH(C13,PRODUCT!$B:$B,0)),"")} | I13: =IF(C13="","",INPUT_SYSTEM!G27) | J13: =IF(C13="","",INPUT_SYSTEM!H27) | K13: =IF(C13="","",INPUT_SYSTEM!J27) | L13: =IF(C13="","",INPUT_SYSTEM!K27) | M13: =IF(C13="","",INPUT_SYSTEM!L27) | N13: =IF(U13<>"SI","",IF(M13<>"",M13,IFERROR(I13*J13*(1+K13)*L13,""))) | O13: =IF(N13="","",IF(OR(H13="",H13=0),N13,ROUNDUP(N13/H13,0))) | P13: {=IFERROR(INDEX(PRODUCT!$I:$I,MATCH(C13,PRODUCT!$B:$B,0)),"")} | Q13: =IF(C13="","",INPUT_SYSTEM!M27) | R13: =IF(P13="","",P13*(1+Q13)) | S13: =IF(O13="","",IF(OR(H13="",H13=0),O13*P13,O13*H13*P13)) | T13: =IF(O13="","",IF(OR(H13="",H13=0),O13*R13,O13*H13*R13)) | U13: =IF(C13="","",INPUT_SYSTEM!C27) | V13: =IF(C13="","",INPUT_SYSTEM!N27)
A14: =IF(INPUT_SYSTEM!D28="","",INPUT_SYSTEM!A28) | B14: =IF(INPUT_SYSTEM!D28="","",INPUT_SYSTEM!B28) | C14: =IF(INPUT_SYSTEM!D28="","",INPUT_SYSTEM!D28) | D14: =IF(C14="","",INPUT_SYSTEM!E28) | E14: =IF(C14="","",INPUT_SYSTEM!F28) | F14: {=IFERROR(INDEX(PRODUCT!$D:$D,MATCH(C14,PRODUCT!$B:$B,0)),"")} | G14: {=IFERROR(INDEX(PRODUCT!$E:$E,MATCH(C14,PRODUCT!$B:$B,0)),"")} | H14: {=IFERROR(INDEX(PRODUCT!$F:$F,MATCH(C14,PRODUCT!$B:$B,0)),"")} | I14: =IF(C14="","",INPUT_SYSTEM!G28) | J14: =IF(C14="","",INPUT_SYSTEM!H28) | K14: =IF(C14="","",INPUT_SYSTEM!J28) | L14: =IF(C14="","",INPUT_SYSTEM!K28) | M14: =IF(C14="","",INPUT_SYSTEM!L28) | N14: =IF(U14<>"SI","",IF(M14<>"",M14,IFERROR(I14*J14*(1+K14)*L14,""))) | O14: =IF(N14="","",IF(OR(H14="",H14=0),N14,ROUNDUP(N14/H14,0))) | P14: {=IFERROR(INDEX(PRODUCT!$I:$I,MATCH(C14,PRODUCT!$B:$B,0)),"")} | Q14: =IF(C14="","",INPUT_SYSTEM!M28) | R14: =IF(P14="","",P14*(1+Q14)) | S14: =IF(O14="","",IF(OR(H14="",H14=0),O14*P14,O14*H14*P14)) | T14: =IF(O14="","",IF(OR(H14="",H14=0),O14*R14,O14*H14*R14)) | U14: =IF(C14="","",INPUT_SYSTEM!C28) | V14: =IF(C14="","",INPUT_SYSTEM!N28)
... A250: =IF(INPUT_SYSTEM!D264="","",INPUT_SYSTEM!A264) | B250: =IF(INPUT_SYSTEM!D264="","",INPUT_SYSTEM!B264) | C250: =IF(INPUT_SYSTEM!D264="","",INPUT_SYSTEM!D264) | D250: =IF(C250="","",INPUT_SYSTEM!E264) | E250: =IF(C250="","",INPUT_SYSTEM!F264) | F250: {=IFERROR(INDEX(PRODUCT!$D:$D,MATCH(C250,PRODUCT!$B:$B,0)),"")} | G250: {=IFERROR(INDEX(PRODUCT!$E:$E,MATCH(C250,PRODUCT!$B:$B,0)),"")} | H250: {=IFERROR(INDEX(PRODUCT!$F:$F,MATCH(C250,PRODUCT!$B:$B,0)),"")} | I250: =IF(C250="","",INPUT_SYSTEM!G264) | J250: =IF(C250="","",INPUT_SYSTEM!H264) | K250: =IF(C250="","",INPUT_SYSTEM!J264) | L250: =IF(C250="","",INPUT_SYSTEM!K264) | M250: =IF(C250="","",INPUT_SYSTEM!L264) | N250: =IF(U250<>"SI","",IF(M250<>"",M250,IFERROR(I250*J250*(1+K250)*L250,""))) | O250: =IF(N250="","",IF(OR(H250="",H250=0),N250,ROUNDUP(N250/H250,0))) | P250: {=IFERROR(INDEX(PRODUCT!$I:$I,MATCH(C250,PRODUCT!$B:$B,0)),"")} | Q250: =IF(C250="","",INPUT_SYSTEM!M264) | R250: =IF(P250="","",P250*(1+Q250)) | S250: =IF(O250="","",IF(OR(H250="",H250=0),O250*P250,O250*H250*P250)) | T250: =IF(O250="","",IF(OR(H250="",H250=0),O250*R250,O250*H250*R250)) | U250: =IF(C250="","",INPUT_SYSTEM!C264) | V250: =IF(C250="","",INPUT_SYSTEM!N264)
A251: =IF(INPUT_SYSTEM!D265="","",INPUT_SYSTEM!A265) | B251: =IF(INPUT_SYSTEM!D265="","",INPUT_SYSTEM!B265) | C251: =IF(INPUT_SYSTEM!D265="","",INPUT_SYSTEM!D265) | D251: =IF(C251="","",INPUT_SYSTEM!E265) | E251: =IF(C251="","",INPUT_SYSTEM!F265) | F251: {=IFERROR(INDEX(PRODUCT!$D:$D,MATCH(C251,PRODUCT!$B:$B,0)),"")} | G251: {=IFERROR(INDEX(PRODUCT!$E:$E,MATCH(C251,PRODUCT!$B:$B,0)),"")} | H251: {=IFERROR(INDEX(PRODUCT!$F:$F,MATCH(C251,PRODUCT!$B:$B,0)),"")} | I251: =IF(C251="","",INPUT_SYSTEM!G265) | J251: =IF(C251="","",INPUT_SYSTEM!H265) | K251: =IF(C251="","",INPUT_SYSTEM!J265) | L251: =IF(C251="","",INPUT_SYSTEM!K265) | M251: =IF(C251="","",INPUT_SYSTEM!L265) | N251: =IF(U251<>"SI","",IF(M251<>"",M251,IFERROR(I251*J251*(1+K251)*L251,""))) | O251: =IF(N251="","",IF(OR(H251="",H251=0),N251,ROUNDUP(N251/H251,0))) | P251: {=IFERROR(INDEX(PRODUCT!$I:$I,MATCH(C251,PRODUCT!$B:$B,0)),"")} | Q251: =IF(C251="","",INPUT_SYSTEM!M265) | R251: =IF(P251="","",P251*(1+Q251)) | S251: =IF(O251="","",IF(OR(H251="",H251=0),O251*P251,O251*H251*P251)) | T251: =IF(O251="","",IF(OR(H251="",H251=0),O251*R251,O251*H251*R251)) | U251: =IF(C251="","",INPUT_SYSTEM!C265)
A252: =IF(INPUT_SYSTEM!D266="","",INPUT_SYSTEM!A266) | B252: =IF(INPUT_SYSTEM!D266="","",INPUT_SYSTEM!B266) | C252: =IF(INPUT_SYSTEM!D266="","",INPUT_SYSTEM!D266) | D252: =IF(C252="","",INPUT_SYSTEM!E266) | E252: =IF(C252="","",INPUT_SYSTEM!F266) | F252: {=IFERROR(INDEX(PRODUCT!$D:$D,MATCH(C252,PRODUCT!$B:$B,0)),"")} | G252: {=IFERROR(INDEX(PRODUCT!$E:$E,MATCH(C252,PRODUCT!$B:$B,0)),"")} | H252: {=IFERROR(INDEX(PRODUCT!$F:$F,MATCH(C252,PRODUCT!$B:$B,0)),"")} | I252: =IF(C252="","",INPUT_SYSTEM!G266) | J252: =IF(C252="","",INPUT_SYSTEM!H266) | K252: =IF(C252="","",INPUT_SYSTEM!J266) | L252: =IF(C252="","",INPUT_SYSTEM!K266) | M252: =IF(C252="","",INPUT_SYSTEM!L266) | N252: =IF(U252<>"SI","",IF(M252<>"",M252,IFERROR(I252*J252*(1+K252)*L252,""))) | O252: =IF(N252="","",IF(OR(H252="",H252=0),N252,ROUNDUP(N252/H252,0))) | P252: {=IFERROR(INDEX(PRODUCT!$I:$I,MATCH(C252,PRODUCT!$B:$B,0)),"")} | Q252: =IF(C252="","",INPUT_SYSTEM!M266) | R252: =IF(P252="","",P252*(1+Q252)) | S252: =IF(O252="","",IF(OR(H252="",H252=0),O252*P252,O252*H252*P252)) | T252: =IF(O252="","",IF(OR(H252="",H252=0),O252*R252,O252*H252*R252)) | U252: =IF(C252="","",INPUT_SYSTEM!C266)
A253: =IF(INPUT_SYSTEM!D267="","",INPUT_SYSTEM!A267) | B253: =IF(INPUT_SYSTEM!D267="","",INPUT_SYSTEM!B267) | C253: =IF(INPUT_SYSTEM!D267="","",INPUT_SYSTEM!D267) | D253: =IF(C253="","",INPUT_SYSTEM!E267) | E253: =IF(C253="","",INPUT_SYSTEM!F267) | F253: {=IFERROR(INDEX(PRODUCT!$D:$D,MATCH(C253,PRODUCT!$B:$B,0)),"")} | G253: {=IFERROR(INDEX(PRODUCT!$E:$E,MATCH(C253,PRODUCT!$B:$B,0)),"")} | H253: {=IFERROR(INDEX(PRODUCT!$F:$F,MATCH(C253,PRODUCT!$B:$B,0)),"")} | I253: =IF(C253="","",INPUT_SYSTEM!G267) | J253: =IF(C253="","",INPUT_SYSTEM!H267) | K253: =IF(C253="","",INPUT_SYSTEM!J267) | L253: =IF(C253="","",INPUT_SYSTEM!K267) | M253: =IF(C253="","",INPUT_SYSTEM!L267) | N253: =IF(U253<>"SI","",IF(M253<>"",M253,IFERROR(I253*J253*(1+K253)*L253,""))) | O253: =IF(N253="","",IF(OR(H253="",H253=0),N253,ROUNDUP(N253/H253,0))) | P253: {=IFERROR(INDEX(PRODUCT!$I:$I,MATCH(C253,PRODUCT!$B:$B,0)),"")} | Q253: =IF(C253="","",INPUT_SYSTEM!M267) | R253: =IF(P253="","",P253*(1+Q253)) | S253: =IF(O253="","",IF(OR(H253="",H253=0),O253*P253,O253*H253*P253)) | T253: =IF(O253="","",IF(OR(H253="",H253=0),O253*R253,O253*H253*R253)) | U253: =IF(C253="","",INPUT_SYSTEM!C267)
A254: =IF(INPUT_SYSTEM!D268="","",INPUT_SYSTEM!A268) | B254: =IF(INPUT_SYSTEM!D268="","",INPUT_SYSTEM!B268) | C254: =IF(INPUT_SYSTEM!D268="","",INPUT_SYSTEM!D268) | D254: =IF(C254="","",INPUT_SYSTEM!E268) | E254: =IF(C254="","",INPUT_SYSTEM!F268) | F254: {=IFERROR(INDEX(PRODUCT!$D:$D,MATCH(C254,PRODUCT!$B:$B,0)),"")} | G254: {=IFERROR(INDEX(PRODUCT!$E:$E,MATCH(C254,PRODUCT!$B:$B,0)),"")} | H254: {=IFERROR(INDEX(PRODUCT!$F:$F,MATCH(C254,PRODUCT!$B:$B,0)),"")} | I254: =IF(C254="","",INPUT_SYSTEM!G268) | J254: =IF(C254="","",INPUT_SYSTEM!H268) | K254: =IF(C254="","",INPUT_SYSTEM!J268) | L254: =IF(C254="","",INPUT_SYSTEM!K268) | M254: =IF(C254="","",INPUT_SYSTEM!L268) | N254: =IF(U254<>"SI","",IF(M254<>"",M254,IFERROR(I254*J254*(1+K254)*L254,""))) | O254: =IF(N254="","",IF(OR(H254="",H254=0),N254,ROUNDUP(N254/H254,0))) | P254: {=IFERROR(INDEX(PRODUCT!$I:$I,MATCH(C254,PRODUCT!$B:$B,0)),"")} | Q254: =IF(C254="","",INPUT_SYSTEM!M268) | R254: =IF(P254="","",P254*(1+Q254)) | S254: =IF(O254="","",IF(OR(H254="",H254=0),O254*P254,O254*H254*P254)) | T254: =IF(O254="","",IF(OR(H254="",H254=0),O254*R254,O254*H254*R254)) | U254: =IF(C254="","",INPUT_SYSTEM!C268)
A255: =IF(INPUT_SYSTEM!D269="","",INPUT_SYSTEM!A269) | B255: =IF(INPUT_SYSTEM!D269="","",INPUT_SYSTEM!B269) | C255: =IF(INPUT_SYSTEM!D269="","",INPUT_SYSTEM!D269) | D255: =IF(C255="","",INPUT_SYSTEM!E269) | E255: =IF(C255="","",INPUT_SYSTEM!F269) | F255: {=IFERROR(INDEX(PRODUCT!$D:$D,MATCH(C255,PRODUCT!$B:$B,0)),"")} | G255: {=IFERROR(INDEX(PRODUCT!$E:$E,MATCH(C255,PRODUCT!$B:$B,0)),"")} | H255: {=IFERROR(INDEX(PRODUCT!$F:$F,MATCH(C255,PRODUCT!$B:$B,0)),"")} | I255: =IF(C255="","",INPUT_SYSTEM!G269) | J255: =IF(C255="","",INPUT_SYSTEM!H269) | K255: =IF(C255="","",INPUT_SYSTEM!J269) | L255: =IF(C255="","",INPUT_SYSTEM!K269) | M255: =IF(C255="","",INPUT_SYSTEM!L269) | N255: =IF(U255<>"SI","",IF(M255<>"",M255,IFERROR(I255*J255*(1+K255)*L255,""))) | O255: =IF(N255="","",IF(OR(H255="",H255=0),N255,ROUNDUP(N255/H255,0))) | P255: {=IFERROR(INDEX(PRODUCT!$I:$I,MATCH(C255,PRODUCT!$B:$B,0)),"")} | Q255: =IF(C255="","",INPUT_SYSTEM!M269) | R255: =IF(P255="","",P255*(1+Q255)) | S255: =IF(O255="","",IF(OR(H255="",H255=0),O255*P255,O255*H255*P255)) | T255: =IF(O255="","",IF(OR(H255="",H255=0),O255*R255,O255*H255*R255)) | U255: =IF(C255="","",INPUT_SYSTEM!C269)
A256: =IF(INPUT_SYSTEM!D270="","",INPUT_SYSTEM!A270) | B256: =IF(INPUT_SYSTEM!D270="","",INPUT_SYSTEM!B270) | C256: =IF(INPUT_SYSTEM!D270="","",INPUT_SYSTEM!D270) | D256: =IF(C256="","",INPUT_SYSTEM!E270) | E256: =IF(C256="","",INPUT_SYSTEM!F270) | F256: {=IFERROR(INDEX(PRODUCT!$D:$D,MATCH(C256,PRODUCT!$B:$B,0)),"")} | G256: {=IFERROR(INDEX(PRODUCT!$E:$E,MATCH(C256,PRODUCT!$B:$B,0)),"")} | H256: {=IFERROR(INDEX(PRODUCT!$F:$F,MATCH(C256,PRODUCT!$B:$B,0)),"")} | I256: =IF(C256="","",INPUT_SYSTEM!G270) | J256: =IF(C256="","",INPUT_SYSTEM!H270) | K256: =IF(C256="","",INPUT_SYSTEM!J270) | L256: =IF(C256="","",INPUT_SYSTEM!K270) | M256: =IF(C256="","",INPUT_SYSTEM!L270) | N256: =IF(U256<>"SI","",IF(M256<>"",M256,IFERROR(I256*J256*(1+K256)*L256,""))) | O256: =IF(N256="","",IF(OR(H256="",H256=0),N256,ROUNDUP(N256/H256,0))) | P256: {=IFERROR(INDEX(PRODUCT!$I:$I,MATCH(C256,PRODUCT!$B:$B,0)),"")} | Q256: =IF(C256="","",INPUT_SYSTEM!M270) | R256: =IF(P256="","",P256*(1+Q256)) | S256: =IF(O256="","",IF(OR(H256="",H256=0),O256*P256,O256*H256*P256)) | T256: =IF(O256="","",IF(OR(H256="",H256=0),O256*R256,O256*H256*R256)) | U256: =IF(C256="","",INPUT_SYSTEM!C270)
A257: =IF(INPUT_SYSTEM!D271="","",INPUT_SYSTEM!A271) | B257: =IF(INPUT_SYSTEM!D271="","",INPUT_SYSTEM!B271) | C257: =IF(INPUT_SYSTEM!D271="","",INPUT_SYSTEM!D271) | D257: =IF(C257="","",INPUT_SYSTEM!E271) | E257: =IF(C257="","",INPUT_SYSTEM!F271) | F257: {=IFERROR(INDEX(PRODUCT!$D:$D,MATCH(C257,PRODUCT!$B:$B,0)),"")} | G257: {=IFERROR(INDEX(PRODUCT!$E:$E,MATCH(C257,PRODUCT!$B:$B,0)),"")} | H257: {=IFERROR(INDEX(PRODUCT!$F:$F,MATCH(C257,PRODUCT!$B:$B,0)),"")} | I257: =IF(C257="","",INPUT_SYSTEM!G271) | J257: =IF(C257="","",INPUT_SYSTEM!H271) | K257: =IF(C257="","",INPUT_SYSTEM!J271) | L257: =IF(C257="","",INPUT_SYSTEM!K271) | M257: =IF(C257="","",INPUT_SYSTEM!L271) | N257: =IF(U257<>"SI","",IF(M257<>"",M257,IFERROR(I257*J257*(1+K257)*L257,""))) | O257: =IF(N257="","",IF(OR(H257="",H257=0),N257,ROUNDUP(N257/H257,0))) | P257: {=IFERROR(INDEX(PRODUCT!$I:$I,MATCH(C257,PRODUCT!$B:$B,0)),"")} | Q257: =IF(C257="","",INPUT_SYSTEM!M271) | R257: =IF(P257="","",P257*(1+Q257)) | S257: =IF(O257="","",IF(OR(H257="",H257=0),O257*P257,O257*H257*P257)) | T257: =IF(O257="","",IF(OR(H257="",H257=0),O257*R257,O257*H257*R257)) | U257: =IF(C257="","",INPUT_SYSTEM!C271)
A258: =IF(INPUT_SYSTEM!D272="","",INPUT_SYSTEM!A272) | B258: =IF(INPUT_SYSTEM!D272="","",INPUT_SYSTEM!B272) | C258: =IF(INPUT_SYSTEM!D272="","",INPUT_SYSTEM!D272) | D258: =IF(C258="","",INPUT_SYSTEM!E272) | E258: =IF(C258="","",INPUT_SYSTEM!F272) | F258: {=IFERROR(INDEX(PRODUCT!$D:$D,MATCH(C258,PRODUCT!$B:$B,0)),"")} | G258: {=IFERROR(INDEX(PRODUCT!$E:$E,MATCH(C258,PRODUCT!$B:$B,0)),"")} | H258: {=IFERROR(INDEX(PRODUCT!$F:$F,MATCH(C258,PRODUCT!$B:$B,0)),"")} | I258: =IF(C258="","",INPUT_SYSTEM!G272) | J258: =IF(C258="","",INPUT_SYSTEM!H272) | K258: =IF(C258="","",INPUT_SYSTEM!J272) | L258: =IF(C258="","",INPUT_SYSTEM!K272) | M258: =IF(C258="","",INPUT_SYSTEM!L272) | N258: =IF(U258<>"SI","",IF(M258<>"",M258,IFERROR(I258*J258*(1+K258)*L258,""))) | O258: =IF(N258="","",IF(OR(H258="",H258=0),N258,ROUNDUP(N258/H258,0))) | P258: {=IFERROR(INDEX(PRODUCT!$I:$I,MATCH(C258,PRODUCT!$B:$B,0)),"")} | Q258: =IF(C258="","",INPUT_SYSTEM!M272) | R258: =IF(P258="","",P258*(1+Q258)) | S258: =IF(O258="","",IF(OR(H258="",H258=0),O258*P258,O258*H258*P258)) | T258: =IF(O258="","",IF(OR(H258="",H258=0),O258*R258,O258*H258*R258)) | U258: =IF(C258="","",INPUT_SYSTEM!C272)
A259: =IF(INPUT_SYSTEM!D273="","",INPUT_SYSTEM!A273) | B259: =IF(INPUT_SYSTEM!D273="","",INPUT_SYSTEM!B273) | C259: =IF(INPUT_SYSTEM!D273="","",INPUT_SYSTEM!D273) | D259: =IF(C259="","",INPUT_SYSTEM!E273) | E259: =IF(C259="","",INPUT_SYSTEM!F273) | F259: {=IFERROR(INDEX(PRODUCT!$D:$D,MATCH(C259,PRODUCT!$B:$B,0)),"")} | G259: {=IFERROR(INDEX(PRODUCT!$E:$E,MATCH(C259,PRODUCT!$B:$B,0)),"")} | H259: {=IFERROR(INDEX(PRODUCT!$F:$F,MATCH(C259,PRODUCT!$B:$B,0)),"")} | I259: =IF(C259="","",INPUT_SYSTEM!G273) | J259: =IF(C259="","",INPUT_SYSTEM!H273) | K259: =IF(C259="","",INPUT_SYSTEM!J273) | L259: =IF(C259="","",INPUT_SYSTEM!K273) | M259: =IF(C259="","",INPUT_SYSTEM!L273) | N259: =IF(U259<>"SI","",IF(M259<>"",M259,IFERROR(I259*J259*(1+K259)*L259,""))) | O259: =IF(N259="","",IF(OR(H259="",H259=0),N259,ROUNDUP(N259/H259,0))) | P259: {=IFERROR(INDEX(PRODUCT!$I:$I,MATCH(C259,PRODUCT!$B:$B,0)),"")} | Q259: =IF(C259="","",INPUT_SYSTEM!M273) | R259: =IF(P259="","",P259*(1+Q259)) | S259: =IF(O259="","",IF(OR(H259="",H259=0),O259*P259,O259*H259*P259)) | T259: =IF(O259="","",IF(OR(H259="",H259=0),O259*R259,O259*H259*R259)) | U259: =IF(C259="","",INPUT_SYSTEM!C273)
A260: =IF(INPUT_SYSTEM!D274="","",INPUT_SYSTEM!A274) | B260: =IF(INPUT_SYSTEM!D274="","",INPUT_SYSTEM!B274) | C260: =IF(INPUT_SYSTEM!D274="","",INPUT_SYSTEM!D274) | D260: =IF(C260="","",INPUT_SYSTEM!E274) | E260: =IF(C260="","",INPUT_SYSTEM!F274) | F260: {=IFERROR(INDEX(PRODUCT!$D:$D,MATCH(C260,PRODUCT!$B:$B,0)),"")} | G260: {=IFERROR(INDEX(PRODUCT!$E:$E,MATCH(C260,PRODUCT!$B:$B,0)),"")} | H260: {=IFERROR(INDEX(PRODUCT!$F:$F,MATCH(C260,PRODUCT!$B:$B,0)),"")} | I260: =IF(C260="","",INPUT_SYSTEM!G274) | J260: =IF(C260="","",INPUT_SYSTEM!H274) | K260: =IF(C260="","",INPUT_SYSTEM!J274) | L260: =IF(C260="","",INPUT_SYSTEM!K274) | M260: =IF(C260="","",INPUT_SYSTEM!L274) | N260: =IF(U260<>"SI","",IF(M260<>"",M260,IFERROR(I260*J260*(1+K260)*L260,""))) | O260: =IF(N260="","",IF(OR(H260="",H260=0),N260,ROUNDUP(N260/H260,0))) | P260: {=IFERROR(INDEX(PRODUCT!$I:$I,MATCH(C260,PRODUCT!$B:$B,0)),"")} | Q260: =IF(C260="","",INPUT_SYSTEM!M274) | R260: =IF(P260="","",P260*(1+Q260)) | S260: =IF(O260="","",IF(OR(H260="",H260=0),O260*P260,O260*H260*P260)) | T260: =IF(O260="","",IF(OR(H260="",H260=0),O260*R260,O260*H260*R260)) | U260: =IF(C260="","",INPUT_SYSTEM!C274)
A261: =IF(INPUT_SYSTEM!D275="","",INPUT_SYSTEM!A275) | B261: =IF(INPUT_SYSTEM!D275="","",INPUT_SYSTEM!B275) | C261: =IF(INPUT_SYSTEM!D275="","",INPUT_SYSTEM!D275) | D261: =IF(C261="","",INPUT_SYSTEM!E275) | E261: =IF(C261="","",INPUT_SYSTEM!F275) | F261: {=IFERROR(INDEX(PRODUCT!$D:$D,MATCH(C261,PRODUCT!$B:$B,0)),"")} | G261: {=IFERROR(INDEX(PRODUCT!$E:$E,MATCH(C261,PRODUCT!$B:$B,0)),"")} | H261: {=IFERROR(INDEX(PRODUCT!$F:$F,MATCH(C261,PRODUCT!$B:$B,0)),"")} | I261: =IF(C261="","",INPUT_SYSTEM!G275) | J261: =IF(C261="","",INPUT_SYSTEM!H275) | K261: =IF(C261="","",INPUT_SYSTEM!J275) | L261: =IF(C261="","",INPUT_SYSTEM!K275) | M261: =IF(C261="","",INPUT_SYSTEM!L275) | N261: =IF(U261<>"SI","",IF(M261<>"",M261,IFERROR(I261*J261*(1+K261)*L261,""))) | O261: =IF(N261="","",IF(OR(H261="",H261=0),N261,ROUNDUP(N261/H261,0))) | P261: {=IFERROR(INDEX(PRODUCT!$I:$I,MATCH(C261,PRODUCT!$B:$B,0)),"")} | Q261: =IF(C261="","",INPUT_SYSTEM!M275) | R261: =IF(P261="","",P261*(1+Q261)) | S261: =IF(O261="","",IF(OR(H261="",H261=0),O261*P261,O261*H261*P261)) | T261: =IF(O261="","",IF(OR(H261="",H261=0),O261*R261,O261*H261*R261)) | U261: =IF(C261="","",INPUT_SYSTEM!C275)
A262: =IF(INPUT_SYSTEM!D276="","",INPUT_SYSTEM!A276) | B262: =IF(INPUT_SYSTEM!D276="","",INPUT_SYSTEM!B276) | C262: =IF(INPUT_SYSTEM!D276="","",INPUT_SYSTEM!D276) | D262: =IF(C262="","",INPUT_SYSTEM!E276) | E262: =IF(C262="","",INPUT_SYSTEM!F276) | F262: {=IFERROR(INDEX(PRODUCT!$D:$D,MATCH(C262,PRODUCT!$B:$B,0)),"")} | G262: {=IFERROR(INDEX(PRODUCT!$E:$E,MATCH(C262,PRODUCT!$B:$B,0)),"")} | H262: {=IFERROR(INDEX(PRODUCT!$F:$F,MATCH(C262,PRODUCT!$B:$B,0)),"")} | I262: =IF(C262="","",INPUT_SYSTEM!G276) | J262: =IF(C262="","",INPUT_SYSTEM!H276) | K262: =IF(C262="","",INPUT_SYSTEM!J276) | L262: =IF(C262="","",INPUT_SYSTEM!K276) | M262: =IF(C262="","",INPUT_SYSTEM!L276) | N262: =IF(U262<>"SI","",IF(M262<>"",M262,IFERROR(I262*J262*(1+K262)*L262,""))) | O262: =IF(N262="","",IF(OR(H262="",H262=0),N262,ROUNDUP(N262/H262,0))) | P262: {=IFERROR(INDEX(PRODUCT!$I:$I,MATCH(C262,PRODUCT!$B:$B,0)),"")} | Q262: =IF(C262="","",INPUT_SYSTEM!M276) | R262: =IF(P262="","",P262*(1+Q262)) | S262: =IF(O262="","",IF(OR(H262="",H262=0),O262*P262,O262*H262*P262)) | T262: =IF(O262="","",IF(OR(H262="",H262=0),O262*R262,O262*H262*R262)) | U262: =IF(C262="","",INPUT_SYSTEM!C276)
... A499: =IF(INPUT_SYSTEM!D513="","",INPUT_SYSTEM!A513) | B499: =IF(INPUT_SYSTEM!D513="","",INPUT_SYSTEM!B513) | C499: =IF(INPUT_SYSTEM!D513="","",INPUT_SYSTEM!D513) | D499: =IF(C499="","",INPUT_SYSTEM!E513) | E499: =IF(C499="","",INPUT_SYSTEM!F513) | F499: {=IFERROR(INDEX(PRODUCT!$D:$D,MATCH(C499,PRODUCT!$B:$B,0)),"")} | G499: {=IFERROR(INDEX(PRODUCT!$E:$E,MATCH(C499,PRODUCT!$B:$B,0)),"")} | H499: {=IFERROR(INDEX(PRODUCT!$F:$F,MATCH(C499,PRODUCT!$B:$B,0)),"")} | I499: =IF(C499="","",INPUT_SYSTEM!G513) | J499: =IF(C499="","",INPUT_SYSTEM!H513) | K499: =IF(C499="","",INPUT_SYSTEM!J513) | L499: =IF(C499="","",INPUT_SYSTEM!K513) | M499: =IF(C499="","",INPUT_SYSTEM!L513) | N499: =IF(U499<>"SI","",IF(M499<>"",M499,IFERROR(I499*J499*(1+K499)*L499,""))) | O499: =IF(N499="","",IF(OR(H499="",H499=0),N499,ROUNDUP(N499/H499,0))) | P499: {=IFERROR(INDEX(PRODUCT!$I:$I,MATCH(C499,PRODUCT!$B:$B,0)),"")} | Q499: =IF(C499="","",INPUT_SYSTEM!M513) | R499: =IF(P499="","",P499*(1+Q499)) | S499: =IF(O499="","",IF(OR(H499="",H499=0),O499*P499,O499*H499*P499)) | T499: =IF(O499="","",IF(OR(H499="",H499=0),O499*R499,O499*H499*R499)) | U499: =IF(C499="","",INPUT_SYSTEM!C513)
A500: =IF(INPUT_SYSTEM!D514="","",INPUT_SYSTEM!A514) | B500: =IF(INPUT_SYSTEM!D514="","",INPUT_SYSTEM!B514) | C500: =IF(INPUT_SYSTEM!D514="","",INPUT_SYSTEM!D514) | D500: =IF(C500="","",INPUT_SYSTEM!E514) | E500: =IF(C500="","",INPUT_SYSTEM!F514) | F500: {=IF(C500="","",xlookup(C500,PRODUCT!$B:$B,PRODUCT!$D:$D,""))} | G500: {=IF(C500="","",xlookup(C500,PRODUCT!$B:$B,PRODUCT!$E:$E,""))} | H500: {=IF(C500="","",xlookup(C500,PRODUCT!$B:$B,PRODUCT!$F:$F,""))} | I500: =IF(C500="","",INPUT_SYSTEM!G514) | J500: =IF(C500="","",INPUT_SYSTEM!H514) | K500: =IF(C500="","",INPUT_SYSTEM!J514) | L500: =IF(C500="","",INPUT_SYSTEM!K514) | M500: =IF(C500="","",INPUT_SYSTEM!L514) | N500: =IF(U500<>"SI","",IF(M500<>"",M500,IFERROR(I500*J500*(1+K500)*L500,""))) | O500: =IF(N500="","",IF(OR(H500="",H500=0),N500,ROUNDUP(N500/H500,0))) | P500: {=IF(C500="","",xlookup(C500,PRODUCT!$B:$B,PRODUCT!$I:$I,""))} | Q500: =IF(C500="","",INPUT_SYSTEM!M514) | R500: =IF(P500="","",P500*(1+Q500)) | S500: =IF(O500="","",IF(OR(H500="",H500=0),O500*P500,O500*H500*P500)) | T500: =IF(O500="","",IF(OR(H500="",H500=0),O500*R500,O500*H500*R500)) | U500: =IF(C500="","",INPUT_SYSTEM!C514)

Sheet PRODUCT_CALCULATION
A1: ITEM | B1: INCLUIR | C1: SKU_FASSA | D1: FAMILIA | E1: NOMBRE_PRODUCTO | F1: CANTIDAD_FINAL_INPUT | G1: UNIDAD_INPUT | H1: CONTENIDO_VENTA | I1: UNIDAD_MATERIAL | J1: M2_UNIDAD | K1: UDS_POR_PALET | L1: PESO_NETO_UNIDAD | M1: PESO_NETO_PALET | N1: M2_PALE | O1: PRECIO_ARIAS_EUR | P1: UNIDAD_PRECIO | Q1: MARGEN_%_APLICADO | R1: RECARGO_LOGISTICO_% | S1: PRECIO_CLIENTE_EUR | T1: SUBTOTAL_EUR | U1: TC_EUR_USD | V1: PRECIO_CLIENTE_USD | W1: SUBTOTAL_USD | X1: ACTIVO_LINEA | Y1: OBSERVACIONES
A2: =IF(INPUT_PRODUCT!C15="";"";INPUT_PRODUCT!A15) | B2: =IF(INPUT_PRODUCT!C15="";"";INPUT_PRODUCT!B15) | C2: =IF(INPUT_PRODUCT!C15="";"";INPUT_PRODUCT!C15) | D2: =IF(INPUT_PRODUCT!C15="";"";INDEX(PRODUCT!A:A;MATCH(INPUT_PRODUCT!C15;PRODUCT!B:B;0))) | E2: =IF(INPUT_PRODUCT!C15="";"";VLOOKUP(INPUT_PRODUCT!C15;PRODUCT!B:C;2;FALSE)) | F2: =IF(INPUT_PRODUCT!C15="";"";INPUT_PRODUCT!J15) | G2: =IF(INPUT_PRODUCT!C15="";"";INPUT_PRODUCT!G15) | H2: =IF(INPUT_PRODUCT!C15="";"";VLOOKUP(INPUT_PRODUCT!C15;PRODUCT!B:F;5;FALSE)) | I2: =IF(INPUT_PRODUCT!C15="";"";VLOOKUP(INPUT_PRODUCT!C15;PRODUCT!B:G;6;FALSE)) | J2: =IF(INPUT_PRODUCT!C15="";"";VLOOKUP(INPUT_PRODUCT!C15;PRODUCT!B:H;7;FALSE)) | K2: =IF(INPUT_PRODUCT!C15="";"";VLOOKUP(INPUT_PRODUCT!C15;PRODUCT!B:I;8;FALSE)) | L2: =IF(INPUT_PRODUCT!C15="";"";VLOOKUP(INPUT_PRODUCT!C15;PRODUCT!B:J;9;FALSE)) | M2: =IF(INPUT_PRODUCT!C15="";"";VLOOKUP(INPUT_PRODUCT!C15;PRODUCT!B:K;10;FALSE)) | N2: =IF(INPUT_PRODUCT!C15="";"";VLOOKUP(INPUT_PRODUCT!C15;PRODUCT!B:L;11;FALSE)) | O2: =IF(INPUT_PRODUCT!C15="";"";VLOOKUP(INPUT_PRODUCT!C15;PRODUCT!B:O;14;FALSE)) | P2: =IF(INPUT_PRODUCT!C15="";"";VLOOKUP(INPUT_PRODUCT!C15;PRODUCT!B:P;15;FALSE)) | Q2: =IF(INPUT_PRODUCT!C15="";"";INPUT_PRODUCT!K15) | S2: =IF(INPUT_PRODUCT!C15="";"";IF(O2="";"";O2*(1+Q2+R2))) | T2: =IF(INPUT_PRODUCT!C15="";"";IF(S2="";"";S2*F2)) | U2: =CONFIG!$B$2 | V2: =IF(INPUT_PRODUCT!C15="";"";IF(S2="";"";S2*U2)) | W2: =IF(INPUT_PRODUCT!C15="";"";IF(T2="";"";T2*U2)) | X2: =IF(INPUT_PRODUCT!C15="";"";VLOOKUP(INPUT_PRODUCT!C15;PRODUCT!B:T;19;FALSE)) | Y2: =IF(INPUT_PRODUCT!C15="";"";INPUT_PRODUCT!L15)
A3: =IF(INPUT_PRODUCT!C16="";"";INPUT_PRODUCT!A16) | B3: =IF(INPUT_PRODUCT!C16="";"";INPUT_PRODUCT!B16) | C3: =IF(INPUT_PRODUCT!C16="";"";INPUT_PRODUCT!C16) | D3: =IF(INPUT_PRODUCT!C16="";"";INDEX(PRODUCT!A:A;MATCH(INPUT_PRODUCT!C16;PRODUCT!B:B;0))) | E3: =IF(INPUT_PRODUCT!C16="";"";VLOOKUP(INPUT_PRODUCT!C16;PRODUCT!B:C;2;FALSE)) | F3: =IF(INPUT_PRODUCT!C16="";"";INPUT_PRODUCT!J16) | G3: =IF(INPUT_PRODUCT!C16="";"";INPUT_PRODUCT!G16) | H3: =IF(INPUT_PRODUCT!C16="";"";VLOOKUP(INPUT_PRODUCT!C16;PRODUCT!B:F;5;FALSE)) | I3: =IF(INPUT_PRODUCT!C16="";"";VLOOKUP(INPUT_PRODUCT!C16;PRODUCT!B:G;6;FALSE)) | J3: =IF(INPUT_PRODUCT!C16="";"";VLOOKUP(INPUT_PRODUCT!C16;PRODUCT!B:H;7;FALSE)) | K3: =IF(INPUT_PRODUCT!C16="";"";VLOOKUP(INPUT_PRODUCT!C16;PRODUCT!B:I;8;FALSE)) | L3: =IF(INPUT_PRODUCT!C16="";"";VLOOKUP(INPUT_PRODUCT!C16;PRODUCT!B:J;9;FALSE)) | M3: =IF(INPUT_PRODUCT!C16="";"";VLOOKUP(INPUT_PRODUCT!C16;PRODUCT!B:K;10;FALSE)) | N3: =IF(INPUT_PRODUCT!C16="";"";VLOOKUP(INPUT_PRODUCT!C16;PRODUCT!B:L;11;FALSE)) | O3: =IF(INPUT_PRODUCT!C16="";"";VLOOKUP(INPUT_PRODUCT!C16;PRODUCT!B:O;14;FALSE)) | P3: =IF(INPUT_PRODUCT!C16="";"";VLOOKUP(INPUT_PRODUCT!C16;PRODUCT!B:P;15;FALSE)) | Q3: =IF(INPUT_PRODUCT!C16="";"";INPUT_PRODUCT!K16) | S3: =IF(INPUT_PRODUCT!C16="";"";IF(O3="";"";O3*(1+Q3+R3))) | T3: =IF(INPUT_PRODUCT!C16="";"";IF(S3="";"";S3*F3)) | U3: =CONFIG!$B$2 | V3: =IF(INPUT_PRODUCT!C16="";"";IF(S3="";"";S3*U3)) | W3: =IF(INPUT_PRODUCT!C16="";"";IF(T3="";"";T3*U3)) | X3: =IF(INPUT_PRODUCT!C16="";"";VLOOKUP(INPUT_PRODUCT!C16;PRODUCT!B:T;19;FALSE)) | Y3: =IF(INPUT_PRODUCT!C16="";"";INPUT_PRODUCT!L16)
A4: =IF(INPUT_PRODUCT!C17="";"";INPUT_PRODUCT!A17) | B4: =IF(INPUT_PRODUCT!C17="";"";INPUT_PRODUCT!B17) | C4: =IF(INPUT_PRODUCT!C17="";"";INPUT_PRODUCT!C17) | D4: =IF(INPUT_PRODUCT!C17="";"";INDEX(PRODUCT!A:A;MATCH(INPUT_PRODUCT!C17;PRODUCT!B:B;0))) | E4: =IF(INPUT_PRODUCT!C17="";"";VLOOKUP(INPUT_PRODUCT!C17;PRODUCT!B:C;2;FALSE)) | F4: =IF(INPUT_PRODUCT!C17="";"";INPUT_PRODUCT!J17) | G4: =IF(INPUT_PRODUCT!C17="";"";INPUT_PRODUCT!G17) | H4: =IF(INPUT_PRODUCT!C17="";"";VLOOKUP(INPUT_PRODUCT!C17;PRODUCT!B:F;5;FALSE)) | I4: =IF(INPUT_PRODUCT!C17="";"";VLOOKUP(INPUT_PRODUCT!C17;PRODUCT!B:G;6;FALSE)) | J4: =IF(INPUT_PRODUCT!C17="";"";VLOOKUP(INPUT_PRODUCT!C17;PRODUCT!B:H;7;FALSE)) | K4: =IF(INPUT_PRODUCT!C17="";"";VLOOKUP(INPUT_PRODUCT!C17;PRODUCT!B:I;8;FALSE)) | L4: =IF(INPUT_PRODUCT!C17="";"";VLOOKUP(INPUT_PRODUCT!C17;PRODUCT!B:J;9;FALSE)) | M4: =IF(INPUT_PRODUCT!C17="";"";VLOOKUP(INPUT_PRODUCT!C17;PRODUCT!B:K;10;FALSE)) | N4: =IF(INPUT_PRODUCT!C17="";"";VLOOKUP(INPUT_PRODUCT!C17;PRODUCT!B:L;11;FALSE)) | O4: =IF(INPUT_PRODUCT!C17="";"";VLOOKUP(INPUT_PRODUCT!C17;PRODUCT!B:O;14;FALSE)) | P4: =IF(INPUT_PRODUCT!C17="";"";VLOOKUP(INPUT_PRODUCT!C17;PRODUCT!B:P;15;FALSE)) | Q4: =IF(INPUT_PRODUCT!C17="";"";INPUT_PRODUCT!K17) | S4: =IF(INPUT_PRODUCT!C17="";"";IF(O4="";"";O4*(1+Q4+R4))) | T4: =IF(INPUT_PRODUCT!C17="";"";IF(S4="";"";S4*F4)) | U4: =CONFIG!$B$2 | V4: =IF(INPUT_PRODUCT!C17="";"";IF(S4="";"";S4*U4)) | W4: =IF(INPUT_PRODUCT!C17="";"";IF(T4="";"";T4*U4)) | X4: =IF(INPUT_PRODUCT!C17="";"";VLOOKUP(INPUT_PRODUCT!C17;PRODUCT!B:T;19;FALSE)) | Y4: =IF(INPUT_PRODUCT!C17="";"";INPUT_PRODUCT!L17)
A5: =IF(INPUT_PRODUCT!C18="";"";INPUT_PRODUCT!A18) | B5: =IF(INPUT_PRODUCT!C18="";"";INPUT_PRODUCT!B18) | C5: =IF(INPUT_PRODUCT!C18="";"";INPUT_PRODUCT!C18) | D5: =IF(INPUT_PRODUCT!C18="";"";INDEX(PRODUCT!A:A;MATCH(INPUT_PRODUCT!C18;PRODUCT!B:B;0))) | E5: =IF(INPUT_PRODUCT!C18="";"";VLOOKUP(INPUT_PRODUCT!C18;PRODUCT!B:C;2;FALSE)) | F5: =IF(INPUT_PRODUCT!C18="";"";INPUT_PRODUCT!J18) | G5: =IF(INPUT_PRODUCT!C18="";"";INPUT_PRODUCT!G18) | H5: =IF(INPUT_PRODUCT!C18="";"";VLOOKUP(INPUT_PRODUCT!C18;PRODUCT!B:F;5;FALSE)) | I5: =IF(INPUT_PRODUCT!C18="";"";VLOOKUP(INPUT_PRODUCT!C18;PRODUCT!B:G;6;FALSE)) | J5: =IF(INPUT_PRODUCT!C18="";"";VLOOKUP(INPUT_PRODUCT!C18;PRODUCT!B:H;7;FALSE)) | K5: =IF(INPUT_PRODUCT!C18="";"";VLOOKUP(INPUT_PRODUCT!C18;PRODUCT!B:I;8;FALSE)) | L5: =IF(INPUT_PRODUCT!C18="";"";VLOOKUP(INPUT_PRODUCT!C18;PRODUCT!B:J;9;FALSE)) | M5: =IF(INPUT_PRODUCT!C18="";"";VLOOKUP(INPUT_PRODUCT!C18;PRODUCT!B:K;10;FALSE)) | N5: =IF(INPUT_PRODUCT!C18="";"";VLOOKUP(INPUT_PRODUCT!C18;PRODUCT!B:L;11;FALSE)) | O5: =IF(INPUT_PRODUCT!C18="";"";VLOOKUP(INPUT_PRODUCT!C18;PRODUCT!B:O;14;FALSE)) | P5: =IF(INPUT_PRODUCT!C18="";"";VLOOKUP(INPUT_PRODUCT!C18;PRODUCT!B:P;15;FALSE)) | Q5: =IF(INPUT_PRODUCT!C18="";"";INPUT_PRODUCT!K18) | S5: =IF(INPUT_PRODUCT!C18="";"";IF(O5="";"";O5*(1+Q5+R5))) | T5: =IF(INPUT_PRODUCT!C18="";"";IF(S5="";"";S5*F5)) | U5: =CONFIG!$B$2 | V5: =IF(INPUT_PRODUCT!C18="";"";IF(S5="";"";S5*U5)) | W5: =IF(INPUT_PRODUCT!C18="";"";IF(T5="";"";T5*U5)) | X5: =IF(INPUT_PRODUCT!C18="";"";VLOOKUP(INPUT_PRODUCT!C18;PRODUCT!B:T;19;FALSE)) | Y5: =IF(INPUT_PRODUCT!C18="";"";INPUT_PRODUCT!L18)
A6: =IF(INPUT_PRODUCT!C19="";"";INPUT_PRODUCT!A19) | B6: =IF(INPUT_PRODUCT!C19="";"";INPUT_PRODUCT!B19) | C6: =IF(INPUT_PRODUCT!C19="";"";INPUT_PRODUCT!C19) | D6: =IF(INPUT_PRODUCT!C19="";"";INDEX(PRODUCT!A:A;MATCH(INPUT_PRODUCT!C19;PRODUCT!B:B;0))) | E6: =IF(INPUT_PRODUCT!C19="";"";VLOOKUP(INPUT_PRODUCT!C19;PRODUCT!B:C;2;FALSE)) | F6: =IF(INPUT_PRODUCT!C19="";"";INPUT_PRODUCT!J19) | G6: =IF(INPUT_PRODUCT!C19="";"";INPUT_PRODUCT!G19) | H6: =IF(INPUT_PRODUCT!C19="";"";VLOOKUP(INPUT_PRODUCT!C19;PRODUCT!B:F;5;FALSE)) | I6: =IF(INPUT_PRODUCT!C19="";"";VLOOKUP(INPUT_PRODUCT!C19;PRODUCT!B:G;6;FALSE)) | J6: =IF(INPUT_PRODUCT!C19="";"";VLOOKUP(INPUT_PRODUCT!C19;PRODUCT!B:H;7;FALSE)) | K6: =IF(INPUT_PRODUCT!C19="";"";VLOOKUP(INPUT_PRODUCT!C19;PRODUCT!B:I;8;FALSE)) | L6: =IF(INPUT_PRODUCT!C19="";"";VLOOKUP(INPUT_PRODUCT!C19;PRODUCT!B:J;9;FALSE)) | M6: =IF(INPUT_PRODUCT!C19="";"";VLOOKUP(INPUT_PRODUCT!C19;PRODUCT!B:K;10;FALSE)) | N6: =IF(INPUT_PRODUCT!C19="";"";VLOOKUP(INPUT_PRODUCT!C19;PRODUCT!B:L;11;FALSE)) | O6: =IF(INPUT_PRODUCT!C19="";"";VLOOKUP(INPUT_PRODUCT!C19;PRODUCT!B:O;14;FALSE)) | P6: =IF(INPUT_PRODUCT!C19="";"";VLOOKUP(INPUT_PRODUCT!C19;PRODUCT!B:P;15;FALSE)) | Q6: =IF(INPUT_PRODUCT!C19="";"";INPUT_PRODUCT!K19) | S6: =IF(INPUT_PRODUCT!C19="";"";IF(O6="";"";O6*(1+Q6+R6))) | T6: =IF(INPUT_PRODUCT!C19="";"";IF(S6="";"";S6*F6)) | U6: =CONFIG!$B$2 | V6: =IF(INPUT_PRODUCT!C19="";"";IF(S6="";"";S6*U6)) | W6: =IF(INPUT_PRODUCT!C19="";"";IF(T6="";"";T6*U6)) | X6: =IF(INPUT_PRODUCT!C19="";"";VLOOKUP(INPUT_PRODUCT!C19;PRODUCT!B:T;19;FALSE)) | Y6: =IF(INPUT_PRODUCT!C19="";"";INPUT_PRODUCT!L19)
A7: =IF(INPUT_PRODUCT!C20="";"";INPUT_PRODUCT!A20) | B7: =IF(INPUT_PRODUCT!C20="";"";INPUT_PRODUCT!B20) | C7: =IF(INPUT_PRODUCT!C20="";"";INPUT_PRODUCT!C20) | D7: =IF(INPUT_PRODUCT!C20="";"";INDEX(PRODUCT!A:A;MATCH(INPUT_PRODUCT!C20;PRODUCT!B:B;0))) | E7: =IF(INPUT_PRODUCT!C20="";"";VLOOKUP(INPUT_PRODUCT!C20;PRODUCT!B:C;2;FALSE)) | F7: =IF(INPUT_PRODUCT!C20="";"";INPUT_PRODUCT!J20) | G7: =IF(INPUT_PRODUCT!C20="";"";INPUT_PRODUCT!G20) | H7: =IF(INPUT_PRODUCT!C20="";"";VLOOKUP(INPUT_PRODUCT!C20;PRODUCT!B:F;5;FALSE)) | I7: =IF(INPUT_PRODUCT!C20="";"";VLOOKUP(INPUT_PRODUCT!C20;PRODUCT!B:G;6;FALSE)) | J7: =IF(INPUT_PRODUCT!C20="";"";VLOOKUP(INPUT_PRODUCT!C20;PRODUCT!B:H;7;FALSE)) | K7: =IF(INPUT_PRODUCT!C20="";"";VLOOKUP(INPUT_PRODUCT!C20;PRODUCT!B:I;8;FALSE)) | L7: =IF(INPUT_PRODUCT!C20="";"";VLOOKUP(INPUT_PRODUCT!C20;PRODUCT!B:J;9;FALSE)) | M7: =IF(INPUT_PRODUCT!C20="";"";VLOOKUP(INPUT_PRODUCT!C20;PRODUCT!B:K;10;FALSE)) | N7: =IF(INPUT_PRODUCT!C20="";"";VLOOKUP(INPUT_PRODUCT!C20;PRODUCT!B:L;11;FALSE)) | O7: =IF(INPUT_PRODUCT!C20="";"";VLOOKUP(INPUT_PRODUCT!C20;PRODUCT!B:O;14;FALSE)) | P7: =IF(INPUT_PRODUCT!C20="";"";VLOOKUP(INPUT_PRODUCT!C20;PRODUCT!B:P;15;FALSE)) | Q7: =IF(INPUT_PRODUCT!C20="";"";INPUT_PRODUCT!K20) | S7: =IF(INPUT_PRODUCT!C20="";"";IF(O7="";"";O7*(1+Q7+R7))) | T7: =IF(INPUT_PRODUCT!C20="";"";IF(S7="";"";S7*F7)) | U7: =CONFIG!$B$2 | V7: =IF(INPUT_PRODUCT!C20="";"";IF(S7="";"";S7*U7)) | W7: =IF(INPUT_PRODUCT!C20="";"";IF(T7="";"";T7*U7)) | X7: =IF(INPUT_PRODUCT!C20="";"";VLOOKUP(INPUT_PRODUCT!C20;PRODUCT!B:T;19;FALSE)) | Y7: =IF(INPUT_PRODUCT!C20="";"";INPUT_PRODUCT!L20)
A8: =IF(INPUT_PRODUCT!C21="";"";INPUT_PRODUCT!A21) | B8: =IF(INPUT_PRODUCT!C21="";"";INPUT_PRODUCT!B21) | C8: =IF(INPUT_PRODUCT!C21="";"";INPUT_PRODUCT!C21) | D8: =IF(INPUT_PRODUCT!C21="";"";INDEX(PRODUCT!A:A;MATCH(INPUT_PRODUCT!C21;PRODUCT!B:B;0))) | E8: =IF(INPUT_PRODUCT!C21="";"";VLOOKUP(INPUT_PRODUCT!C21;PRODUCT!B:C;2;FALSE)) | F8: =IF(INPUT_PRODUCT!C21="";"";INPUT_PRODUCT!J21) | G8: =IF(INPUT_PRODUCT!C21="";"";INPUT_PRODUCT!G21) | H8: =IF(INPUT_PRODUCT!C21="";"";VLOOKUP(INPUT_PRODUCT!C21;PRODUCT!B:F;5;FALSE)) | I8: =IF(INPUT_PRODUCT!C21="";"";VLOOKUP(INPUT_PRODUCT!C21;PRODUCT!B:G;6;FALSE)) | J8: =IF(INPUT_PRODUCT!C21="";"";VLOOKUP(INPUT_PRODUCT!C21;PRODUCT!B:H;7;FALSE)) | K8: =IF(INPUT_PRODUCT!C21="";"";VLOOKUP(INPUT_PRODUCT!C21;PRODUCT!B:I;8;FALSE)) | L8: =IF(INPUT_PRODUCT!C21="";"";VLOOKUP(INPUT_PRODUCT!C21;PRODUCT!B:J;9;FALSE)) | M8: =IF(INPUT_PRODUCT!C21="";"";VLOOKUP(INPUT_PRODUCT!C21;PRODUCT!B:K;10;FALSE)) | N8: =IF(INPUT_PRODUCT!C21="";"";VLOOKUP(INPUT_PRODUCT!C21;PRODUCT!B:L;11;FALSE)) | O8: =IF(INPUT_PRODUCT!C21="";"";VLOOKUP(INPUT_PRODUCT!C21;PRODUCT!B:O;14;FALSE)) | P8: =IF(INPUT_PRODUCT!C21="";"";VLOOKUP(INPUT_PRODUCT!C21;PRODUCT!B:P;15;FALSE)) | Q8: =IF(INPUT_PRODUCT!C21="";"";INPUT_PRODUCT!K21) | S8: =IF(INPUT_PRODUCT!C21="";"";IF(O8="";"";O8*(1+Q8+R8))) | T8: =IF(INPUT_PRODUCT!C21="";"";IF(S8="";"";S8*F8)) | U8: =CONFIG!$B$2 | V8: =IF(INPUT_PRODUCT!C21="";"";IF(S8="";"";S8*U8)) | W8: =IF(INPUT_PRODUCT!C21="";"";IF(T8="";"";T8*U8)) | X8: =IF(INPUT_PRODUCT!C21="";"";VLOOKUP(INPUT_PRODUCT!C21;PRODUCT!B:T;19;FALSE)) | Y8: =IF(INPUT_PRODUCT!C21="";"";INPUT_PRODUCT!L21)
A9: =IF(INPUT_PRODUCT!C22="";"";INPUT_PRODUCT!A22) | B9: =IF(INPUT_PRODUCT!C22="";"";INPUT_PRODUCT!B22) | C9: =IF(INPUT_PRODUCT!C22="";"";INPUT_PRODUCT!C22) | D9: =IF(INPUT_PRODUCT!C22="";"";INDEX(PRODUCT!A:A;MATCH(INPUT_PRODUCT!C22;PRODUCT!B:B;0))) | E9: =IF(INPUT_PRODUCT!C22="";"";VLOOKUP(INPUT_PRODUCT!C22;PRODUCT!B:C;2;FALSE)) | F9: =IF(INPUT_PRODUCT!C22="";"";INPUT_PRODUCT!J22) | G9: =IF(INPUT_PRODUCT!C22="";"";INPUT_PRODUCT!G22) | H9: =IF(INPUT_PRODUCT!C22="";"";VLOOKUP(INPUT_PRODUCT!C22;PRODUCT!B:F;5;FALSE)) | I9: =IF(INPUT_PRODUCT!C22="";"";VLOOKUP(INPUT_PRODUCT!C22;PRODUCT!B:G;6;FALSE)) | J9: =IF(INPUT_PRODUCT!C22="";"";VLOOKUP(INPUT_PRODUCT!C22;PRODUCT!B:H;7;FALSE)) | K9: =IF(INPUT_PRODUCT!C22="";"";VLOOKUP(INPUT_PRODUCT!C22;PRODUCT!B:I;8;FALSE)) | L9: =IF(INPUT_PRODUCT!C22="";"";VLOOKUP(INPUT_PRODUCT!C22;PRODUCT!B:J;9;FALSE)) | M9: =IF(INPUT_PRODUCT!C22="";"";VLOOKUP(INPUT_PRODUCT!C22;PRODUCT!B:K;10;FALSE)) | N9: =IF(INPUT_PRODUCT!C22="";"";VLOOKUP(INPUT_PRODUCT!C22;PRODUCT!B:L;11;FALSE)) | O9: =IF(INPUT_PRODUCT!C22="";"";VLOOKUP(INPUT_PRODUCT!C22;PRODUCT!B:O;14;FALSE)) | P9: =IF(INPUT_PRODUCT!C22="";"";VLOOKUP(INPUT_PRODUCT!C22;PRODUCT!B:P;15;FALSE)) | Q9: =IF(INPUT_PRODUCT!C22="";"";INPUT_PRODUCT!K22) | S9: =IF(INPUT_PRODUCT!C22="";"";IF(O9="";"";O9*(1+Q9+R9))) | T9: =IF(INPUT_PRODUCT!C22="";"";IF(S9="";"";S9*F9)) | U9: =CONFIG!$B$2 | V9: =IF(INPUT_PRODUCT!C22="";"";IF(S9="";"";S9*U9)) | W9: =IF(INPUT_PRODUCT!C22="";"";IF(T9="";"";T9*U9)) | X9: =IF(INPUT_PRODUCT!C22="";"";VLOOKUP(INPUT_PRODUCT!C22;PRODUCT!B:T;19;FALSE)) | Y9: =IF(INPUT_PRODUCT!C22="";"";INPUT_PRODUCT!L22)
A10: =IF(INPUT_PRODUCT!C23="";"";INPUT_PRODUCT!A23) | B10: =IF(INPUT_PRODUCT!C23="";"";INPUT_PRODUCT!B23) | C10: =IF(INPUT_PRODUCT!C23="";"";INPUT_PRODUCT!C23) | D10: =IF(INPUT_PRODUCT!C23="";"";INDEX(PRODUCT!A:A;MATCH(INPUT_PRODUCT!C23;PRODUCT!B:B;0))) | E10: =IF(INPUT_PRODUCT!C23="";"";VLOOKUP(INPUT_PRODUCT!C23;PRODUCT!B:C;2;FALSE)) | F10: =IF(INPUT_PRODUCT!C23="";"";INPUT_PRODUCT!J23) | G10: =IF(INPUT_PRODUCT!C23="";"";INPUT_PRODUCT!G23) | H10: =IF(INPUT_PRODUCT!C23="";"";VLOOKUP(INPUT_PRODUCT!C23;PRODUCT!B:F;5;FALSE)) | I10: =IF(INPUT_PRODUCT!C23="";"";VLOOKUP(INPUT_PRODUCT!C23;PRODUCT!B:G;6;FALSE)) | J10: =IF(INPUT_PRODUCT!C23="";"";VLOOKUP(INPUT_PRODUCT!C23;PRODUCT!B:H;7;FALSE)) | K10: =IF(INPUT_PRODUCT!C23="";"";VLOOKUP(INPUT_PRODUCT!C23;PRODUCT!B:I;8;FALSE)) | L10: =IF(INPUT_PRODUCT!C23="";"";VLOOKUP(INPUT_PRODUCT!C23;PRODUCT!B:J;9;FALSE)) | M10: =IF(INPUT_PRODUCT!C23="";"";VLOOKUP(INPUT_PRODUCT!C23;PRODUCT!B:K;10;FALSE)) | N10: =IF(INPUT_PRODUCT!C23="";"";VLOOKUP(INPUT_PRODUCT!C23;PRODUCT!B:L;11;FALSE)) | O10: =IF(INPUT_PRODUCT!C23="";"";VLOOKUP(INPUT_PRODUCT!C23;PRODUCT!B:O;14;FALSE)) | P10: =IF(INPUT_PRODUCT!C23="";"";VLOOKUP(INPUT_PRODUCT!C23;PRODUCT!B:P;15;FALSE)) | Q10: =IF(INPUT_PRODUCT!C23="";"";INPUT_PRODUCT!K23) | S10: =IF(INPUT_PRODUCT!C23="";"";IF(O10="";"";O10*(1+Q10+R10))) | T10: =IF(INPUT_PRODUCT!C23="";"";IF(S10="";"";S10*F10)) | U10: =CONFIG!$B$2 | V10: =IF(INPUT_PRODUCT!C23="";"";IF(S10="";"";S10*U10)) | W10: =IF(INPUT_PRODUCT!C23="";"";IF(T10="";"";T10*U10)) | X10: =IF(INPUT_PRODUCT!C23="";"";VLOOKUP(INPUT_PRODUCT!C23;PRODUCT!B:T;19;FALSE)) | Y10: =IF(INPUT_PRODUCT!C23="";"";INPUT_PRODUCT!L23)
A11: =IF(INPUT_PRODUCT!C24="";"";INPUT_PRODUCT!A24) | B11: =IF(INPUT_PRODUCT!C24="";"";INPUT_PRODUCT!B24) | C11: =IF(INPUT_PRODUCT!C24="";"";INPUT_PRODUCT!C24) | D11: =IF(INPUT_PRODUCT!C24="";"";INDEX(PRODUCT!A:A;MATCH(INPUT_PRODUCT!C24;PRODUCT!B:B;0))) | E11: =IF(INPUT_PRODUCT!C24="";"";VLOOKUP(INPUT_PRODUCT!C24;PRODUCT!B:C;2;FALSE)) | F11: =IF(INPUT_PRODUCT!C24="";"";INPUT_PRODUCT!J24) | G11: =IF(INPUT_PRODUCT!C24="";"";INPUT_PRODUCT!G24) | H11: =IF(INPUT_PRODUCT!C24="";"";VLOOKUP(INPUT_PRODUCT!C24;PRODUCT!B:F;5;FALSE)) | I11: =IF(INPUT_PRODUCT!C24="";"";VLOOKUP(INPUT_PRODUCT!C24;PRODUCT!B:G;6;FALSE)) | J11: =IF(INPUT_PRODUCT!C24="";"";VLOOKUP(INPUT_PRODUCT!C24;PRODUCT!B:H;7;FALSE)) | K11: =IF(INPUT_PRODUCT!C24="";"";VLOOKUP(INPUT_PRODUCT!C24;PRODUCT!B:I;8;FALSE)) | L11: =IF(INPUT_PRODUCT!C24="";"";VLOOKUP(INPUT_PRODUCT!C24;PRODUCT!B:J;9;FALSE)) | M11: =IF(INPUT_PRODUCT!C24="";"";VLOOKUP(INPUT_PRODUCT!C24;PRODUCT!B:K;10;FALSE)) | N11: =IF(INPUT_PRODUCT!C24="";"";VLOOKUP(INPUT_PRODUCT!C24;PRODUCT!B:L;11;FALSE)) | O11: =IF(INPUT_PRODUCT!C24="";"";VLOOKUP(INPUT_PRODUCT!C24;PRODUCT!B:O;14;FALSE)) | P11: =IF(INPUT_PRODUCT!C24="";"";VLOOKUP(INPUT_PRODUCT!C24;PRODUCT!B:P;15;FALSE)) | Q11: =IF(INPUT_PRODUCT!C24="";"";INPUT_PRODUCT!K24) | S11: =IF(INPUT_PRODUCT!C24="";"";IF(O11="";"";O11*(1+Q11+R11))) | T11: =IF(INPUT_PRODUCT!C24="";"";IF(S11="";"";S11*F11)) | U11: =CONFIG!$B$2 | V11: =IF(INPUT_PRODUCT!C24="";"";IF(S11="";"";S11*U11)) | W11: =IF(INPUT_PRODUCT!C24="";"";IF(T11="";"";T11*U11)) | X11: =IF(INPUT_PRODUCT!C24="";"";VLOOKUP(INPUT_PRODUCT!C24;PRODUCT!B:T;19;FALSE)) | Y11: =IF(INPUT_PRODUCT!C24="";"";INPUT_PRODUCT!L24)
A12: =IF(INPUT_PRODUCT!C25="";"";INPUT_PRODUCT!A25) | B12: =IF(INPUT_PRODUCT!C25="";"";INPUT_PRODUCT!B25) | C12: =IF(INPUT_PRODUCT!C25="";"";INPUT_PRODUCT!C25) | D12: =IF(INPUT_PRODUCT!C25="";"";INDEX(PRODUCT!A:A;MATCH(INPUT_PRODUCT!C25;PRODUCT!B:B;0))) | E12: =IF(INPUT_PRODUCT!C25="";"";VLOOKUP(INPUT_PRODUCT!C25;PRODUCT!B:C;2;FALSE)) | F12: =IF(INPUT_PRODUCT!C25="";"";INPUT_PRODUCT!J25) | G12: =IF(INPUT_PRODUCT!C25="";"";INPUT_PRODUCT!G25) | H12: =IF(INPUT_PRODUCT!C25="";"";VLOOKUP(INPUT_PRODUCT!C25;PRODUCT!B:F;5;FALSE)) | I12: =IF(INPUT_PRODUCT!C25="";"";VLOOKUP(INPUT_PRODUCT!C25;PRODUCT!B:G;6;FALSE)) | J12: =IF(INPUT_PRODUCT!C25="";"";VLOOKUP(INPUT_PRODUCT!C25;PRODUCT!B:H;7;FALSE)) | K12: =IF(INPUT_PRODUCT!C25="";"";VLOOKUP(INPUT_PRODUCT!C25;PRODUCT!B:I;8;FALSE)) | L12: =IF(INPUT_PRODUCT!C25="";"";VLOOKUP(INPUT_PRODUCT!C25;PRODUCT!B:J;9;FALSE)) | M12: =IF(INPUT_PRODUCT!C25="";"";VLOOKUP(INPUT_PRODUCT!C25;PRODUCT!B:K;10;FALSE)) | N12: =IF(INPUT_PRODUCT!C25="";"";VLOOKUP(INPUT_PRODUCT!C25;PRODUCT!B:L;11;FALSE)) | O12: =IF(INPUT_PRODUCT!C25="";"";VLOOKUP(INPUT_PRODUCT!C25;PRODUCT!B:O;14;FALSE)) | P12: =IF(INPUT_PRODUCT!C25="";"";VLOOKUP(INPUT_PRODUCT!C25;PRODUCT!B:P;15;FALSE)) | Q12: =IF(INPUT_PRODUCT!C25="";"";INPUT_PRODUCT!K25) | S12: =IF(INPUT_PRODUCT!C25="";"";IF(O12="";"";O12*(1+Q12+R12))) | T12: =IF(INPUT_PRODUCT!C25="";"";IF(S12="";"";S12*F12)) | U12: =CONFIG!$B$2 | V12: =IF(INPUT_PRODUCT!C25="";"";IF(S12="";"";S12*U12)) | W12: =IF(INPUT_PRODUCT!C25="";"";IF(T12="";"";T12*U12)) | X12: =IF(INPUT_PRODUCT!C25="";"";VLOOKUP(INPUT_PRODUCT!C25;PRODUCT!B:T;19;FALSE)) | Y12: =IF(INPUT_PRODUCT!C25="";"";INPUT_PRODUCT!L25)
A13: =IF(INPUT_PRODUCT!C26="";"";INPUT_PRODUCT!A26) | B13: =IF(INPUT_PRODUCT!C26="";"";INPUT_PRODUCT!B26) | C13: =IF(INPUT_PRODUCT!C26="";"";INPUT_PRODUCT!C26) | D13: =IF(INPUT_PRODUCT!C26="";"";INDEX(PRODUCT!A:A;MATCH(INPUT_PRODUCT!C26;PRODUCT!B:B;0))) | E13: =IF(INPUT_PRODUCT!C26="";"";VLOOKUP(INPUT_PRODUCT!C26;PRODUCT!B:C;2;FALSE)) | F13: =IF(INPUT_PRODUCT!C26="";"";INPUT_PRODUCT!J26) | G13: =IF(INPUT_PRODUCT!C26="";"";INPUT_PRODUCT!G26) | H13: =IF(INPUT_PRODUCT!C26="";"";VLOOKUP(INPUT_PRODUCT!C26;PRODUCT!B:F;5;FALSE)) | I13: =IF(INPUT_PRODUCT!C26="";"";VLOOKUP(INPUT_PRODUCT!C26;PRODUCT!B:G;6;FALSE)) | J13: =IF(INPUT_PRODUCT!C26="";"";VLOOKUP(INPUT_PRODUCT!C26;PRODUCT!B:H;7;FALSE)) | K13: =IF(INPUT_PRODUCT!C26="";"";VLOOKUP(INPUT_PRODUCT!C26;PRODUCT!B:I;8;FALSE)) | L13: =IF(INPUT_PRODUCT!C26="";"";VLOOKUP(INPUT_PRODUCT!C26;PRODUCT!B:J;9;FALSE)) | M13: =IF(INPUT_PRODUCT!C26="";"";VLOOKUP(INPUT_PRODUCT!C26;PRODUCT!B:K;10;FALSE)) | N13: =IF(INPUT_PRODUCT!C26="";"";VLOOKUP(INPUT_PRODUCT!C26;PRODUCT!B:L;11;FALSE)) | O13: =IF(INPUT_PRODUCT!C26="";"";VLOOKUP(INPUT_PRODUCT!C26;PRODUCT!B:O;14;FALSE)) | P13: =IF(INPUT_PRODUCT!C26="";"";VLOOKUP(INPUT_PRODUCT!C26;PRODUCT!B:P;15;FALSE)) | Q13: =IF(INPUT_PRODUCT!C26="";"";INPUT_PRODUCT!K26) | S13: =IF(INPUT_PRODUCT!C26="";"";IF(O13="";"";O13*(1+Q13+R13))) | T13: =IF(INPUT_PRODUCT!C26="";"";IF(S13="";"";S13*F13)) | U13: =CONFIG!$B$2 | V13: =IF(INPUT_PRODUCT!C26="";"";IF(S13="";"";S13*U13)) | W13: =IF(INPUT_PRODUCT!C26="";"";IF(T13="";"";T13*U13)) | X13: =IF(INPUT_PRODUCT!C26="";"";VLOOKUP(INPUT_PRODUCT!C26;PRODUCT!B:T;19;FALSE)) | Y13: =IF(INPUT_PRODUCT!C26="";"";INPUT_PRODUCT!L26)
... A199: =IF(INPUT_PRODUCT!C212="";"";INPUT_PRODUCT!A212) | B199: =IF(INPUT_PRODUCT!C212="";"";INPUT_PRODUCT!B212) | C199: =IF(INPUT_PRODUCT!C212="";"";INPUT_PRODUCT!C212) | D199: =IF(INPUT_PRODUCT!C212="";"";INDEX(PRODUCT!A:A;MATCH(INPUT_PRODUCT!C212;PRODUCT!B:B;0))) | E199: =IF(INPUT_PRODUCT!C212="";"";VLOOKUP(INPUT_PRODUCT!C212;PRODUCT!B:C;2;FALSE)) | F199: =IF(INPUT_PRODUCT!C212="";"";INPUT_PRODUCT!J212) | G199: =IF(INPUT_PRODUCT!C212="";"";INPUT_PRODUCT!G212) | H199: =IF(INPUT_PRODUCT!C212="";"";VLOOKUP(INPUT_PRODUCT!C212;PRODUCT!B:F;5;FALSE)) | I199: =IF(INPUT_PRODUCT!C212="";"";VLOOKUP(INPUT_PRODUCT!C212;PRODUCT!B:G;6;FALSE)) | J199: =IF(INPUT_PRODUCT!C212="";"";VLOOKUP(INPUT_PRODUCT!C212;PRODUCT!B:H;7;FALSE)) | K199: =IF(INPUT_PRODUCT!C212="";"";VLOOKUP(INPUT_PRODUCT!C212;PRODUCT!B:I;8;FALSE)) | L199: =IF(INPUT_PRODUCT!C212="";"";VLOOKUP(INPUT_PRODUCT!C212;PRODUCT!B:J;9;FALSE)) | M199: =IF(INPUT_PRODUCT!C212="";"";VLOOKUP(INPUT_PRODUCT!C212;PRODUCT!B:K;10;FALSE)) | N199: =IF(INPUT_PRODUCT!C212="";"";VLOOKUP(INPUT_PRODUCT!C212;PRODUCT!B:L;11;FALSE)) | O199: =IF(INPUT_PRODUCT!C212="";"";VLOOKUP(INPUT_PRODUCT!C212;PRODUCT!B:O;14;FALSE)) | P199: =IF(INPUT_PRODUCT!C212="";"";VLOOKUP(INPUT_PRODUCT!C212;PRODUCT!B:P;15;FALSE)) | Q199: =IF(INPUT_PRODUCT!C212="";"";INPUT_PRODUCT!K212) | S199: =IF(INPUT_PRODUCT!C212="";"";IF(O199="";"";O199*(1+Q199+R199))) | T199: =IF(INPUT_PRODUCT!C212="";"";IF(S199="";"";S199*F199)) | U199: =CONFIG!$B$2 | V199: =IF(INPUT_PRODUCT!C212="";"";IF(S199="";"";S199*U199)) | W199: =IF(INPUT_PRODUCT!C212="";"";IF(T199="";"";T199*U199)) | X199: =IF(INPUT_PRODUCT!C212="";"";VLOOKUP(INPUT_PRODUCT!C212;PRODUCT!B:T;19;FALSE)) | Y199: =IF(INPUT_PRODUCT!C212="";"";INPUT_PRODUCT!L212)

Sheet LOGISTIC
A1: CLIENTE | B1: PROYECTO | C1: N_COTIZACION | D1: EXPORTADOR | E1: IMPORTADOR | F1: ORIGEN | G1: INCOTERM | H1: PUERTO_SALIDA | I1: PUERTO_DESTINO | J1: REGIMEN | K1: SKU_FASSA | L1: NOMBRE_PRODUCTO | M1: HS_CODE | N1: NORMA | O1: USO | P1: DIMENSION | Q1: ESPESOR | R1: UNIDADES_SUMINISTRO | S1: UDS_POR_PALET | T1: M2_UNIDAD | U1: M2_PALE | V1: PESO_NETO_UNIDAD | W1: PESO_NETO_PALET | X1: TOTAL_PALETS | Y1: TOTAL_M2 | Z1: TOTAL_PESO_NETO | AA1: TOTAL_PESO_BRUTO | AB1: TIPO_CONTENEDOR | AC1: PALLETS_POR_CONTENEDOR | AD1: PESO_UTIL_CONTENEDOR | AE1: N_CONTENEDORES | AF1: VALOR_MERCANCIA_EUR | AG1: VALOR_LOGISTICO_EUR | AH1: VALOR_CIF_EUR | AI1: OBSERVACIONES_LOGISTICA
A2: Cliente | B2: =INPUT_PRODUCT!B1
A3: Proyecto | B3: =INPUT_PRODUCT!B2
A4: N_Cotización | B4: =INPUT_PRODUCT!B6
A5: Incoterm | B5: =INPUT_PRODUCT!B7
A6: Origen | B6: Tarancón, España
A8: =INPUT_PRODUCT!B1 | B8: =INPUT_PRODUCT!B2 | C8: =INPUT_PRODUCT!B6 | D8: Arias Group Caribe SRL | F8: Tarancón, España | G8: =INPUT_PRODUCT!B7 | K8: =IF(PRODUCT_CALCULATION!B2="SI";PRODUCT_CALCULATION!C2;"") | L8: =IF(PRODUCT_CALCULATION!B2="SI";PRODUCT_CALCULATION!E2;"") | M8: =IF(PRODUCT_CALCULATION!C2="";"";VLOOKUP(PRODUCT_CALCULATION!C2;PRODUCT!B:Q;16;FALSE)) | N8: =IF(PRODUCT_CALCULATION!C2="";"";VLOOKUP(PRODUCT_CALCULATION!C2;PRODUCT!B:R;17;FALSE)) | O8: =IF(PRODUCT_CALCULATION!C2="";"";VLOOKUP(PRODUCT_CALCULATION!C2;PRODUCT!B:S;18;FALSE)) | P8: =IF(PRODUCT_CALCULATION!C2="";"";VLOOKUP(PRODUCT_CALCULATION!C2;PRODUCT!B:D;3;FALSE)) | Q8: =IF(PRODUCT_CALCULATION!C2="";"";VLOOKUP(PRODUCT_CALCULATION!C2;PRODUCT!B:E;4;FALSE)) | R8: =IF(PRODUCT_CALCULATION!B2="SI";PRODUCT_CALCULATION!F2;"") | S8: =IF(PRODUCT_CALCULATION!B2="SI";PRODUCT_CALCULATION!K2;"") | T8: =IF(PRODUCT_CALCULATION!B2="SI";PRODUCT_CALCULATION!J2;"") | U8: =IF(PRODUCT_CALCULATION!B2="SI";PRODUCT_CALCULATION!N2;"") | V8: =IF(PRODUCT_CALCULATION!B2="SI";PRODUCT_CALCULATION!L2;"") | W8: =IF(PRODUCT_CALCULATION!B2="SI";PRODUCT_CALCULATION!M2;"") | X8: =IF(R2="";"";CEILING(R2/S2;1)) | Y8: =IF(R2="";"";R2*T2) | Z8: =IF(R2="";"";R2*V2)
A9: =INPUT_PRODUCT!B1 | B9: =INPUT_PRODUCT!B2 | C9: =INPUT_PRODUCT!B6 | D9: Arias Group Caribe SRL | F9: Tarancón, España | G9: =INPUT_PRODUCT!B7 | K9: =IF(PRODUCT_CALCULATION!B3="SI";PRODUCT_CALCULATION!C3;"") | L9: =IF(PRODUCT_CALCULATION!B3="SI";PRODUCT_CALCULATION!E3;"") | M9: =IF(PRODUCT_CALCULATION!C3="";"";VLOOKUP(PRODUCT_CALCULATION!C3;PRODUCT!B:Q;16;FALSE)) | N9: =IF(PRODUCT_CALCULATION!C3="";"";VLOOKUP(PRODUCT_CALCULATION!C3;PRODUCT!B:R;17;FALSE)) | O9: =IF(PRODUCT_CALCULATION!C3="";"";VLOOKUP(PRODUCT_CALCULATION!C3;PRODUCT!B:S;18;FALSE)) | P9: =IF(PRODUCT_CALCULATION!C3="";"";VLOOKUP(PRODUCT_CALCULATION!C3;PRODUCT!B:D;3;FALSE)) | Q9: =IF(PRODUCT_CALCULATION!C3="";"";VLOOKUP(PRODUCT_CALCULATION!C3;PRODUCT!B:E;4;FALSE)) | R9: =IF(PRODUCT_CALCULATION!B3="SI";PRODUCT_CALCULATION!F3;"") | S9: =IF(PRODUCT_CALCULATION!B3="SI";PRODUCT_CALCULATION!K3;"") | T9: =IF(PRODUCT_CALCULATION!B3="SI";PRODUCT_CALCULATION!J3;"") | U9: =IF(PRODUCT_CALCULATION!B3="SI";PRODUCT_CALCULATION!N3;"") | V9: =IF(PRODUCT_CALCULATION!B3="SI";PRODUCT_CALCULATION!L3;"") | W9: =IF(PRODUCT_CALCULATION!B3="SI";PRODUCT_CALCULATION!M3;"") | X9: =IF(R3="";"";CEILING(R3/S3;1)) | Y9: =IF(R3="";"";R3*T3) | Z9: =IF(R3="";"";R3*V3)
A10: =INPUT_PRODUCT!B1 | B10: =INPUT_PRODUCT!B2 | C10: =INPUT_PRODUCT!B6 | D10: Arias Group Caribe SRL | F10: Tarancón, España | G10: =INPUT_PRODUCT!B7 | K10: =IF(PRODUCT_CALCULATION!B4="SI";PRODUCT_CALCULATION!C4;"") | L10: =IF(PRODUCT_CALCULATION!B4="SI";PRODUCT_CALCULATION!E4;"") | M10: =IF(PRODUCT_CALCULATION!C4="";"";VLOOKUP(PRODUCT_CALCULATION!C4;PRODUCT!B:Q;16;FALSE)) | N10: =IF(PRODUCT_CALCULATION!C4="";"";VLOOKUP(PRODUCT_CALCULATION!C4;PRODUCT!B:R;17;FALSE)) | O10: =IF(PRODUCT_CALCULATION!C4="";"";VLOOKUP(PRODUCT_CALCULATION!C4;PRODUCT!B:S;18;FALSE)) | P10: =IF(PRODUCT_CALCULATION!C4="";"";VLOOKUP(PRODUCT_CALCULATION!C4;PRODUCT!B:D;3;FALSE)) | Q10: =IF(PRODUCT_CALCULATION!C4="";"";VLOOKUP(PRODUCT_CALCULATION!C4;PRODUCT!B:E;4;FALSE)) | R10: =IF(PRODUCT_CALCULATION!B4="SI";PRODUCT_CALCULATION!F4;"") | S10: =IF(PRODUCT_CALCULATION!B4="SI";PRODUCT_CALCULATION!K4;"") | T10: =IF(PRODUCT_CALCULATION!B4="SI";PRODUCT_CALCULATION!J4;"") | U10: =IF(PRODUCT_CALCULATION!B4="SI";PRODUCT_CALCULATION!N4;"") | V10: =IF(PRODUCT_CALCULATION!B4="SI";PRODUCT_CALCULATION!L4;"") | W10: =IF(PRODUCT_CALCULATION!B4="SI";PRODUCT_CALCULATION!M4;"") | X10: =IF(R4="";"";CEILING(R4/S4;1)) | Y10: =IF(R4="";"";R4*T4) | Z10: =IF(R4="";"";R4*V4)
A11: =INPUT_PRODUCT!B1 | B11: =INPUT_PRODUCT!B2 | C11: =INPUT_PRODUCT!B6 | D11: Arias Group Caribe SRL | F11: Tarancón, España | G11: =INPUT_PRODUCT!B7 | K11: =IF(PRODUCT_CALCULATION!B5="SI";PRODUCT_CALCULATION!C5;"") | L11: =IF(PRODUCT_CALCULATION!B5="SI";PRODUCT_CALCULATION!E5;"") | M11: =IF(PRODUCT_CALCULATION!C5="";"";VLOOKUP(PRODUCT_CALCULATION!C5;PRODUCT!B:Q;16;FALSE)) | N11: =IF(PRODUCT_CALCULATION!C5="";"";VLOOKUP(PRODUCT_CALCULATION!C5;PRODUCT!B:R;17;FALSE)) | O11: =IF(PRODUCT_CALCULATION!C5="";"";VLOOKUP(PRODUCT_CALCULATION!C5;PRODUCT!B:S;18;FALSE)) | P11: =IF(PRODUCT_CALCULATION!C5="";"";VLOOKUP(PRODUCT_CALCULATION!C5;PRODUCT!B:D;3;FALSE)) | Q11: =IF(PRODUCT_CALCULATION!C5="";"";VLOOKUP(PRODUCT_CALCULATION!C5;PRODUCT!B:E;4;FALSE)) | R11: =IF(PRODUCT_CALCULATION!B5="SI";PRODUCT_CALCULATION!F5;"") | S11: =IF(PRODUCT_CALCULATION!B5="SI";PRODUCT_CALCULATION!K5;"") | T11: =IF(PRODUCT_CALCULATION!B5="SI";PRODUCT_CALCULATION!J5;"") | U11: =IF(PRODUCT_CALCULATION!B5="SI";PRODUCT_CALCULATION!N5;"") | V11: =IF(PRODUCT_CALCULATION!B5="SI";PRODUCT_CALCULATION!L5;"") | W11: =IF(PRODUCT_CALCULATION!B5="SI";PRODUCT_CALCULATION!M5;"") | X11: =IF(R5="";"";CEILING(R5/S5;1)) | Y11: =IF(R5="";"";R5*T5) | Z11: =IF(R5="";"";R5*V5)
A12: =INPUT_PRODUCT!B1 | B12: =INPUT_PRODUCT!B2 | C12: =INPUT_PRODUCT!B6 | D12: Arias Group Caribe SRL | F12: Tarancón, España | G12: =INPUT_PRODUCT!B7 | K12: =IF(PRODUCT_CALCULATION!B6="SI";PRODUCT_CALCULATION!C6;"") | L12: =IF(PRODUCT_CALCULATION!B6="SI";PRODUCT_CALCULATION!E6;"") | M12: =IF(PRODUCT_CALCULATION!C6="";"";VLOOKUP(PRODUCT_CALCULATION!C6;PRODUCT!B:Q;16;FALSE)) | N12: =IF(PRODUCT_CALCULATION!C6="";"";VLOOKUP(PRODUCT_CALCULATION!C6;PRODUCT!B:R;17;FALSE)) | O12: =IF(PRODUCT_CALCULATION!C6="";"";VLOOKUP(PRODUCT_CALCULATION!C6;PRODUCT!B:S;18;FALSE)) | P12: =IF(PRODUCT_CALCULATION!C6="";"";VLOOKUP(PRODUCT_CALCULATION!C6;PRODUCT!B:D;3;FALSE)) | Q12: =IF(PRODUCT_CALCULATION!C6="";"";VLOOKUP(PRODUCT_CALCULATION!C6;PRODUCT!B:E;4;FALSE)) | R12: =IF(PRODUCT_CALCULATION!B6="SI";PRODUCT_CALCULATION!F6;"") | S12: =IF(PRODUCT_CALCULATION!B6="SI";PRODUCT_CALCULATION!K6;"") | T12: =IF(PRODUCT_CALCULATION!B6="SI";PRODUCT_CALCULATION!J6;"") | U12: =IF(PRODUCT_CALCULATION!B6="SI";PRODUCT_CALCULATION!N6;"") | V12: =IF(PRODUCT_CALCULATION!B6="SI";PRODUCT_CALCULATION!L6;"") | W12: =IF(PRODUCT_CALCULATION!B6="SI";PRODUCT_CALCULATION!M6;"") | X12: =IF(R6="";"";CEILING(R6/S6;1)) | Y12: =IF(R6="";"";R6*T6) | Z12: =IF(R6="";"";R6*V6)
A13: =INPUT_PRODUCT!B1 | B13: =INPUT_PRODUCT!B2 | C13: =INPUT_PRODUCT!B6 | D13: Arias Group Caribe SRL | F13: Tarancón, España | G13: =INPUT_PRODUCT!B7 | K13: =IF(PRODUCT_CALCULATION!B7="SI";PRODUCT_CALCULATION!C7;"") | L13: =IF(PRODUCT_CALCULATION!B7="SI";PRODUCT_CALCULATION!E7;"") | M13: =IF(PRODUCT_CALCULATION!C7="";"";VLOOKUP(PRODUCT_CALCULATION!C7;PRODUCT!B:Q;16;FALSE)) | N13: =IF(PRODUCT_CALCULATION!C7="";"";VLOOKUP(PRODUCT_CALCULATION!C7;PRODUCT!B:R;17;FALSE)) | O13: =IF(PRODUCT_CALCULATION!C7="";"";VLOOKUP(PRODUCT_CALCULATION!C7;PRODUCT!B:S;18;FALSE)) | P13: =IF(PRODUCT_CALCULATION!C7="";"";VLOOKUP(PRODUCT_CALCULATION!C7;PRODUCT!B:D;3;FALSE)) | Q13: =IF(PRODUCT_CALCULATION!C7="";"";VLOOKUP(PRODUCT_CALCULATION!C7;PRODUCT!B:E;4;FALSE)) | R13: =IF(PRODUCT_CALCULATION!B7="SI";PRODUCT_CALCULATION!F7;"") | S13: =IF(PRODUCT_CALCULATION!B7="SI";PRODUCT_CALCULATION!K7;"") | T13: =IF(PRODUCT_CALCULATION!B7="SI";PRODUCT_CALCULATION!J7;"") | U13: =IF(PRODUCT_CALCULATION!B7="SI";PRODUCT_CALCULATION!N7;"") | V13: =IF(PRODUCT_CALCULATION!B7="SI";PRODUCT_CALCULATION!L7;"") | W13: =IF(PRODUCT_CALCULATION!B7="SI";PRODUCT_CALCULATION!M7;"") | X13: =IF(R7="";"";CEILING(R7/S7;1)) | Y13: =IF(R7="";"";R7*T7) | Z13: =IF(R7="";"";R7*V7)
A14: =INPUT_PRODUCT!B1 | B14: =INPUT_PRODUCT!B2 | C14: =INPUT_PRODUCT!B6 | D14: Arias Group Caribe SRL | F14: Tarancón, España | G14: =INPUT_PRODUCT!B7 | K14: =IF(PRODUCT_CALCULATION!B8="SI";PRODUCT_CALCULATION!C8;"") | L14: =IF(PRODUCT_CALCULATION!B8="SI";PRODUCT_CALCULATION!E8;"") | M14: =IF(PRODUCT_CALCULATION!C8="";"";VLOOKUP(PRODUCT_CALCULATION!C8;PRODUCT!B:Q;16;FALSE)) | N14: =IF(PRODUCT_CALCULATION!C8="";"";VLOOKUP(PRODUCT_CALCULATION!C8;PRODUCT!B:R;17;FALSE)) | O14: =IF(PRODUCT_CALCULATION!C8="";"";VLOOKUP(PRODUCT_CALCULATION!C8;PRODUCT!B:S;18;FALSE)) | P14: =IF(PRODUCT_CALCULATION!C8="";"";VLOOKUP(PRODUCT_CALCULATION!C8;PRODUCT!B:D;3;FALSE)) | Q14: =IF(PRODUCT_CALCULATION!C8="";"";VLOOKUP(PRODUCT_CALCULATION!C8;PRODUCT!B:E;4;FALSE)) | R14: =IF(PRODUCT_CALCULATION!B8="SI";PRODUCT_CALCULATION!F8;"") | S14: =IF(PRODUCT_CALCULATION!B8="SI";PRODUCT_CALCULATION!K8;"") | T14: =IF(PRODUCT_CALCULATION!B8="SI";PRODUCT_CALCULATION!J8;"") | U14: =IF(PRODUCT_CALCULATION!B8="SI";PRODUCT_CALCULATION!N8;"") | V14: =IF(PRODUCT_CALCULATION!B8="SI";PRODUCT_CALCULATION!L8;"") | W14: =IF(PRODUCT_CALCULATION!B8="SI";PRODUCT_CALCULATION!M8;"") | X14: =IF(R8="";"";CEILING(R8/S8;1)) | Y14: =IF(R8="";"";R8*T8) | Z14: =IF(R8="";"";R8*V8)
A15: =INPUT_PRODUCT!B1 | B15: =INPUT_PRODUCT!B2 | C15: =INPUT_PRODUCT!B6 | D15: Arias Group Caribe SRL | F15: Tarancón, España | G15: =INPUT_PRODUCT!B7 | K15: =IF(PRODUCT_CALCULATION!B9="SI";PRODUCT_CALCULATION!C9;"") | L15: =IF(PRODUCT_CALCULATION!B9="SI";PRODUCT_CALCULATION!E9;"") | M15: =IF(PRODUCT_CALCULATION!C9="";"";VLOOKUP(PRODUCT_CALCULATION!C9;PRODUCT!B:Q;16;FALSE)) | N15: =IF(PRODUCT_CALCULATION!C9="";"";VLOOKUP(PRODUCT_CALCULATION!C9;PRODUCT!B:R;17;FALSE)) | O15: =IF(PRODUCT_CALCULATION!C9="";"";VLOOKUP(PRODUCT_CALCULATION!C9;PRODUCT!B:S;18;FALSE)) | P15: =IF(PRODUCT_CALCULATION!C9="";"";VLOOKUP(PRODUCT_CALCULATION!C9;PRODUCT!B:D;3;FALSE)) | Q15: =IF(PRODUCT_CALCULATION!C9="";"";VLOOKUP(PRODUCT_CALCULATION!C9;PRODUCT!B:E;4;FALSE)) | R15: =IF(PRODUCT_CALCULATION!B9="SI";PRODUCT_CALCULATION!F9;"") | S15: =IF(PRODUCT_CALCULATION!B9="SI";PRODUCT_CALCULATION!K9;"") | T15: =IF(PRODUCT_CALCULATION!B9="SI";PRODUCT_CALCULATION!J9;"") | U15: =IF(PRODUCT_CALCULATION!B9="SI";PRODUCT_CALCULATION!N9;"") | V15: =IF(PRODUCT_CALCULATION!B9="SI";PRODUCT_CALCULATION!L9;"") | W15: =IF(PRODUCT_CALCULATION!B9="SI";PRODUCT_CALCULATION!M9;"") | X15: =IF(R9="";"";CEILING(R9/S9;1)) | Y15: =IF(R9="";"";R9*T9) | Z15: =IF(R9="";"";R9*V9)
A16: =INPUT_PRODUCT!B1 | B16: =INPUT_PRODUCT!B2 | C16: =INPUT_PRODUCT!B6 | D16: Arias Group Caribe SRL | F16: Tarancón, España | G16: =INPUT_PRODUCT!B7 | K16: =IF(PRODUCT_CALCULATION!B10="SI";PRODUCT_CALCULATION!C10;"") | L16: =IF(PRODUCT_CALCULATION!B10="SI";PRODUCT_CALCULATION!E10;"") | M16: =IF(PRODUCT_CALCULATION!C10="";"";VLOOKUP(PRODUCT_CALCULATION!C10;PRODUCT!B:Q;16;FALSE)) | N16: =IF(PRODUCT_CALCULATION!C10="";"";VLOOKUP(PRODUCT_CALCULATION!C10;PRODUCT!B:R;17;FALSE)) | O16: =IF(PRODUCT_CALCULATION!C10="";"";VLOOKUP(PRODUCT_CALCULATION!C10;PRODUCT!B:S;18;FALSE)) | P16: =IF(PRODUCT_CALCULATION!C10="";"";VLOOKUP(PRODUCT_CALCULATION!C10;PRODUCT!B:D;3;FALSE)) | Q16: =IF(PRODUCT_CALCULATION!C10="";"";VLOOKUP(PRODUCT_CALCULATION!C10;PRODUCT!B:E;4;FALSE)) | R16: =IF(PRODUCT_CALCULATION!B10="SI";PRODUCT_CALCULATION!F10;"") | S16: =IF(PRODUCT_CALCULATION!B10="SI";PRODUCT_CALCULATION!K10;"") | T16: =IF(PRODUCT_CALCULATION!B10="SI";PRODUCT_CALCULATION!J10;"") | U16: =IF(PRODUCT_CALCULATION!B10="SI";PRODUCT_CALCULATION!N10;"") | V16: =IF(PRODUCT_CALCULATION!B10="SI";PRODUCT_CALCULATION!L10;"") | W16: =IF(PRODUCT_CALCULATION!B10="SI";PRODUCT_CALCULATION!M10;"") | X16: =IF(R10="";"";CEILING(R10/S10;1)) | Y16: =IF(R10="";"";R10*T10) | Z16: =IF(R10="";"";R10*V10)
A17: =INPUT_PRODUCT!B1 | B17: =INPUT_PRODUCT!B2 | C17: =INPUT_PRODUCT!B6 | D17: Arias Group Caribe SRL | F17: Tarancón, España | G17: =INPUT_PRODUCT!B7 | K17: =IF(PRODUCT_CALCULATION!B11="SI";PRODUCT_CALCULATION!C11;"") | L17: =IF(PRODUCT_CALCULATION!B11="SI";PRODUCT_CALCULATION!E11;"") | M17: =IF(PRODUCT_CALCULATION!C11="";"";VLOOKUP(PRODUCT_CALCULATION!C11;PRODUCT!B:Q;16;FALSE)) | N17: =IF(PRODUCT_CALCULATION!C11="";"";VLOOKUP(PRODUCT_CALCULATION!C11;PRODUCT!B:R;17;FALSE)) | O17: =IF(PRODUCT_CALCULATION!C11="";"";VLOOKUP(PRODUCT_CALCULATION!C11;PRODUCT!B:S;18;FALSE)) | P17: =IF(PRODUCT_CALCULATION!C11="";"";VLOOKUP(PRODUCT_CALCULATION!C11;PRODUCT!B:D;3;FALSE)) | Q17: =IF(PRODUCT_CALCULATION!C11="";"";VLOOKUP(PRODUCT_CALCULATION!C11;PRODUCT!B:E;4;FALSE)) | R17: =IF(PRODUCT_CALCULATION!B11="SI";PRODUCT_CALCULATION!F11;"") | S17: =IF(PRODUCT_CALCULATION!B11="SI";PRODUCT_CALCULATION!K11;"") | T17: =IF(PRODUCT_CALCULATION!B11="SI";PRODUCT_CALCULATION!J11;"") | U17: =IF(PRODUCT_CALCULATION!B11="SI";PRODUCT_CALCULATION!N11;"") | V17: =IF(PRODUCT_CALCULATION!B11="SI";PRODUCT_CALCULATION!L11;"") | W17: =IF(PRODUCT_CALCULATION!B11="SI";PRODUCT_CALCULATION!M11;"") | X17: =IF(R11="";"";CEILING(R11/S11;1)) | Y17: =IF(R11="";"";R11*T11) | Z17: =IF(R11="";"";R11*V11)
A18: =INPUT_PRODUCT!B1 | B18: =INPUT_PRODUCT!B2 | C18: =INPUT_PRODUCT!B6 | D18: Arias Group Caribe SRL | F18: Tarancón, España | G18: =INPUT_PRODUCT!B7 | K18: =IF(PRODUCT_CALCULATION!B12="SI";PRODUCT_CALCULATION!C12;"") | L18: =IF(PRODUCT_CALCULATION!B12="SI";PRODUCT_CALCULATION!E12;"") | M18: =IF(PRODUCT_CALCULATION!C12="";"";VLOOKUP(PRODUCT_CALCULATION!C12;PRODUCT!B:Q;16;FALSE)) | N18: =IF(PRODUCT_CALCULATION!C12="";"";VLOOKUP(PRODUCT_CALCULATION!C12;PRODUCT!B:R;17;FALSE)) | O18: =IF(PRODUCT_CALCULATION!C12="";"";VLOOKUP(PRODUCT_CALCULATION!C12;PRODUCT!B:S;18;FALSE)) | P18: =IF(PRODUCT_CALCULATION!C12="";"";VLOOKUP(PRODUCT_CALCULATION!C12;PRODUCT!B:D;3;FALSE)) | Q18: =IF(PRODUCT_CALCULATION!C12="";"";VLOOKUP(PRODUCT_CALCULATION!C12;PRODUCT!B:E;4;FALSE)) | R18: =IF(PRODUCT_CALCULATION!B12="SI";PRODUCT_CALCULATION!F12;"") | S18: =IF(PRODUCT_CALCULATION!B12="SI";PRODUCT_CALCULATION!K12;"") | T18: =IF(PRODUCT_CALCULATION!B12="SI";PRODUCT_CALCULATION!J12;"") | U18: =IF(PRODUCT_CALCULATION!B12="SI";PRODUCT_CALCULATION!N12;"") | V18: =IF(PRODUCT_CALCULATION!B12="SI";PRODUCT_CALCULATION!L12;"") | W18: =IF(PRODUCT_CALCULATION!B12="SI";PRODUCT_CALCULATION!M12;"") | X18: =IF(R12="";"";CEILING(R12/S12;1)) | Y18: =IF(R12="";"";R12*T12) | Z18: =IF(R12="";"";R12*V12)
A19: =INPUT_PRODUCT!B1 | B19: =INPUT_PRODUCT!B2 | C19: =INPUT_PRODUCT!B6 | D19: Arias Group Caribe SRL | F19: Tarancón, España | G19: =INPUT_PRODUCT!B7 | K19: =IF(PRODUCT_CALCULATION!B13="SI";PRODUCT_CALCULATION!C13;"") | L19: =IF(PRODUCT_CALCULATION!B13="SI";PRODUCT_CALCULATION!E13;"") | M19: =IF(PRODUCT_CALCULATION!C13="";"";VLOOKUP(PRODUCT_CALCULATION!C13;PRODUCT!B:Q;16;FALSE)) | N19: =IF(PRODUCT_CALCULATION!C13="";"";VLOOKUP(PRODUCT_CALCULATION!C13;PRODUCT!B:R;17;FALSE)) | O19: =IF(PRODUCT_CALCULATION!C13="";"";VLOOKUP(PRODUCT_CALCULATION!C13;PRODUCT!B:S;18;FALSE)) | P19: =IF(PRODUCT_CALCULATION!C13="";"";VLOOKUP(PRODUCT_CALCULATION!C13;PRODUCT!B:D;3;FALSE)) | Q19: =IF(PRODUCT_CALCULATION!C13="";"";VLOOKUP(PRODUCT_CALCULATION!C13;PRODUCT!B:E;4;FALSE)) | R19: =IF(PRODUCT_CALCULATION!B13="SI";PRODUCT_CALCULATION!F13;"") | S19: =IF(PRODUCT_CALCULATION!B13="SI";PRODUCT_CALCULATION!K13;"") | T19: =IF(PRODUCT_CALCULATION!B13="SI";PRODUCT_CALCULATION!J13;"") | U19: =IF(PRODUCT_CALCULATION!B13="SI";PRODUCT_CALCULATION!N13;"") | V19: =IF(PRODUCT_CALCULATION!B13="SI";PRODUCT_CALCULATION!L13;"") | W19: =IF(PRODUCT_CALCULATION!B13="SI";PRODUCT_CALCULATION!M13;"") | X19: =IF(R13="";"";CEILING(R13/S13;1)) | Y19: =IF(R13="";"";R13*T13) | Z19: =IF(R13="";"";R13*V13)
A20: =INPUT_PRODUCT!B1 | B20: =INPUT_PRODUCT!B2 | C20: =INPUT_PRODUCT!B6 | D20: Arias Group Caribe SRL | F20: Tarancón, España | G20: =INPUT_PRODUCT!B7 | K20: =IF(PRODUCT_CALCULATION!B14="SI";PRODUCT_CALCULATION!C14;"") | L20: =IF(PRODUCT_CALCULATION!B14="SI";PRODUCT_CALCULATION!E14;"") | M20: =IF(PRODUCT_CALCULATION!C14="";"";VLOOKUP(PRODUCT_CALCULATION!C14;PRODUCT!B:Q;16;FALSE)) | N20: =IF(PRODUCT_CALCULATION!C14="";"";VLOOKUP(PRODUCT_CALCULATION!C14;PRODUCT!B:R;17;FALSE)) | O20: =IF(PRODUCT_CALCULATION!C14="";"";VLOOKUP(PRODUCT_CALCULATION!C14;PRODUCT!B:S;18;FALSE)) | P20: =IF(PRODUCT_CALCULATION!C14="";"";VLOOKUP(PRODUCT_CALCULATION!C14;PRODUCT!B:D;3;FALSE)) | Q20: =IF(PRODUCT_CALCULATION!C14="";"";VLOOKUP(PRODUCT_CALCULATION!C14;PRODUCT!B:E;4;FALSE)) | R20: =IF(PRODUCT_CALCULATION!B14="SI";PRODUCT_CALCULATION!F14;"") | S20: =IF(PRODUCT_CALCULATION!B14="SI";PRODUCT_CALCULATION!K14;"") | T20: =IF(PRODUCT_CALCULATION!B14="SI";PRODUCT_CALCULATION!J14;"") | U20: =IF(PRODUCT_CALCULATION!B14="SI";PRODUCT_CALCULATION!N14;"") | V20: =IF(PRODUCT_CALCULATION!B14="SI";PRODUCT_CALCULATION!L14;"") | W20: =IF(PRODUCT_CALCULATION!B14="SI";PRODUCT_CALCULATION!M14;"") | X20: =IF(R14="";"";CEILING(R14/S14;1)) | Y20: =IF(R14="";"";R14*T14) | Z20: =IF(R14="";"";R14*V14)
A21: =INPUT_PRODUCT!B1 | B21: =INPUT_PRODUCT!B2 | C21: =INPUT_PRODUCT!B6 | D21: Arias Group Caribe SRL | F21: Tarancón, España | G21: =INPUT_PRODUCT!B7 | K21: =IF(PRODUCT_CALCULATION!B15="SI";PRODUCT_CALCULATION!C15;"") | L21: =IF(PRODUCT_CALCULATION!B15="SI";PRODUCT_CALCULATION!E15;"") | M21: =IF(PRODUCT_CALCULATION!C15="";"";VLOOKUP(PRODUCT_CALCULATION!C15;PRODUCT!B:Q;16;FALSE)) | N21: =IF(PRODUCT_CALCULATION!C15="";"";VLOOKUP(PRODUCT_CALCULATION!C15;PRODUCT!B:R;17;FALSE)) | O21: =IF(PRODUCT_CALCULATION!C15="";"";VLOOKUP(PRODUCT_CALCULATION!C15;PRODUCT!B:S;18;FALSE)) | P21: =IF(PRODUCT_CALCULATION!C15="";"";VLOOKUP(PRODUCT_CALCULATION!C15;PRODUCT!B:D;3;FALSE)) | Q21: =IF(PRODUCT_CALCULATION!C15="";"";VLOOKUP(PRODUCT_CALCULATION!C15;PRODUCT!B:E;4;FALSE)) | R21: =IF(PRODUCT_CALCULATION!B15="SI";PRODUCT_CALCULATION!F15;"") | S21: =IF(PRODUCT_CALCULATION!B15="SI";PRODUCT_CALCULATION!K15;"") | T21: =IF(PRODUCT_CALCULATION!B15="SI";PRODUCT_CALCULATION!J15;"") | U21: =IF(PRODUCT_CALCULATION!B15="SI";PRODUCT_CALCULATION!N15;"") | V21: =IF(PRODUCT_CALCULATION!B15="SI";PRODUCT_CALCULATION!L15;"") | W21: =IF(PRODUCT_CALCULATION!B15="SI";PRODUCT_CALCULATION!M15;"") | X21: =IF(R15="";"";CEILING(R15/S15;1)) | Y21: =IF(R15="";"";R15*T15) | Z21: =IF(R15="";"";R15*V15)
A22: =INPUT_PRODUCT!B1 | B22: =INPUT_PRODUCT!B2 | C22: =INPUT_PRODUCT!B6 | D22: Arias Group Caribe SRL | F22: Tarancón, España | G22: =INPUT_PRODUCT!B7 | K22: =IF(PRODUCT_CALCULATION!B16="SI";PRODUCT_CALCULATION!C16;"") | L22: =IF(PRODUCT_CALCULATION!B16="SI";PRODUCT_CALCULATION!E16;"") | M22: =IF(PRODUCT_CALCULATION!C16="";"";VLOOKUP(PRODUCT_CALCULATION!C16;PRODUCT!B:Q;16;FALSE)) | N22: =IF(PRODUCT_CALCULATION!C16="";"";VLOOKUP(PRODUCT_CALCULATION!C16;PRODUCT!B:R;17;FALSE)) | O22: =IF(PRODUCT_CALCULATION!C16="";"";VLOOKUP(PRODUCT_CALCULATION!C16;PRODUCT!B:S;18;FALSE)) | P22: =IF(PRODUCT_CALCULATION!C16="";"";VLOOKUP(PRODUCT_CALCULATION!C16;PRODUCT!B:D;3;FALSE)) | Q22: =IF(PRODUCT_CALCULATION!C16="";"";VLOOKUP(PRODUCT_CALCULATION!C16;PRODUCT!B:E;4;FALSE)) | R22: =IF(PRODUCT_CALCULATION!B16="SI";PRODUCT_CALCULATION!F16;"") | S22: =IF(PRODUCT_CALCULATION!B16="SI";PRODUCT_CALCULATION!K16;"") | T22: =IF(PRODUCT_CALCULATION!B16="SI";PRODUCT_CALCULATION!J16;"") | U22: =IF(PRODUCT_CALCULATION!B16="SI";PRODUCT_CALCULATION!N16;"") | V22: =IF(PRODUCT_CALCULATION!B16="SI";PRODUCT_CALCULATION!L16;"") | W22: =IF(PRODUCT_CALCULATION!B16="SI";PRODUCT_CALCULATION!M16;"") | X22: =IF(R16="";"";CEILING(R16/S16;1)) | Y22: =IF(R16="";"";R16*T16) | Z22: =IF(R16="";"";R16*V16)
A23: =INPUT_PRODUCT!B1 | B23: =INPUT_PRODUCT!B2 | C23: =INPUT_PRODUCT!B6 | D23: Arias Group Caribe SRL | F23: Tarancón, España | G23: =INPUT_PRODUCT!B7 | K23: =IF(PRODUCT_CALCULATION!B17="SI";PRODUCT_CALCULATION!C17;"") | L23: =IF(PRODUCT_CALCULATION!B17="SI";PRODUCT_CALCULATION!E17;"") | M23: =IF(PRODUCT_CALCULATION!C17="";"";VLOOKUP(PRODUCT_CALCULATION!C17;PRODUCT!B:Q;16;FALSE)) | N23: =IF(PRODUCT_CALCULATION!C17="";"";VLOOKUP(PRODUCT_CALCULATION!C17;PRODUCT!B:R;17;FALSE)) | O23: =IF(PRODUCT_CALCULATION!C17="";"";VLOOKUP(PRODUCT_CALCULATION!C17;PRODUCT!B:S;18;FALSE)) | P23: =IF(PRODUCT_CALCULATION!C17="";"";VLOOKUP(PRODUCT_CALCULATION!C17;PRODUCT!B:D;3;FALSE)) | Q23: =IF(PRODUCT_CALCULATION!C17="";"";VLOOKUP(PRODUCT_CALCULATION!C17;PRODUCT!B:E;4;FALSE)) | R23: =IF(PRODUCT_CALCULATION!B17="SI";PRODUCT_CALCULATION!F17;"") | S23: =IF(PRODUCT_CALCULATION!B17="SI";PRODUCT_CALCULATION!K17;"") | T23: =IF(PRODUCT_CALCULATION!B17="SI";PRODUCT_CALCULATION!J17;"") | U23: =IF(PRODUCT_CALCULATION!B17="SI";PRODUCT_CALCULATION!N17;"") | V23: =IF(PRODUCT_CALCULATION!B17="SI";PRODUCT_CALCULATION!L17;"") | W23: =IF(PRODUCT_CALCULATION!B17="SI";PRODUCT_CALCULATION!M17;"") | X23: =IF(R17="";"";CEILING(R17/S17;1)) | Y23: =IF(R17="";"";R17*T17) | Z23: =IF(R17="";"";R17*V17)
A24: =INPUT_PRODUCT!B1 | B24: =INPUT_PRODUCT!B2 | C24: =INPUT_PRODUCT!B6 | D24: Arias Group Caribe SRL | F24: Tarancón, España | G24: =INPUT_PRODUCT!B7 | K24: =IF(PRODUCT_CALCULATION!B18="SI";PRODUCT_CALCULATION!C18;"") | L24: =IF(PRODUCT_CALCULATION!B18="SI";PRODUCT_CALCULATION!E18;"") | M24: =IF(PRODUCT_CALCULATION!C18="";"";VLOOKUP(PRODUCT_CALCULATION!C18;PRODUCT!B:Q;16;FALSE)) | N24: =IF(PRODUCT_CALCULATION!C18="";"";VLOOKUP(PRODUCT_CALCULATION!C18;PRODUCT!B:R;17;FALSE)) | O24: =IF(PRODUCT_CALCULATION!C18="";"";VLOOKUP(PRODUCT_CALCULATION!C18;PRODUCT!B:S;18;FALSE)) | P24: =IF(PRODUCT_CALCULATION!C18="";"";VLOOKUP(PRODUCT_CALCULATION!C18;PRODUCT!B:D;3;FALSE)) | Q24: =IF(PRODUCT_CALCULATION!C18="";"";VLOOKUP(PRODUCT_CALCULATION!C18;PRODUCT!B:E;4;FALSE)) | R24: =IF(PRODUCT_CALCULATION!B18="SI";PRODUCT_CALCULATION!F18;"") | S24: =IF(PRODUCT_CALCULATION!B18="SI";PRODUCT_CALCULATION!K18;"") | T24: =IF(PRODUCT_CALCULATION!B18="SI";PRODUCT_CALCULATION!J18;"") | U24: =IF(PRODUCT_CALCULATION!B18="SI";PRODUCT_CALCULATION!N18;"") | V24: =IF(PRODUCT_CALCULATION!B18="SI";PRODUCT_CALCULATION!L18;"") | W24: =IF(PRODUCT_CALCULATION!B18="SI";PRODUCT_CALCULATION!M18;"") | X24: =IF(R18="";"";CEILING(R18/S18;1)) | Y24: =IF(R18="";"";R18*T18) | Z24: =IF(R18="";"";R18*V18)
A25: =INPUT_PRODUCT!B1 | B25: =INPUT_PRODUCT!B2 | C25: =INPUT_PRODUCT!B6 | D25: Arias Group Caribe SRL | F25: Tarancón, España | G25: =INPUT_PRODUCT!B7 | K25: =IF(PRODUCT_CALCULATION!B19="SI";PRODUCT_CALCULATION!C19;"") | L25: =IF(PRODUCT_CALCULATION!B19="SI";PRODUCT_CALCULATION!E19;"") | M25: =IF(PRODUCT_CALCULATION!C19="";"";VLOOKUP(PRODUCT_CALCULATION!C19;PRODUCT!B:Q;16;FALSE)) | N25: =IF(PRODUCT_CALCULATION!C19="";"";VLOOKUP(PRODUCT_CALCULATION!C19;PRODUCT!B:R;17;FALSE)) | O25: =IF(PRODUCT_CALCULATION!C19="";"";VLOOKUP(PRODUCT_CALCULATION!C19;PRODUCT!B:S;18;FALSE)) | P25: =IF(PRODUCT_CALCULATION!C19="";"";VLOOKUP(PRODUCT_CALCULATION!C19;PRODUCT!B:D;3;FALSE)) | Q25: =IF(PRODUCT_CALCULATION!C19="";"";VLOOKUP(PRODUCT_CALCULATION!C19;PRODUCT!B:E;4;FALSE)) | R25: =IF(PRODUCT_CALCULATION!B19="SI";PRODUCT_CALCULATION!F19;"") | S25: =IF(PRODUCT_CALCULATION!B19="SI";PRODUCT_CALCULATION!K19;"") | T25: =IF(PRODUCT_CALCULATION!B19="SI";PRODUCT_CALCULATION!J19;"") | U25: =IF(PRODUCT_CALCULATION!B19="SI";PRODUCT_CALCULATION!N19;"") | V25: =IF(PRODUCT_CALCULATION!B19="SI";PRODUCT_CALCULATION!L19;"") | W25: =IF(PRODUCT_CALCULATION!B19="SI";PRODUCT_CALCULATION!M19;"") | X25: =IF(R19="";"";CEILING(R19/S19;1)) | Y25: =IF(R19="";"";R19*T19) | Z25: =IF(R19="";"";R19*V19)
A26: =INPUT_PRODUCT!B1 | B26: =INPUT_PRODUCT!B2 | C26: =INPUT_PRODUCT!B6 | D26: Arias Group Caribe SRL | F26: Tarancón, España | G26: =INPUT_PRODUCT!B7 | K26: =IF(PRODUCT_CALCULATION!B20="SI";PRODUCT_CALCULATION!C20;"") | L26: =IF(PRODUCT_CALCULATION!B20="SI";PRODUCT_CALCULATION!E20;"") | M26: =IF(PRODUCT_CALCULATION!C20="";"";VLOOKUP(PRODUCT_CALCULATION!C20;PRODUCT!B:Q;16;FALSE)) | N26: =IF(PRODUCT_CALCULATION!C20="";"";VLOOKUP(PRODUCT_CALCULATION!C20;PRODUCT!B:R;17;FALSE)) | O26: =IF(PRODUCT_CALCULATION!C20="";"";VLOOKUP(PRODUCT_CALCULATION!C20;PRODUCT!B:S;18;FALSE)) | P26: =IF(PRODUCT_CALCULATION!C20="";"";VLOOKUP(PRODUCT_CALCULATION!C20;PRODUCT!B:D;3;FALSE)) | Q26: =IF(PRODUCT_CALCULATION!C20="";"";VLOOKUP(PRODUCT_CALCULATION!C20;PRODUCT!B:E;4;FALSE)) | R26: =IF(PRODUCT_CALCULATION!B20="SI";PRODUCT_CALCULATION!F20;"") | S26: =IF(PRODUCT_CALCULATION!B20="SI";PRODUCT_CALCULATION!K20;"") | T26: =IF(PRODUCT_CALCULATION!B20="SI";PRODUCT_CALCULATION!J20;"") | U26: =IF(PRODUCT_CALCULATION!B20="SI";PRODUCT_CALCULATION!N20;"") | V26: =IF(PRODUCT_CALCULATION!B20="SI";PRODUCT_CALCULATION!L20;"") | W26: =IF(PRODUCT_CALCULATION!B20="SI";PRODUCT_CALCULATION!M20;"") | X26: =IF(R20="";"";CEILING(R20/S20;1)) | Y26: =IF(R20="";"";R20*T20) | Z26: =IF(R20="";"";R20*V20)
A27: =INPUT_PRODUCT!B1 | B27: =INPUT_PRODUCT!B2 | C27: =INPUT_PRODUCT!B6 | D27: Arias Group Caribe SRL | F27: Tarancón, España | G27: =INPUT_PRODUCT!B7 | K27: =IF(PRODUCT_CALCULATION!B21="SI";PRODUCT_CALCULATION!C21;"") | L27: =IF(PRODUCT_CALCULATION!B21="SI";PRODUCT_CALCULATION!E21;"") | M27: =IF(PRODUCT_CALCULATION!C21="";"";VLOOKUP(PRODUCT_CALCULATION!C21;PRODUCT!B:Q;16;FALSE)) | N27: =IF(PRODUCT_CALCULATION!C21="";"";VLOOKUP(PRODUCT_CALCULATION!C21;PRODUCT!B:R;17;FALSE)) | O27: =IF(PRODUCT_CALCULATION!C21="";"";VLOOKUP(PRODUCT_CALCULATION!C21;PRODUCT!B:S;18;FALSE)) | P27: =IF(PRODUCT_CALCULATION!C21="";"";VLOOKUP(PRODUCT_CALCULATION!C21;PRODUCT!B:D;3;FALSE)) | Q27: =IF(PRODUCT_CALCULATION!C21="";"";VLOOKUP(PRODUCT_CALCULATION!C21;PRODUCT!B:E;4;FALSE)) | R27: =IF(PRODUCT_CALCULATION!B21="SI";PRODUCT_CALCULATION!F21;"") | S27: =IF(PRODUCT_CALCULATION!B21="SI";PRODUCT_CALCULATION!K21;"") | T27: =IF(PRODUCT_CALCULATION!B21="SI";PRODUCT_CALCULATION!J21;"") | U27: =IF(PRODUCT_CALCULATION!B21="SI";PRODUCT_CALCULATION!N21;"") | V27: =IF(PRODUCT_CALCULATION!B21="SI";PRODUCT_CALCULATION!L21;"") | W27: =IF(PRODUCT_CALCULATION!B21="SI";PRODUCT_CALCULATION!M21;"") | X27: =IF(R21="";"";CEILING(R21/S21;1)) | Y27: =IF(R21="";"";R21*T21) | Z27: =IF(R21="";"";R21*V21)
A28: =INPUT_PRODUCT!B1 | B28: =INPUT_PRODUCT!B2 | C28: =INPUT_PRODUCT!B6 | D28: Arias Group Caribe SRL | F28: Tarancón, España | G28: =INPUT_PRODUCT!B7 | K28: =IF(PRODUCT_CALCULATION!B22="SI";PRODUCT_CALCULATION!C22;"") | L28: =IF(PRODUCT_CALCULATION!B22="SI";PRODUCT_CALCULATION!E22;"") | M28: =IF(PRODUCT_CALCULATION!C22="";"";VLOOKUP(PRODUCT_CALCULATION!C22;PRODUCT!B:Q;16;FALSE)) | N28: =IF(PRODUCT_CALCULATION!C22="";"";VLOOKUP(PRODUCT_CALCULATION!C22;PRODUCT!B:R;17;FALSE)) | O28: =IF(PRODUCT_CALCULATION!C22="";"";VLOOKUP(PRODUCT_CALCULATION!C22;PRODUCT!B:S;18;FALSE)) | P28: =IF(PRODUCT_CALCULATION!C22="";"";VLOOKUP(PRODUCT_CALCULATION!C22;PRODUCT!B:D;3;FALSE)) | Q28: =IF(PRODUCT_CALCULATION!C22="";"";VLOOKUP(PRODUCT_CALCULATION!C22;PRODUCT!B:E;4;FALSE)) | R28: =IF(PRODUCT_CALCULATION!B22="SI";PRODUCT_CALCULATION!F22;"") | S28: =IF(PRODUCT_CALCULATION!B22="SI";PRODUCT_CALCULATION!K22;"") | T28: =IF(PRODUCT_CALCULATION!B22="SI";PRODUCT_CALCULATION!J22;"") | U28: =IF(PRODUCT_CALCULATION!B22="SI";PRODUCT_CALCULATION!N22;"") | V28: =IF(PRODUCT_CALCULATION!B22="SI";PRODUCT_CALCULATION!L22;"") | W28: =IF(PRODUCT_CALCULATION!B22="SI";PRODUCT_CALCULATION!M22;"") | X28: =IF(R22="";"";CEILING(R22/S22;1)) | Y28: =IF(R22="";"";R22*T22) | Z28: =IF(R22="";"";R22*V22)
A29: =INPUT_PRODUCT!B1 | B29: =INPUT_PRODUCT!B2 | C29: =INPUT_PRODUCT!B6 | D29: Arias Group Caribe SRL | F29: Tarancón, España | G29: =INPUT_PRODUCT!B7 | K29: =IF(PRODUCT_CALCULATION!B23="SI";PRODUCT_CALCULATION!C23;"") | L29: =IF(PRODUCT_CALCULATION!B23="SI";PRODUCT_CALCULATION!E23;"") | M29: =IF(PRODUCT_CALCULATION!C23="";"";VLOOKUP(PRODUCT_CALCULATION!C23;PRODUCT!B:Q;16;FALSE)) | N29: =IF(PRODUCT_CALCULATION!C23="";"";VLOOKUP(PRODUCT_CALCULATION!C23;PRODUCT!B:R;17;FALSE)) | O29: =IF(PRODUCT_CALCULATION!C23="";"";VLOOKUP(PRODUCT_CALCULATION!C23;PRODUCT!B:S;18;FALSE)) | P29: =IF(PRODUCT_CALCULATION!C23="";"";VLOOKUP(PRODUCT_CALCULATION!C23;PRODUCT!B:D;3;FALSE)) | Q29: =IF(PRODUCT_CALCULATION!C23="";"";VLOOKUP(PRODUCT_CALCULATION!C23;PRODUCT!B:E;4;FALSE)) | R29: =IF(PRODUCT_CALCULATION!B23="SI";PRODUCT_CALCULATION!F23;"") | S29: =IF(PRODUCT_CALCULATION!B23="SI";PRODUCT_CALCULATION!K23;"") | T29: =IF(PRODUCT_CALCULATION!B23="SI";PRODUCT_CALCULATION!J23;"") | U29: =IF(PRODUCT_CALCULATION!B23="SI";PRODUCT_CALCULATION!N23;"") | V29: =IF(PRODUCT_CALCULATION!B23="SI";PRODUCT_CALCULATION!L23;"") | W29: =IF(PRODUCT_CALCULATION!B23="SI";PRODUCT_CALCULATION!M23;"") | X29: =IF(R23="";"";CEILING(R23/S23;1)) | Y29: =IF(R23="";"";R23*T23) | Z29: =IF(R23="";"";R23*V23)
A30: =INPUT_PRODUCT!B1 | B30: =INPUT_PRODUCT!B2 | C30: =INPUT_PRODUCT!B6 | D30: Arias Group Caribe SRL | F30: Tarancón, España | G30: =INPUT_PRODUCT!B7 | K30: =IF(PRODUCT_CALCULATION!B24="SI";PRODUCT_CALCULATION!C24;"") | L30: =IF(PRODUCT_CALCULATION!B24="SI";PRODUCT_CALCULATION!E24;"") | M30: =IF(PRODUCT_CALCULATION!C24="";"";VLOOKUP(PRODUCT_CALCULATION!C24;PRODUCT!B:Q;16;FALSE)) | N30: =IF(PRODUCT_CALCULATION!C24="";"";VLOOKUP(PRODUCT_CALCULATION!C24;PRODUCT!B:R;17;FALSE)) | O30: =IF(PRODUCT_CALCULATION!C24="";"";VLOOKUP(PRODUCT_CALCULATION!C24;PRODUCT!B:S;18;FALSE)) | P30: =IF(PRODUCT_CALCULATION!C24="";"";VLOOKUP(PRODUCT_CALCULATION!C24;PRODUCT!B:D;3;FALSE)) | Q30: =IF(PRODUCT_CALCULATION!C24="";"";VLOOKUP(PRODUCT_CALCULATION!C24;PRODUCT!B:E;4;FALSE)) | R30: =IF(PRODUCT_CALCULATION!B24="SI";PRODUCT_CALCULATION!F24;"") | S30: =IF(PRODUCT_CALCULATION!B24="SI";PRODUCT_CALCULATION!K24;"") | T30: =IF(PRODUCT_CALCULATION!B24="SI";PRODUCT_CALCULATION!J24;"") | U30: =IF(PRODUCT_CALCULATION!B24="SI";PRODUCT_CALCULATION!N24;"") | V30: =IF(PRODUCT_CALCULATION!B24="SI";PRODUCT_CALCULATION!L24;"") | W30: =IF(PRODUCT_CALCULATION!B24="SI";PRODUCT_CALCULATION!M24;"") | X30: =IF(R24="";"";CEILING(R24/S24;1)) | Y30: =IF(R24="";"";R24*T24) | Z30: =IF(R24="";"";R24*V24)
A31: =INPUT_PRODUCT!B1 | B31: =INPUT_PRODUCT!B2 | C31: =INPUT_PRODUCT!B6 | D31: Arias Group Caribe SRL | F31: Tarancón, España | G31: =INPUT_PRODUCT!B7 | K31: =IF(PRODUCT_CALCULATION!B25="SI";PRODUCT_CALCULATION!C25;"") | L31: =IF(PRODUCT_CALCULATION!B25="SI";PRODUCT_CALCULATION!E25;"") | M31: =IF(PRODUCT_CALCULATION!C25="";"";VLOOKUP(PRODUCT_CALCULATION!C25;PRODUCT!B:Q;16;FALSE)) | N31: =IF(PRODUCT_CALCULATION!C25="";"";VLOOKUP(PRODUCT_CALCULATION!C25;PRODUCT!B:R;17;FALSE)) | O31: =IF(PRODUCT_CALCULATION!C25="";"";VLOOKUP(PRODUCT_CALCULATION!C25;PRODUCT!B:S;18;FALSE)) | P31: =IF(PRODUCT_CALCULATION!C25="";"";VLOOKUP(PRODUCT_CALCULATION!C25;PRODUCT!B:D;3;FALSE)) | Q31: =IF(PRODUCT_CALCULATION!C25="";"";VLOOKUP(PRODUCT_CALCULATION!C25;PRODUCT!B:E;4;FALSE)) | R31: =IF(PRODUCT_CALCULATION!B25="SI";PRODUCT_CALCULATION!F25;"") | S31: =IF(PRODUCT_CALCULATION!B25="SI";PRODUCT_CALCULATION!K25;"") | T31: =IF(PRODUCT_CALCULATION!B25="SI";PRODUCT_CALCULATION!J25;"") | U31: =IF(PRODUCT_CALCULATION!B25="SI";PRODUCT_CALCULATION!N25;"") | V31: =IF(PRODUCT_CALCULATION!B25="SI";PRODUCT_CALCULATION!L25;"") | W31: =IF(PRODUCT_CALCULATION!B25="SI";PRODUCT_CALCULATION!M25;"") | X31: =IF(R25="";"";CEILING(R25/S25;1)) | Y31: =IF(R25="";"";R25*T25) | Z31: =IF(R25="";"";R25*V25)
A32: =INPUT_PRODUCT!B1 | B32: =INPUT_PRODUCT!B2 | C32: =INPUT_PRODUCT!B6 | D32: Arias Group Caribe SRL | F32: Tarancón, España | G32: =INPUT_PRODUCT!B7 | K32: =IF(PRODUCT_CALCULATION!B26="SI";PRODUCT_CALCULATION!C26;"") | L32: =IF(PRODUCT_CALCULATION!B26="SI";PRODUCT_CALCULATION!E26;"") | M32: =IF(PRODUCT_CALCULATION!C26="";"";VLOOKUP(PRODUCT_CALCULATION!C26;PRODUCT!B:Q;16;FALSE)) | N32: =IF(PRODUCT_CALCULATION!C26="";"";VLOOKUP(PRODUCT_CALCULATION!C26;PRODUCT!B:R;17;FALSE)) | O32: =IF(PRODUCT_CALCULATION!C26="";"";VLOOKUP(PRODUCT_CALCULATION!C26;PRODUCT!B:S;18;FALSE)) | P32: =IF(PRODUCT_CALCULATION!C26="";"";VLOOKUP(PRODUCT_CALCULATION!C26;PRODUCT!B:D;3;FALSE)) | Q32: =IF(PRODUCT_CALCULATION!C26="";"";VLOOKUP(PRODUCT_CALCULATION!C26;PRODUCT!B:E;4;FALSE)) | R32: =IF(PRODUCT_CALCULATION!B26="SI";PRODUCT_CALCULATION!F26;"") | S32: =IF(PRODUCT_CALCULATION!B26="SI";PRODUCT_CALCULATION!K26;"") | T32: =IF(PRODUCT_CALCULATION!B26="SI";PRODUCT_CALCULATION!J26;"") | U32: =IF(PRODUCT_CALCULATION!B26="SI";PRODUCT_CALCULATION!N26;"") | V32: =IF(PRODUCT_CALCULATION!B26="SI";PRODUCT_CALCULATION!L26;"") | W32: =IF(PRODUCT_CALCULATION!B26="SI";PRODUCT_CALCULATION!M26;"") | X32: =IF(R26="";"";CEILING(R26/S26;1)) | Y32: =IF(R26="";"";R26*T26) | Z32: =IF(R26="";"";R26*V26)
A33: =INPUT_PRODUCT!B1 | B33: =INPUT_PRODUCT!B2 | C33: =INPUT_PRODUCT!B6 | D33: Arias Group Caribe SRL | F33: Tarancón, España | G33: =INPUT_PRODUCT!B7 | K33: =IF(PRODUCT_CALCULATION!B27="SI";PRODUCT_CALCULATION!C27;"") | L33: =IF(PRODUCT_CALCULATION!B27="SI";PRODUCT_CALCULATION!E27;"") | M33: =IF(PRODUCT_CALCULATION!C27="";"";VLOOKUP(PRODUCT_CALCULATION!C27;PRODUCT!B:Q;16;FALSE)) | N33: =IF(PRODUCT_CALCULATION!C27="";"";VLOOKUP(PRODUCT_CALCULATION!C27;PRODUCT!B:R;17;FALSE)) | O33: =IF(PRODUCT_CALCULATION!C27="";"";VLOOKUP(PRODUCT_CALCULATION!C27;PRODUCT!B:S;18;FALSE)) | P33: =IF(PRODUCT_CALCULATION!C27="";"";VLOOKUP(PRODUCT_CALCULATION!C27;PRODUCT!B:D;3;FALSE)) | Q33: =IF(PRODUCT_CALCULATION!C27="";"";VLOOKUP(PRODUCT_CALCULATION!C27;PRODUCT!B:E;4;FALSE)) | R33: =IF(PRODUCT_CALCULATION!B27="SI";PRODUCT_CALCULATION!F27;"") | S33: =IF(PRODUCT_CALCULATION!B27="SI";PRODUCT_CALCULATION!K27;"") | T33: =IF(PRODUCT_CALCULATION!B27="SI";PRODUCT_CALCULATION!J27;"") | U33: =IF(PRODUCT_CALCULATION!B27="SI";PRODUCT_CALCULATION!N27;"") | V33: =IF(PRODUCT_CALCULATION!B27="SI";PRODUCT_CALCULATION!L27;"") | W33: =IF(PRODUCT_CALCULATION!B27="SI";PRODUCT_CALCULATION!M27;"") | X33: =IF(R27="";"";CEILING(R27/S27;1)) | Y33: =IF(R27="";"";R27*T27) | Z33: =IF(R27="";"";R27*V27)
A34: =INPUT_PRODUCT!B1 | B34: =INPUT_PRODUCT!B2 | C34: =INPUT_PRODUCT!B6 | D34: Arias Group Caribe SRL | F34: Tarancón, España | G34: =INPUT_PRODUCT!B7 | K34: =IF(PRODUCT_CALCULATION!B28="SI";PRODUCT_CALCULATION!C28;"") | L34: =IF(PRODUCT_CALCULATION!B28="SI";PRODUCT_CALCULATION!E28;"") | M34: =IF(PRODUCT_CALCULATION!C28="";"";VLOOKUP(PRODUCT_CALCULATION!C28;PRODUCT!B:Q;16;FALSE)) | N34: =IF(PRODUCT_CALCULATION!C28="";"";VLOOKUP(PRODUCT_CALCULATION!C28;PRODUCT!B:R;17;FALSE)) | O34: =IF(PRODUCT_CALCULATION!C28="";"";VLOOKUP(PRODUCT_CALCULATION!C28;PRODUCT!B:S;18;FALSE)) | P34: =IF(PRODUCT_CALCULATION!C28="";"";VLOOKUP(PRODUCT_CALCULATION!C28;PRODUCT!B:D;3;FALSE)) | Q34: =IF(PRODUCT_CALCULATION!C28="";"";VLOOKUP(PRODUCT_CALCULATION!C28;PRODUCT!B:E;4;FALSE)) | R34: =IF(PRODUCT_CALCULATION!B28="SI";PRODUCT_CALCULATION!F28;"") | S34: =IF(PRODUCT_CALCULATION!B28="SI";PRODUCT_CALCULATION!K28;"") | T34: =IF(PRODUCT_CALCULATION!B28="SI";PRODUCT_CALCULATION!J28;"") | U34: =IF(PRODUCT_CALCULATION!B28="SI";PRODUCT_CALCULATION!N28;"") | V34: =IF(PRODUCT_CALCULATION!B28="SI";PRODUCT_CALCULATION!L28;"") | W34: =IF(PRODUCT_CALCULATION!B28="SI";PRODUCT_CALCULATION!M28;"") | X34: =IF(R28="";"";CEILING(R28/S28;1)) | Y34: =IF(R28="";"";R28*T28) | Z34: =IF(R28="";"";R28*V28)
A35: =INPUT_PRODUCT!B1 | B35: =INPUT_PRODUCT!B2 | C35: =INPUT_PRODUCT!B6 | D35: Arias Group Caribe SRL | F35: Tarancón, España | G35: =INPUT_PRODUCT!B7 | K35: =IF(PRODUCT_CALCULATION!B29="SI";PRODUCT_CALCULATION!C29;"") | L35: =IF(PRODUCT_CALCULATION!B29="SI";PRODUCT_CALCULATION!E29;"") | M35: =IF(PRODUCT_CALCULATION!C29="";"";VLOOKUP(PRODUCT_CALCULATION!C29;PRODUCT!B:Q;16;FALSE)) | N35: =IF(PRODUCT_CALCULATION!C29="";"";VLOOKUP(PRODUCT_CALCULATION!C29;PRODUCT!B:R;17;FALSE)) | O35: =IF(PRODUCT_CALCULATION!C29="";"";VLOOKUP(PRODUCT_CALCULATION!C29;PRODUCT!B:S;18;FALSE)) | P35: =IF(PRODUCT_CALCULATION!C29="";"";VLOOKUP(PRODUCT_CALCULATION!C29;PRODUCT!B:D;3;FALSE)) | Q35: =IF(PRODUCT_CALCULATION!C29="";"";VLOOKUP(PRODUCT_CALCULATION!C29;PRODUCT!B:E;4;FALSE)) | R35: =IF(PRODUCT_CALCULATION!B29="SI";PRODUCT_CALCULATION!F29;"") | S35: =IF(PRODUCT_CALCULATION!B29="SI";PRODUCT_CALCULATION!K29;"") | T35: =IF(PRODUCT_CALCULATION!B29="SI";PRODUCT_CALCULATION!J29;"") | U35: =IF(PRODUCT_CALCULATION!B29="SI";PRODUCT_CALCULATION!N29;"") | V35: =IF(PRODUCT_CALCULATION!B29="SI";PRODUCT_CALCULATION!L29;"") | W35: =IF(PRODUCT_CALCULATION!B29="SI";PRODUCT_CALCULATION!M29;"") | X35: =IF(R29="";"";CEILING(R29/S29;1)) | Y35: =IF(R29="";"";R29*T29) | Z35: =IF(R29="";"";R29*V29)
A36: =INPUT_PRODUCT!B1 | B36: =INPUT_PRODUCT!B2 | C36: =INPUT_PRODUCT!B6 | D36: Arias Group Caribe SRL | F36: Tarancón, España | G36: =INPUT_PRODUCT!B7 | K36: =IF(PRODUCT_CALCULATION!B30="SI";PRODUCT_CALCULATION!C30;"") | L36: =IF(PRODUCT_CALCULATION!B30="SI";PRODUCT_CALCULATION!E30;"") | M36: =IF(PRODUCT_CALCULATION!C30="";"";VLOOKUP(PRODUCT_CALCULATION!C30;PRODUCT!B:Q;16;FALSE)) | N36: =IF(PRODUCT_CALCULATION!C30="";"";VLOOKUP(PRODUCT_CALCULATION!C30;PRODUCT!B:R;17;FALSE)) | O36: =IF(PRODUCT_CALCULATION!C30="";"";VLOOKUP(PRODUCT_CALCULATION!C30;PRODUCT!B:S;18;FALSE)) | P36: =IF(PRODUCT_CALCULATION!C30="";"";VLOOKUP(PRODUCT_CALCULATION!C30;PRODUCT!B:D;3;FALSE)) | Q36: =IF(PRODUCT_CALCULATION!C30="";"";VLOOKUP(PRODUCT_CALCULATION!C30;PRODUCT!B:E;4;FALSE)) | R36: =IF(PRODUCT_CALCULATION!B30="SI";PRODUCT_CALCULATION!F30;"") | S36: =IF(PRODUCT_CALCULATION!B30="SI";PRODUCT_CALCULATION!K30;"") | T36: =IF(PRODUCT_CALCULATION!B30="SI";PRODUCT_CALCULATION!J30;"") | U36: =IF(PRODUCT_CALCULATION!B30="SI";PRODUCT_CALCULATION!N30;"") | V36: =IF(PRODUCT_CALCULATION!B30="SI";PRODUCT_CALCULATION!L30;"") | W36: =IF(PRODUCT_CALCULATION!B30="SI";PRODUCT_CALCULATION!M30;"") | X36: =IF(R30="";"";CEILING(R30/S30;1)) | Y36: =IF(R30="";"";R30*T30) | Z36: =IF(R30="";"";R30*V30)
A37: =INPUT_PRODUCT!B1 | B37: =INPUT_PRODUCT!B2 | C37: =INPUT_PRODUCT!B6 | D37: Arias Group Caribe SRL | F37: Tarancón, España | G37: =INPUT_PRODUCT!B7 | K37: =IF(PRODUCT_CALCULATION!B31="SI";PRODUCT_CALCULATION!C31;"") | L37: =IF(PRODUCT_CALCULATION!B31="SI";PRODUCT_CALCULATION!E31;"") | M37: =IF(PRODUCT_CALCULATION!C31="";"";VLOOKUP(PRODUCT_CALCULATION!C31;PRODUCT!B:Q;16;FALSE)) | N37: =IF(PRODUCT_CALCULATION!C31="";"";VLOOKUP(PRODUCT_CALCULATION!C31;PRODUCT!B:R;17;FALSE)) | O37: =IF(PRODUCT_CALCULATION!C31="";"";VLOOKUP(PRODUCT_CALCULATION!C31;PRODUCT!B:S;18;FALSE)) | P37: =IF(PRODUCT_CALCULATION!C31="";"";VLOOKUP(PRODUCT_CALCULATION!C31;PRODUCT!B:D;3;FALSE)) | Q37: =IF(PRODUCT_CALCULATION!C31="";"";VLOOKUP(PRODUCT_CALCULATION!C31;PRODUCT!B:E;4;FALSE)) | R37: =IF(PRODUCT_CALCULATION!B31="SI";PRODUCT_CALCULATION!F31;"") | S37: =IF(PRODUCT_CALCULATION!B31="SI";PRODUCT_CALCULATION!K31;"") | T37: =IF(PRODUCT_CALCULATION!B31="SI";PRODUCT_CALCULATION!J31;"") | U37: =IF(PRODUCT_CALCULATION!B31="SI";PRODUCT_CALCULATION!N31;"") | V37: =IF(PRODUCT_CALCULATION!B31="SI";PRODUCT_CALCULATION!L31;"") | W37: =IF(PRODUCT_CALCULATION!B31="SI";PRODUCT_CALCULATION!M31;"") | X37: =IF(R31="";"";CEILING(R31/S31;1)) | Y37: =IF(R31="";"";R31*T31) | Z37: =IF(R31="";"";R31*V31)
A38: =INPUT_PRODUCT!B1 | B38: =INPUT_PRODUCT!B2 | C38: =INPUT_PRODUCT!B6 | D38: Arias Group Caribe SRL | F38: Tarancón, España | G38: =INPUT_PRODUCT!B7 | K38: =IF(PRODUCT_CALCULATION!B32="SI";PRODUCT_CALCULATION!C32;"") | L38: =IF(PRODUCT_CALCULATION!B32="SI";PRODUCT_CALCULATION!E32;"") | M38: =IF(PRODUCT_CALCULATION!C32="";"";VLOOKUP(PRODUCT_CALCULATION!C32;PRODUCT!B:Q;16;FALSE)) | N38: =IF(PRODUCT_CALCULATION!C32="";"";VLOOKUP(PRODUCT_CALCULATION!C32;PRODUCT!B:R;17;FALSE)) | O38: =IF(PRODUCT_CALCULATION!C32="";"";VLOOKUP(PRODUCT_CALCULATION!C32;PRODUCT!B:S;18;FALSE)) | P38: =IF(PRODUCT_CALCULATION!C32="";"";VLOOKUP(PRODUCT_CALCULATION!C32;PRODUCT!B:D;3;FALSE)) | Q38: =IF(PRODUCT_CALCULATION!C32="";"";VLOOKUP(PRODUCT_CALCULATION!C32;PRODUCT!B:E;4;FALSE)) | R38: =IF(PRODUCT_CALCULATION!B32="SI";PRODUCT_CALCULATION!F32;"") | S38: =IF(PRODUCT_CALCULATION!B32="SI";PRODUCT_CALCULATION!K32;"") | T38: =IF(PRODUCT_CALCULATION!B32="SI";PRODUCT_CALCULATION!J32;"") | U38: =IF(PRODUCT_CALCULATION!B32="SI";PRODUCT_CALCULATION!N32;"") | V38: =IF(PRODUCT_CALCULATION!B32="SI";PRODUCT_CALCULATION!L32;"") | W38: =IF(PRODUCT_CALCULATION!B32="SI";PRODUCT_CALCULATION!M32;"") | X38: =IF(R32="";"";CEILING(R32/S32;1)) | Y38: =IF(R32="";"";R32*T32) | Z38: =IF(R32="";"";R32*V32)
A39: =INPUT_PRODUCT!B1 | B39: =INPUT_PRODUCT!B2 | C39: =INPUT_PRODUCT!B6 | D39: Arias Group Caribe SRL | F39: Tarancón, España | G39: =INPUT_PRODUCT!B7 | K39: =IF(PRODUCT_CALCULATION!B33="SI";PRODUCT_CALCULATION!C33;"") | L39: =IF(PRODUCT_CALCULATION!B33="SI";PRODUCT_CALCULATION!E33;"") | M39: =IF(PRODUCT_CALCULATION!C33="";"";VLOOKUP(PRODUCT_CALCULATION!C33;PRODUCT!B:Q;16;FALSE)) | N39: =IF(PRODUCT_CALCULATION!C33="";"";VLOOKUP(PRODUCT_CALCULATION!C33;PRODUCT!B:R;17;FALSE)) | O39: =IF(PRODUCT_CALCULATION!C33="";"";VLOOKUP(PRODUCT_CALCULATION!C33;PRODUCT!B:S;18;FALSE)) | P39: =IF(PRODUCT_CALCULATION!C33="";"";VLOOKUP(PRODUCT_CALCULATION!C33;PRODUCT!B:D;3;FALSE)) | Q39: =IF(PRODUCT_CALCULATION!C33="";"";VLOOKUP(PRODUCT_CALCULATION!C33;PRODUCT!B:E;4;FALSE)) | R39: =IF(PRODUCT_CALCULATION!B33="SI";PRODUCT_CALCULATION!F33;"") | S39: =IF(PRODUCT_CALCULATION!B33="SI";PRODUCT_CALCULATION!K33;"") | T39: =IF(PRODUCT_CALCULATION!B33="SI";PRODUCT_CALCULATION!J33;"") | U39: =IF(PRODUCT_CALCULATION!B33="SI";PRODUCT_CALCULATION!N33;"") | V39: =IF(PRODUCT_CALCULATION!B33="SI";PRODUCT_CALCULATION!L33;"") | W39: =IF(PRODUCT_CALCULATION!B33="SI";PRODUCT_CALCULATION!M33;"") | X39: =IF(R33="";"";CEILING(R33/S33;1)) | Y39: =IF(R33="";"";R33*T33) | Z39: =IF(R33="";"";R33*V33)
A40: =INPUT_PRODUCT!B1 | B40: =INPUT_PRODUCT!B2 | C40: =INPUT_PRODUCT!B6 | D40: Arias Group Caribe SRL | F40: Tarancón, España | G40: =INPUT_PRODUCT!B7 | K40: =IF(PRODUCT_CALCULATION!B34="SI";PRODUCT_CALCULATION!C34;"") | L40: =IF(PRODUCT_CALCULATION!B34="SI";PRODUCT_CALCULATION!E34;"") | M40: =IF(PRODUCT_CALCULATION!C34="";"";VLOOKUP(PRODUCT_CALCULATION!C34;PRODUCT!B:Q;16;FALSE)) | N40: =IF(PRODUCT_CALCULATION!C34="";"";VLOOKUP(PRODUCT_CALCULATION!C34;PRODUCT!B:R;17;FALSE)) | O40: =IF(PRODUCT_CALCULATION!C34="";"";VLOOKUP(PRODUCT_CALCULATION!C34;PRODUCT!B:S;18;FALSE)) | P40: =IF(PRODUCT_CALCULATION!C34="";"";VLOOKUP(PRODUCT_CALCULATION!C34;PRODUCT!B:D;3;FALSE)) | Q40: =IF(PRODUCT_CALCULATION!C34="";"";VLOOKUP(PRODUCT_CALCULATION!C34;PRODUCT!B:E;4;FALSE)) | R40: =IF(PRODUCT_CALCULATION!B34="SI";PRODUCT_CALCULATION!F34;"") | S40: =IF(PRODUCT_CALCULATION!B34="SI";PRODUCT_CALCULATION!K34;"") | T40: =IF(PRODUCT_CALCULATION!B34="SI";PRODUCT_CALCULATION!J34;"") | U40: =IF(PRODUCT_CALCULATION!B34="SI";PRODUCT_CALCULATION!N34;"") | V40: =IF(PRODUCT_CALCULATION!B34="SI";PRODUCT_CALCULATION!L34;"") | W40: =IF(PRODUCT_CALCULATION!B34="SI";PRODUCT_CALCULATION!M34;"") | X40: =IF(R34="";"";CEILING(R34/S34;1)) | Y40: =IF(R34="";"";R34*T34) | Z40: =IF(R34="";"";R34*V34)
A41: =INPUT_PRODUCT!B1 | B41: =INPUT_PRODUCT!B2 | C41: =INPUT_PRODUCT!B6 | D41: Arias Group Caribe SRL | F41: Tarancón, España | G41: =INPUT_PRODUCT!B7 | K41: =IF(PRODUCT_CALCULATION!B35="SI";PRODUCT_CALCULATION!C35;"") | L41: =IF(PRODUCT_CALCULATION!B35="SI";PRODUCT_CALCULATION!E35;"") | M41: =IF(PRODUCT_CALCULATION!C35="";"";VLOOKUP(PRODUCT_CALCULATION!C35;PRODUCT!B:Q;16;FALSE)) | N41: =IF(PRODUCT_CALCULATION!C35="";"";VLOOKUP(PRODUCT_CALCULATION!C35;PRODUCT!B:R;17;FALSE)) | O41: =IF(PRODUCT_CALCULATION!C35="";"";VLOOKUP(PRODUCT_CALCULATION!C35;PRODUCT!B:S;18;FALSE)) | P41: =IF(PRODUCT_CALCULATION!C35="";"";VLOOKUP(PRODUCT_CALCULATION!C35;PRODUCT!B:D;3;FALSE)) | Q41: =IF(PRODUCT_CALCULATION!C35="";"";VLOOKUP(PRODUCT_CALCULATION!C35;PRODUCT!B:E;4;FALSE)) | R41: =IF(PRODUCT_CALCULATION!B35="SI";PRODUCT_CALCULATION!F35;"") | S41: =IF(PRODUCT_CALCULATION!B35="SI";PRODUCT_CALCULATION!K35;"") | T41: =IF(PRODUCT_CALCULATION!B35="SI";PRODUCT_CALCULATION!J35;"") | U41: =IF(PRODUCT_CALCULATION!B35="SI";PRODUCT_CALCULATION!N35;"") | V41: =IF(PRODUCT_CALCULATION!B35="SI";PRODUCT_CALCULATION!L35;"") | W41: =IF(PRODUCT_CALCULATION!B35="SI";PRODUCT_CALCULATION!M35;"") | X41: =IF(R35="";"";CEILING(R35/S35;1)) | Y41: =IF(R35="";"";R35*T35) | Z41: =IF(R35="";"";R35*V35)
A42: =INPUT_PRODUCT!B1 | B42: =INPUT_PRODUCT!B2 | C42: =INPUT_PRODUCT!B6 | D42: Arias Group Caribe SRL | F42: Tarancón, España | G42: =INPUT_PRODUCT!B7 | K42: =IF(PRODUCT_CALCULATION!B36="SI";PRODUCT_CALCULATION!C36;"") | L42: =IF(PRODUCT_CALCULATION!B36="SI";PRODUCT_CALCULATION!E36;"") | M42: =IF(PRODUCT_CALCULATION!C36="";"";VLOOKUP(PRODUCT_CALCULATION!C36;PRODUCT!B:Q;16;FALSE)) | N42: =IF(PRODUCT_CALCULATION!C36="";"";VLOOKUP(PRODUCT_CALCULATION!C36;PRODUCT!B:R;17;FALSE)) | O42: =IF(PRODUCT_CALCULATION!C36="";"";VLOOKUP(PRODUCT_CALCULATION!C36;PRODUCT!B:S;18;FALSE)) | P42: =IF(PRODUCT_CALCULATION!C36="";"";VLOOKUP(PRODUCT_CALCULATION!C36;PRODUCT!B:D;3;FALSE)) | Q42: =IF(PRODUCT_CALCULATION!C36="";"";VLOOKUP(PRODUCT_CALCULATION!C36;PRODUCT!B:E;4;FALSE)) | R42: =IF(PRODUCT_CALCULATION!B36="SI";PRODUCT_CALCULATION!F36;"") | S42: =IF(PRODUCT_CALCULATION!B36="SI";PRODUCT_CALCULATION!K36;"") | T42: =IF(PRODUCT_CALCULATION!B36="SI";PRODUCT_CALCULATION!J36;"") | U42: =IF(PRODUCT_CALCULATION!B36="SI";PRODUCT_CALCULATION!N36;"") | V42: =IF(PRODUCT_CALCULATION!B36="SI";PRODUCT_CALCULATION!L36;"") | W42: =IF(PRODUCT_CALCULATION!B36="SI";PRODUCT_CALCULATION!M36;"") | X42: =IF(R36="";"";CEILING(R36/S36;1)) | Y42: =IF(R36="";"";R36*T36) | Z42: =IF(R36="";"";R36*V36)
A43: =INPUT_PRODUCT!B1 | B43: =INPUT_PRODUCT!B2 | C43: =INPUT_PRODUCT!B6 | D43: Arias Group Caribe SRL | F43: Tarancón, España | G43: =INPUT_PRODUCT!B7 | K43: =IF(PRODUCT_CALCULATION!B37="SI";PRODUCT_CALCULATION!C37;"") | L43: =IF(PRODUCT_CALCULATION!B37="SI";PRODUCT_CALCULATION!E37;"") | M43: =IF(PRODUCT_CALCULATION!C37="";"";VLOOKUP(PRODUCT_CALCULATION!C37;PRODUCT!B:Q;16;FALSE)) | N43: =IF(PRODUCT_CALCULATION!C37="";"";VLOOKUP(PRODUCT_CALCULATION!C37;PRODUCT!B:R;17;FALSE)) | O43: =IF(PRODUCT_CALCULATION!C37="";"";VLOOKUP(PRODUCT_CALCULATION!C37;PRODUCT!B:S;18;FALSE)) | P43: =IF(PRODUCT_CALCULATION!C37="";"";VLOOKUP(PRODUCT_CALCULATION!C37;PRODUCT!B:D;3;FALSE)) | Q43: =IF(PRODUCT_CALCULATION!C37="";"";VLOOKUP(PRODUCT_CALCULATION!C37;PRODUCT!B:E;4;FALSE)) | R43: =IF(PRODUCT_CALCULATION!B37="SI";PRODUCT_CALCULATION!F37;"") | S43: =IF(PRODUCT_CALCULATION!B37="SI";PRODUCT_CALCULATION!K37;"") | T43: =IF(PRODUCT_CALCULATION!B37="SI";PRODUCT_CALCULATION!J37;"") | U43: =IF(PRODUCT_CALCULATION!B37="SI";PRODUCT_CALCULATION!N37;"") | V43: =IF(PRODUCT_CALCULATION!B37="SI";PRODUCT_CALCULATION!L37;"") | W43: =IF(PRODUCT_CALCULATION!B37="SI";PRODUCT_CALCULATION!M37;"") | X43: =IF(R37="";"";CEILING(R37/S37;1)) | Y43: =IF(R37="";"";R37*T37) | Z43: =IF(R37="";"";R37*V37)
A44: =INPUT_PRODUCT!B1 | B44: =INPUT_PRODUCT!B2 | C44: =INPUT_PRODUCT!B6 | D44: Arias Group Caribe SRL | F44: Tarancón, España | G44: =INPUT_PRODUCT!B7 | K44: =IF(PRODUCT_CALCULATION!B38="SI";PRODUCT_CALCULATION!C38;"") | L44: =IF(PRODUCT_CALCULATION!B38="SI";PRODUCT_CALCULATION!E38;"") | M44: =IF(PRODUCT_CALCULATION!C38="";"";VLOOKUP(PRODUCT_CALCULATION!C38;PRODUCT!B:Q;16;FALSE)) | N44: =IF(PRODUCT_CALCULATION!C38="";"";VLOOKUP(PRODUCT_CALCULATION!C38;PRODUCT!B:R;17;FALSE)) | O44: =IF(PRODUCT_CALCULATION!C38="";"";VLOOKUP(PRODUCT_CALCULATION!C38;PRODUCT!B:S;18;FALSE)) | P44: =IF(PRODUCT_CALCULATION!C38="";"";VLOOKUP(PRODUCT_CALCULATION!C38;PRODUCT!B:D;3;FALSE)) | Q44: =IF(PRODUCT_CALCULATION!C38="";"";VLOOKUP(PRODUCT_CALCULATION!C38;PRODUCT!B:E;4;FALSE)) | R44: =IF(PRODUCT_CALCULATION!B38="SI";PRODUCT_CALCULATION!F38;"") | S44: =IF(PRODUCT_CALCULATION!B38="SI";PRODUCT_CALCULATION!K38;"") | T44: =IF(PRODUCT_CALCULATION!B38="SI";PRODUCT_CALCULATION!J38;"") | U44: =IF(PRODUCT_CALCULATION!B38="SI";PRODUCT_CALCULATION!N38;"") | V44: =IF(PRODUCT_CALCULATION!B38="SI";PRODUCT_CALCULATION!L38;"") | W44: =IF(PRODUCT_CALCULATION!B38="SI";PRODUCT_CALCULATION!M38;"") | X44: =IF(R38="";"";CEILING(R38/S38;1)) | Y44: =IF(R38="";"";R38*T38) | Z44: =IF(R38="";"";R38*V38)
A45: =INPUT_PRODUCT!B1 | B45: =INPUT_PRODUCT!B2 | C45: =INPUT_PRODUCT!B6 | D45: Arias Group Caribe SRL | F45: Tarancón, España | G45: =INPUT_PRODUCT!B7 | K45: =IF(PRODUCT_CALCULATION!B39="SI";PRODUCT_CALCULATION!C39;"") | L45: =IF(PRODUCT_CALCULATION!B39="SI";PRODUCT_CALCULATION!E39;"") | M45: =IF(PRODUCT_CALCULATION!C39="";"";VLOOKUP(PRODUCT_CALCULATION!C39;PRODUCT!B:Q;16;FALSE)) | N45: =IF(PRODUCT_CALCULATION!C39="";"";VLOOKUP(PRODUCT_CALCULATION!C39;PRODUCT!B:R;17;FALSE)) | O45: =IF(PRODUCT_CALCULATION!C39="";"";VLOOKUP(PRODUCT_CALCULATION!C39;PRODUCT!B:S;18;FALSE)) | P45: =IF(PRODUCT_CALCULATION!C39="";"";VLOOKUP(PRODUCT_CALCULATION!C39;PRODUCT!B:D;3;FALSE)) | Q45: =IF(PRODUCT_CALCULATION!C39="";"";VLOOKUP(PRODUCT_CALCULATION!C39;PRODUCT!B:E;4;FALSE)) | R45: =IF(PRODUCT_CALCULATION!B39="SI";PRODUCT_CALCULATION!F39;"") | S45: =IF(PRODUCT_CALCULATION!B39="SI";PRODUCT_CALCULATION!K39;"") | T45: =IF(PRODUCT_CALCULATION!B39="SI";PRODUCT_CALCULATION!J39;"") | U45: =IF(PRODUCT_CALCULATION!B39="SI";PRODUCT_CALCULATION!N39;"") | V45: =IF(PRODUCT_CALCULATION!B39="SI";PRODUCT_CALCULATION!L39;"") | W45: =IF(PRODUCT_CALCULATION!B39="SI";PRODUCT_CALCULATION!M39;"") | X45: =IF(R39="";"";CEILING(R39/S39;1)) | Y45: =IF(R39="";"";R39*T39) | Z45: =IF(R39="";"";R39*V39)
A46: =INPUT_PRODUCT!B1 | B46: =INPUT_PRODUCT!B2 | C46: =INPUT_PRODUCT!B6 | D46: Arias Group Caribe SRL | F46: Tarancón, España | G46: =INPUT_PRODUCT!B7 | K46: =IF(PRODUCT_CALCULATION!B40="SI";PRODUCT_CALCULATION!C40;"") | L46: =IF(PRODUCT_CALCULATION!B40="SI";PRODUCT_CALCULATION!E40;"") | M46: =IF(PRODUCT_CALCULATION!C40="";"";VLOOKUP(PRODUCT_CALCULATION!C40;PRODUCT!B:Q;16;FALSE)) | N46: =IF(PRODUCT_CALCULATION!C40="";"";VLOOKUP(PRODUCT_CALCULATION!C40;PRODUCT!B:R;17;FALSE)) | O46: =IF(PRODUCT_CALCULATION!C40="";"";VLOOKUP(PRODUCT_CALCULATION!C40;PRODUCT!B:S;18;FALSE)) | P46: =IF(PRODUCT_CALCULATION!C40="";"";VLOOKUP(PRODUCT_CALCULATION!C40;PRODUCT!B:D;3;FALSE)) | Q46: =IF(PRODUCT_CALCULATION!C40="";"";VLOOKUP(PRODUCT_CALCULATION!C40;PRODUCT!B:E;4;FALSE)) | R46: =IF(PRODUCT_CALCULATION!B40="SI";PRODUCT_CALCULATION!F40;"") | S46: =IF(PRODUCT_CALCULATION!B40="SI";PRODUCT_CALCULATION!K40;"") | T46: =IF(PRODUCT_CALCULATION!B40="SI";PRODUCT_CALCULATION!J40;"") | U46: =IF(PRODUCT_CALCULATION!B40="SI";PRODUCT_CALCULATION!N40;"") | V46: =IF(PRODUCT_CALCULATION!B40="SI";PRODUCT_CALCULATION!L40;"") | W46: =IF(PRODUCT_CALCULATION!B40="SI";PRODUCT_CALCULATION!M40;"") | X46: =IF(R40="";"";CEILING(R40/S40;1)) | Y46: =IF(R40="";"";R40*T40) | Z46: =IF(R40="";"";R40*V40)
A47: =INPUT_PRODUCT!B1 | B47: =INPUT_PRODUCT!B2 | C47: =INPUT_PRODUCT!B6 | D47: Arias Group Caribe SRL | F47: Tarancón, España | G47: =INPUT_PRODUCT!B7 | K47: =IF(PRODUCT_CALCULATION!B41="SI";PRODUCT_CALCULATION!C41;"") | L47: =IF(PRODUCT_CALCULATION!B41="SI";PRODUCT_CALCULATION!E41;"") | M47: =IF(PRODUCT_CALCULATION!C41="";"";VLOOKUP(PRODUCT_CALCULATION!C41;PRODUCT!B:Q;16;FALSE)) | N47: =IF(PRODUCT_CALCULATION!C41="";"";VLOOKUP(PRODUCT_CALCULATION!C41;PRODUCT!B:R;17;FALSE)) | O47: =IF(PRODUCT_CALCULATION!C41="";"";VLOOKUP(PRODUCT_CALCULATION!C41;PRODUCT!B:S;18;FALSE)) | P47: =IF(PRODUCT_CALCULATION!C41="";"";VLOOKUP(PRODUCT_CALCULATION!C41;PRODUCT!B:D;3;FALSE)) | Q47: =IF(PRODUCT_CALCULATION!C41="";"";VLOOKUP(PRODUCT_CALCULATION!C41;PRODUCT!B:E;4;FALSE)) | R47: =IF(PRODUCT_CALCULATION!B41="SI";PRODUCT_CALCULATION!F41;"") | S47: =IF(PRODUCT_CALCULATION!B41="SI";PRODUCT_CALCULATION!K41;"") | T47: =IF(PRODUCT_CALCULATION!B41="SI";PRODUCT_CALCULATION!J41;"") | U47: =IF(PRODUCT_CALCULATION!B41="SI";PRODUCT_CALCULATION!N41;"") | V47: =IF(PRODUCT_CALCULATION!B41="SI";PRODUCT_CALCULATION!L41;"") | W47: =IF(PRODUCT_CALCULATION!B41="SI";PRODUCT_CALCULATION!M41;"") | X47: =IF(R41="";"";CEILING(R41/S41;1)) | Y47: =IF(R41="";"";R41*T41) | Z47: =IF(R41="";"";R41*V41)
A48: =INPUT_PRODUCT!B1 | B48: =INPUT_PRODUCT!B2 | C48: =INPUT_PRODUCT!B6 | D48: Arias Group Caribe SRL | F48: Tarancón, España | G48: =INPUT_PRODUCT!B7 | K48: =IF(PRODUCT_CALCULATION!B42="SI";PRODUCT_CALCULATION!C42;"") | L48: =IF(PRODUCT_CALCULATION!B42="SI";PRODUCT_CALCULATION!E42;"") | M48: =IF(PRODUCT_CALCULATION!C42="";"";VLOOKUP(PRODUCT_CALCULATION!C42;PRODUCT!B:Q;16;FALSE)) | N48: =IF(PRODUCT_CALCULATION!C42="";"";VLOOKUP(PRODUCT_CALCULATION!C42;PRODUCT!B:R;17;FALSE)) | O48: =IF(PRODUCT_CALCULATION!C42="";"";VLOOKUP(PRODUCT_CALCULATION!C42;PRODUCT!B:S;18;FALSE)) | P48: =IF(PRODUCT_CALCULATION!C42="";"";VLOOKUP(PRODUCT_CALCULATION!C42;PRODUCT!B:D;3;FALSE)) | Q48: =IF(PRODUCT_CALCULATION!C42="";"";VLOOKUP(PRODUCT_CALCULATION!C42;PRODUCT!B:E;4;FALSE)) | R48: =IF(PRODUCT_CALCULATION!B42="SI";PRODUCT_CALCULATION!F42;"") | S48: =IF(PRODUCT_CALCULATION!B42="SI";PRODUCT_CALCULATION!K42;"") | T48: =IF(PRODUCT_CALCULATION!B42="SI";PRODUCT_CALCULATION!J42;"") | U48: =IF(PRODUCT_CALCULATION!B42="SI";PRODUCT_CALCULATION!N42;"") | V48: =IF(PRODUCT_CALCULATION!B42="SI";PRODUCT_CALCULATION!L42;"") | W48: =IF(PRODUCT_CALCULATION!B42="SI";PRODUCT_CALCULATION!M42;"") | X48: =IF(R42="";"";CEILING(R42/S42;1)) | Y48: =IF(R42="";"";R42*T42) | Z48: =IF(R42="";"";R42*V42)
A49: =INPUT_PRODUCT!B1 | B49: =INPUT_PRODUCT!B2 | C49: =INPUT_PRODUCT!B6 | D49: Arias Group Caribe SRL | F49: Tarancón, España | G49: =INPUT_PRODUCT!B7 | K49: =IF(PRODUCT_CALCULATION!B43="SI";PRODUCT_CALCULATION!C43;"") | L49: =IF(PRODUCT_CALCULATION!B43="SI";PRODUCT_CALCULATION!E43;"") | M49: =IF(PRODUCT_CALCULATION!C43="";"";VLOOKUP(PRODUCT_CALCULATION!C43;PRODUCT!B:Q;16;FALSE)) | N49: =IF(PRODUCT_CALCULATION!C43="";"";VLOOKUP(PRODUCT_CALCULATION!C43;PRODUCT!B:R;17;FALSE)) | O49: =IF(PRODUCT_CALCULATION!C43="";"";VLOOKUP(PRODUCT_CALCULATION!C43;PRODUCT!B:S;18;FALSE)) | P49: =IF(PRODUCT_CALCULATION!C43="";"";VLOOKUP(PRODUCT_CALCULATION!C43;PRODUCT!B:D;3;FALSE)) | Q49: =IF(PRODUCT_CALCULATION!C43="";"";VLOOKUP(PRODUCT_CALCULATION!C43;PRODUCT!B:E;4;FALSE)) | R49: =IF(PRODUCT_CALCULATION!B43="SI";PRODUCT_CALCULATION!F43;"") | S49: =IF(PRODUCT_CALCULATION!B43="SI";PRODUCT_CALCULATION!K43;"") | T49: =IF(PRODUCT_CALCULATION!B43="SI";PRODUCT_CALCULATION!J43;"") | U49: =IF(PRODUCT_CALCULATION!B43="SI";PRODUCT_CALCULATION!N43;"") | V49: =IF(PRODUCT_CALCULATION!B43="SI";PRODUCT_CALCULATION!L43;"") | W49: =IF(PRODUCT_CALCULATION!B43="SI";PRODUCT_CALCULATION!M43;"") | X49: =IF(R43="";"";CEILING(R43/S43;1)) | Y49: =IF(R43="";"";R43*T43) | Z49: =IF(R43="";"";R43*V43)
A50: =INPUT_PRODUCT!B1 | B50: =INPUT_PRODUCT!B2 | C50: =INPUT_PRODUCT!B6 | D50: Arias Group Caribe SRL | F50: Tarancón, España | G50: =INPUT_PRODUCT!B7 | K50: =IF(PRODUCT_CALCULATION!B44="SI";PRODUCT_CALCULATION!C44;"") | L50: =IF(PRODUCT_CALCULATION!B44="SI";PRODUCT_CALCULATION!E44;"") | M50: =IF(PRODUCT_CALCULATION!C44="";"";VLOOKUP(PRODUCT_CALCULATION!C44;PRODUCT!B:Q;16;FALSE)) | N50: =IF(PRODUCT_CALCULATION!C44="";"";VLOOKUP(PRODUCT_CALCULATION!C44;PRODUCT!B:R;17;FALSE)) | O50: =IF(PRODUCT_CALCULATION!C44="";"";VLOOKUP(PRODUCT_CALCULATION!C44;PRODUCT!B:S;18;FALSE)) | P50: =IF(PRODUCT_CALCULATION!C44="";"";VLOOKUP(PRODUCT_CALCULATION!C44;PRODUCT!B:D;3;FALSE)) | Q50: =IF(PRODUCT_CALCULATION!C44="";"";VLOOKUP(PRODUCT_CALCULATION!C44;PRODUCT!B:E;4;FALSE)) | R50: =IF(PRODUCT_CALCULATION!B44="SI";PRODUCT_CALCULATION!F44;"") | S50: =IF(PRODUCT_CALCULATION!B44="SI";PRODUCT_CALCULATION!K44;"") | T50: =IF(PRODUCT_CALCULATION!B44="SI";PRODUCT_CALCULATION!J44;"") | U50: =IF(PRODUCT_CALCULATION!B44="SI";PRODUCT_CALCULATION!N44;"") | V50: =IF(PRODUCT_CALCULATION!B44="SI";PRODUCT_CALCULATION!L44;"") | W50: =IF(PRODUCT_CALCULATION!B44="SI";PRODUCT_CALCULATION!M44;"") | X50: =IF(R44="";"";CEILING(R44/S44;1)) | Y50: =IF(R44="";"";R44*T44) | Z50: =IF(R44="";"";R44*V44)
A51: =INPUT_PRODUCT!B1 | B51: =INPUT_PRODUCT!B2 | C51: =INPUT_PRODUCT!B6 | D51: Arias Group Caribe SRL | F51: Tarancón, España | G51: =INPUT_PRODUCT!B7 | K51: =IF(PRODUCT_CALCULATION!B45="SI";PRODUCT_CALCULATION!C45;"") | L51: =IF(PRODUCT_CALCULATION!B45="SI";PRODUCT_CALCULATION!E45;"") | M51: =IF(PRODUCT_CALCULATION!C45="";"";VLOOKUP(PRODUCT_CALCULATION!C45;PRODUCT!B:Q;16;FALSE)) | N51: =IF(PRODUCT_CALCULATION!C45="";"";VLOOKUP(PRODUCT_CALCULATION!C45;PRODUCT!B:R;17;FALSE)) | O51: =IF(PRODUCT_CALCULATION!C45="";"";VLOOKUP(PRODUCT_CALCULATION!C45;PRODUCT!B:S;18;FALSE)) | P51: =IF(PRODUCT_CALCULATION!C45="";"";VLOOKUP(PRODUCT_CALCULATION!C45;PRODUCT!B:D;3;FALSE)) | Q51: =IF(PRODUCT_CALCULATION!C45="";"";VLOOKUP(PRODUCT_CALCULATION!C45;PRODUCT!B:E;4;FALSE)) | R51: =IF(PRODUCT_CALCULATION!B45="SI";PRODUCT_CALCULATION!F45;"") | S51: =IF(PRODUCT_CALCULATION!B45="SI";PRODUCT_CALCULATION!K45;"") | T51: =IF(PRODUCT_CALCULATION!B45="SI";PRODUCT_CALCULATION!J45;"") | U51: =IF(PRODUCT_CALCULATION!B45="SI";PRODUCT_CALCULATION!N45;"") | V51: =IF(PRODUCT_CALCULATION!B45="SI";PRODUCT_CALCULATION!L45;"") | W51: =IF(PRODUCT_CALCULATION!B45="SI";PRODUCT_CALCULATION!M45;"") | X51: =IF(R45="";"";CEILING(R45/S45;1)) | Y51: =IF(R45="";"";R45*T45) | Z51: =IF(R45="";"";R45*V45)
A52: =INPUT_PRODUCT!B1 | B52: =INPUT_PRODUCT!B2 | C52: =INPUT_PRODUCT!B6 | D52: Arias Group Caribe SRL | F52: Tarancón, España | G52: =INPUT_PRODUCT!B7 | K52: =IF(PRODUCT_CALCULATION!B46="SI";PRODUCT_CALCULATION!C46;"") | L52: =IF(PRODUCT_CALCULATION!B46="SI";PRODUCT_CALCULATION!E46;"") | M52: =IF(PRODUCT_CALCULATION!C46="";"";VLOOKUP(PRODUCT_CALCULATION!C46;PRODUCT!B:Q;16;FALSE)) | N52: =IF(PRODUCT_CALCULATION!C46="";"";VLOOKUP(PRODUCT_CALCULATION!C46;PRODUCT!B:R;17;FALSE)) | O52: =IF(PRODUCT_CALCULATION!C46="";"";VLOOKUP(PRODUCT_CALCULATION!C46;PRODUCT!B:S;18;FALSE)) | P52: =IF(PRODUCT_CALCULATION!C46="";"";VLOOKUP(PRODUCT_CALCULATION!C46;PRODUCT!B:D;3;FALSE)) | Q52: =IF(PRODUCT_CALCULATION!C46="";"";VLOOKUP(PRODUCT_CALCULATION!C46;PRODUCT!B:E;4;FALSE)) | R52: =IF(PRODUCT_CALCULATION!B46="SI";PRODUCT_CALCULATION!F46;"") | S52: =IF(PRODUCT_CALCULATION!B46="SI";PRODUCT_CALCULATION!K46;"") | T52: =IF(PRODUCT_CALCULATION!B46="SI";PRODUCT_CALCULATION!J46;"") | U52: =IF(PRODUCT_CALCULATION!B46="SI";PRODUCT_CALCULATION!N46;"") | V52: =IF(PRODUCT_CALCULATION!B46="SI";PRODUCT_CALCULATION!L46;"") | W52: =IF(PRODUCT_CALCULATION!B46="SI";PRODUCT_CALCULATION!M46;"") | X52: =IF(R46="";"";CEILING(R46/S46;1)) | Y52: =IF(R46="";"";R46*T46) | Z52: =IF(R46="";"";R46*V46)
A53: =INPUT_PRODUCT!B1 | B53: =INPUT_PRODUCT!B2 | C53: =INPUT_PRODUCT!B6 | D53: Arias Group Caribe SRL | F53: Tarancón, España | G53: =INPUT_PRODUCT!B7 | K53: =IF(PRODUCT_CALCULATION!B47="SI";PRODUCT_CALCULATION!C47;"") | L53: =IF(PRODUCT_CALCULATION!B47="SI";PRODUCT_CALCULATION!E47;"") | M53: =IF(PRODUCT_CALCULATION!C47="";"";VLOOKUP(PRODUCT_CALCULATION!C47;PRODUCT!B:Q;16;FALSE)) | N53: =IF(PRODUCT_CALCULATION!C47="";"";VLOOKUP(PRODUCT_CALCULATION!C47;PRODUCT!B:R;17;FALSE)) | O53: =IF(PRODUCT_CALCULATION!C47="";"";VLOOKUP(PRODUCT_CALCULATION!C47;PRODUCT!B:S;18;FALSE)) | P53: =IF(PRODUCT_CALCULATION!C47="";"";VLOOKUP(PRODUCT_CALCULATION!C47;PRODUCT!B:D;3;FALSE)) | Q53: =IF(PRODUCT_CALCULATION!C47="";"";VLOOKUP(PRODUCT_CALCULATION!C47;PRODUCT!B:E;4;FALSE)) | R53: =IF(PRODUCT_CALCULATION!B47="SI";PRODUCT_CALCULATION!F47;"") | S53: =IF(PRODUCT_CALCULATION!B47="SI";PRODUCT_CALCULATION!K47;"") | T53: =IF(PRODUCT_CALCULATION!B47="SI";PRODUCT_CALCULATION!J47;"") | U53: =IF(PRODUCT_CALCULATION!B47="SI";PRODUCT_CALCULATION!N47;"") | V53: =IF(PRODUCT_CALCULATION!B47="SI";PRODUCT_CALCULATION!L47;"") | W53: =IF(PRODUCT_CALCULATION!B47="SI";PRODUCT_CALCULATION!M47;"") | X53: =IF(R47="";"";CEILING(R47/S47;1)) | Y53: =IF(R47="";"";R47*T47) | Z53: =IF(R47="";"";R47*V47)
A54: =INPUT_PRODUCT!B1 | B54: =INPUT_PRODUCT!B2 | C54: =INPUT_PRODUCT!B6 | D54: Arias Group Caribe SRL | F54: Tarancón, España | G54: =INPUT_PRODUCT!B7 | K54: =IF(PRODUCT_CALCULATION!B48="SI";PRODUCT_CALCULATION!C48;"") | L54: =IF(PRODUCT_CALCULATION!B48="SI";PRODUCT_CALCULATION!E48;"") | M54: =IF(PRODUCT_CALCULATION!C48="";"";VLOOKUP(PRODUCT_CALCULATION!C48;PRODUCT!B:Q;16;FALSE)) | N54: =IF(PRODUCT_CALCULATION!C48="";"";VLOOKUP(PRODUCT_CALCULATION!C48;PRODUCT!B:R;17;FALSE)) | O54: =IF(PRODUCT_CALCULATION!C48="";"";VLOOKUP(PRODUCT_CALCULATION!C48;PRODUCT!B:S;18;FALSE)) | P54: =IF(PRODUCT_CALCULATION!C48="";"";VLOOKUP(PRODUCT_CALCULATION!C48;PRODUCT!B:D;3;FALSE)) | Q54: =IF(PRODUCT_CALCULATION!C48="";"";VLOOKUP(PRODUCT_CALCULATION!C48;PRODUCT!B:E;4;FALSE)) | R54: =IF(PRODUCT_CALCULATION!B48="SI";PRODUCT_CALCULATION!F48;"") | S54: =IF(PRODUCT_CALCULATION!B48="SI";PRODUCT_CALCULATION!K48;"") | T54: =IF(PRODUCT_CALCULATION!B48="SI";PRODUCT_CALCULATION!J48;"") | U54: =IF(PRODUCT_CALCULATION!B48="SI";PRODUCT_CALCULATION!N48;"") | V54: =IF(PRODUCT_CALCULATION!B48="SI";PRODUCT_CALCULATION!L48;"") | W54: =IF(PRODUCT_CALCULATION!B48="SI";PRODUCT_CALCULATION!M48;"") | X54: =IF(R48="";"";CEILING(R48/S48;1)) | Y54: =IF(R48="";"";R48*T48) | Z54: =IF(R48="";"";R48*V48)
A55: =INPUT_PRODUCT!B1 | B55: =INPUT_PRODUCT!B2 | C55: =INPUT_PRODUCT!B6 | D55: Arias Group Caribe SRL | F55: Tarancón, España | G55: =INPUT_PRODUCT!B7 | K55: =IF(PRODUCT_CALCULATION!B49="SI";PRODUCT_CALCULATION!C49;"") | L55: =IF(PRODUCT_CALCULATION!B49="SI";PRODUCT_CALCULATION!E49;"") | M55: =IF(PRODUCT_CALCULATION!C49="";"";VLOOKUP(PRODUCT_CALCULATION!C49;PRODUCT!B:Q;16;FALSE)) | N55: =IF(PRODUCT_CALCULATION!C49="";"";VLOOKUP(PRODUCT_CALCULATION!C49;PRODUCT!B:R;17;FALSE)) | O55: =IF(PRODUCT_CALCULATION!C49="";"";VLOOKUP(PRODUCT_CALCULATION!C49;PRODUCT!B:S;18;FALSE)) | P55: =IF(PRODUCT_CALCULATION!C49="";"";VLOOKUP(PRODUCT_CALCULATION!C49;PRODUCT!B:D;3;FALSE)) | Q55: =IF(PRODUCT_CALCULATION!C49="";"";VLOOKUP(PRODUCT_CALCULATION!C49;PRODUCT!B:E;4;FALSE)) | R55: =IF(PRODUCT_CALCULATION!B49="SI";PRODUCT_CALCULATION!F49;"") | S55: =IF(PRODUCT_CALCULATION!B49="SI";PRODUCT_CALCULATION!K49;"") | T55: =IF(PRODUCT_CALCULATION!B49="SI";PRODUCT_CALCULATION!J49;"") | U55: =IF(PRODUCT_CALCULATION!B49="SI";PRODUCT_CALCULATION!N49;"") | V55: =IF(PRODUCT_CALCULATION!B49="SI";PRODUCT_CALCULATION!L49;"") | W55: =IF(PRODUCT_CALCULATION!B49="SI";PRODUCT_CALCULATION!M49;"") | X55: =IF(R49="";"";CEILING(R49/S49;1)) | Y55: =IF(R49="";"";R49*T49) | Z55: =IF(R49="";"";R49*V49)
A56: =INPUT_PRODUCT!B1 | B56: =INPUT_PRODUCT!B2 | C56: =INPUT_PRODUCT!B6 | D56: Arias Group Caribe SRL | F56: Tarancón, España | G56: =INPUT_PRODUCT!B7 | K56: =IF(PRODUCT_CALCULATION!B50="SI";PRODUCT_CALCULATION!C50;"") | L56: =IF(PRODUCT_CALCULATION!B50="SI";PRODUCT_CALCULATION!E50;"") | M56: =IF(PRODUCT_CALCULATION!C50="";"";VLOOKUP(PRODUCT_CALCULATION!C50;PRODUCT!B:Q;16;FALSE)) | N56: =IF(PRODUCT_CALCULATION!C50="";"";VLOOKUP(PRODUCT_CALCULATION!C50;PRODUCT!B:R;17;FALSE)) | O56: =IF(PRODUCT_CALCULATION!C50="";"";VLOOKUP(PRODUCT_CALCULATION!C50;PRODUCT!B:S;18;FALSE)) | P56: =IF(PRODUCT_CALCULATION!C50="";"";VLOOKUP(PRODUCT_CALCULATION!C50;PRODUCT!B:D;3;FALSE)) | Q56: =IF(PRODUCT_CALCULATION!C50="";"";VLOOKUP(PRODUCT_CALCULATION!C50;PRODUCT!B:E;4;FALSE)) | R56: =IF(PRODUCT_CALCULATION!B50="SI";PRODUCT_CALCULATION!F50;"") | S56: =IF(PRODUCT_CALCULATION!B50="SI";PRODUCT_CALCULATION!K50;"") | T56: =IF(PRODUCT_CALCULATION!B50="SI";PRODUCT_CALCULATION!J50;"") | U56: =IF(PRODUCT_CALCULATION!B50="SI";PRODUCT_CALCULATION!N50;"") | V56: =IF(PRODUCT_CALCULATION!B50="SI";PRODUCT_CALCULATION!L50;"") | W56: =IF(PRODUCT_CALCULATION!B50="SI";PRODUCT_CALCULATION!M50;"") | X56: =IF(R50="";"";CEILING(R50/S50;1)) | Y56: =IF(R50="";"";R50*T50) | Z56: =IF(R50="";"";R50*V50)
A57: =INPUT_PRODUCT!B1 | B57: =INPUT_PRODUCT!B2 | C57: =INPUT_PRODUCT!B6 | D57: Arias Group Caribe SRL | F57: Tarancón, España | G57: =INPUT_PRODUCT!B7 | K57: =IF(PRODUCT_CALCULATION!B51="SI";PRODUCT_CALCULATION!C51;"") | L57: =IF(PRODUCT_CALCULATION!B51="SI";PRODUCT_CALCULATION!E51;"") | M57: =IF(PRODUCT_CALCULATION!C51="";"";VLOOKUP(PRODUCT_CALCULATION!C51;PRODUCT!B:Q;16;FALSE)) | N57: =IF(PRODUCT_CALCULATION!C51="";"";VLOOKUP(PRODUCT_CALCULATION!C51;PRODUCT!B:R;17;FALSE)) | O57: =IF(PRODUCT_CALCULATION!C51="";"";VLOOKUP(PRODUCT_CALCULATION!C51;PRODUCT!B:S;18;FALSE)) | P57: =IF(PRODUCT_CALCULATION!C51="";"";VLOOKUP(PRODUCT_CALCULATION!C51;PRODUCT!B:D;3;FALSE)) | Q57: =IF(PRODUCT_CALCULATION!C51="";"";VLOOKUP(PRODUCT_CALCULATION!C51;PRODUCT!B:E;4;FALSE)) | R57: =IF(PRODUCT_CALCULATION!B51="SI";PRODUCT_CALCULATION!F51;"") | S57: =IF(PRODUCT_CALCULATION!B51="SI";PRODUCT_CALCULATION!K51;"") | T57: =IF(PRODUCT_CALCULATION!B51="SI";PRODUCT_CALCULATION!J51;"") | U57: =IF(PRODUCT_CALCULATION!B51="SI";PRODUCT_CALCULATION!N51;"") | V57: =IF(PRODUCT_CALCULATION!B51="SI";PRODUCT_CALCULATION!L51;"") | W57: =IF(PRODUCT_CALCULATION!B51="SI";PRODUCT_CALCULATION!M51;"") | X57: =IF(R51="";"";CEILING(R51/S51;1)) | Y57: =IF(R51="";"";R51*T51) | Z57: =IF(R51="";"";R51*V51)
A58: =INPUT_PRODUCT!B1 | B58: =INPUT_PRODUCT!B2 | C58: =INPUT_PRODUCT!B6 | D58: Arias Group Caribe SRL | F58: Tarancón, España | G58: =INPUT_PRODUCT!B7 | K58: =IF(PRODUCT_CALCULATION!B52="SI";PRODUCT_CALCULATION!C52;"") | L58: =IF(PRODUCT_CALCULATION!B52="SI";PRODUCT_CALCULATION!E52;"") | M58: =IF(PRODUCT_CALCULATION!C52="";"";VLOOKUP(PRODUCT_CALCULATION!C52;PRODUCT!B:Q;16;FALSE)) | N58: =IF(PRODUCT_CALCULATION!C52="";"";VLOOKUP(PRODUCT_CALCULATION!C52;PRODUCT!B:R;17;FALSE)) | O58: =IF(PRODUCT_CALCULATION!C52="";"";VLOOKUP(PRODUCT_CALCULATION!C52;PRODUCT!B:S;18;FALSE)) | P58: =IF(PRODUCT_CALCULATION!C52="";"";VLOOKUP(PRODUCT_CALCULATION!C52;PRODUCT!B:D;3;FALSE)) | Q58: =IF(PRODUCT_CALCULATION!C52="";"";VLOOKUP(PRODUCT_CALCULATION!C52;PRODUCT!B:E;4;FALSE)) | R58: =IF(PRODUCT_CALCULATION!B52="SI";PRODUCT_CALCULATION!F52;"") | S58: =IF(PRODUCT_CALCULATION!B52="SI";PRODUCT_CALCULATION!K52;"") | T58: =IF(PRODUCT_CALCULATION!B52="SI";PRODUCT_CALCULATION!J52;"") | U58: =IF(PRODUCT_CALCULATION!B52="SI";PRODUCT_CALCULATION!N52;"") | V58: =IF(PRODUCT_CALCULATION!B52="SI";PRODUCT_CALCULATION!L52;"") | W58: =IF(PRODUCT_CALCULATION!B52="SI";PRODUCT_CALCULATION!M52;"") | X58: =IF(R52="";"";CEILING(R52/S52;1)) | Y58: =IF(R52="";"";R52*T52) | Z58: =IF(R52="";"";R52*V52)
A59: =INPUT_PRODUCT!B1 | B59: =INPUT_PRODUCT!B2 | C59: =INPUT_PRODUCT!B6 | D59: Arias Group Caribe SRL | F59: Tarancón, España | G59: =INPUT_PRODUCT!B7 | K59: =IF(PRODUCT_CALCULATION!B53="SI";PRODUCT_CALCULATION!C53;"") | L59: =IF(PRODUCT_CALCULATION!B53="SI";PRODUCT_CALCULATION!E53;"") | M59: =IF(PRODUCT_CALCULATION!C53="";"";VLOOKUP(PRODUCT_CALCULATION!C53;PRODUCT!B:Q;16;FALSE)) | N59: =IF(PRODUCT_CALCULATION!C53="";"";VLOOKUP(PRODUCT_CALCULATION!C53;PRODUCT!B:R;17;FALSE)) | O59: =IF(PRODUCT_CALCULATION!C53="";"";VLOOKUP(PRODUCT_CALCULATION!C53;PRODUCT!B:S;18;FALSE)) | P59: =IF(PRODUCT_CALCULATION!C53="";"";VLOOKUP(PRODUCT_CALCULATION!C53;PRODUCT!B:D;3;FALSE)) | Q59: =IF(PRODUCT_CALCULATION!C53="";"";VLOOKUP(PRODUCT_CALCULATION!C53;PRODUCT!B:E;4;FALSE)) | R59: =IF(PRODUCT_CALCULATION!B53="SI";PRODUCT_CALCULATION!F53;"") | S59: =IF(PRODUCT_CALCULATION!B53="SI";PRODUCT_CALCULATION!K53;"") | T59: =IF(PRODUCT_CALCULATION!B53="SI";PRODUCT_CALCULATION!J53;"") | U59: =IF(PRODUCT_CALCULATION!B53="SI";PRODUCT_CALCULATION!N53;"") | V59: =IF(PRODUCT_CALCULATION!B53="SI";PRODUCT_CALCULATION!L53;"") | W59: =IF(PRODUCT_CALCULATION!B53="SI";PRODUCT_CALCULATION!M53;"") | X59: =IF(R53="";"";CEILING(R53/S53;1)) | Y59: =IF(R53="";"";R53*T53) | Z59: =IF(R53="";"";R53*V53)
A60: =INPUT_PRODUCT!B1 | B60: =INPUT_PRODUCT!B2 | C60: =INPUT_PRODUCT!B6 | D60: Arias Group Caribe SRL | F60: Tarancón, España | G60: =INPUT_PRODUCT!B7 | K60: =IF(PRODUCT_CALCULATION!B54="SI";PRODUCT_CALCULATION!C54;"") | L60: =IF(PRODUCT_CALCULATION!B54="SI";PRODUCT_CALCULATION!E54;"") | M60: =IF(PRODUCT_CALCULATION!C54="";"";VLOOKUP(PRODUCT_CALCULATION!C54;PRODUCT!B:Q;16;FALSE)) | N60: =IF(PRODUCT_CALCULATION!C54="";"";VLOOKUP(PRODUCT_CALCULATION!C54;PRODUCT!B:R;17;FALSE)) | O60: =IF(PRODUCT_CALCULATION!C54="";"";VLOOKUP(PRODUCT_CALCULATION!C54;PRODUCT!B:S;18;FALSE)) | P60: =IF(PRODUCT_CALCULATION!C54="";"";VLOOKUP(PRODUCT_CALCULATION!C54;PRODUCT!B:D;3;FALSE)) | Q60: =IF(PRODUCT_CALCULATION!C54="";"";VLOOKUP(PRODUCT_CALCULATION!C54;PRODUCT!B:E;4;FALSE)) | R60: =IF(PRODUCT_CALCULATION!B54="SI";PRODUCT_CALCULATION!F54;"") | S60: =IF(PRODUCT_CALCULATION!B54="SI";PRODUCT_CALCULATION!K54;"") | T60: =IF(PRODUCT_CALCULATION!B54="SI";PRODUCT_CALCULATION!J54;"") | U60: =IF(PRODUCT_CALCULATION!B54="SI";PRODUCT_CALCULATION!N54;"") | V60: =IF(PRODUCT_CALCULATION!B54="SI";PRODUCT_CALCULATION!L54;"") | W60: =IF(PRODUCT_CALCULATION!B54="SI";PRODUCT_CALCULATION!M54;"") | X60: =IF(R54="";"";CEILING(R54/S54;1)) | Y60: =IF(R54="";"";R54*T54) | Z60: =IF(R54="";"";R54*V54)
A61: =INPUT_PRODUCT!B1 | B61: =INPUT_PRODUCT!B2 | C61: =INPUT_PRODUCT!B6 | D61: Arias Group Caribe SRL | F61: Tarancón, España | G61: =INPUT_PRODUCT!B7 | K61: =IF(PRODUCT_CALCULATION!B55="SI";PRODUCT_CALCULATION!C55;"") | L61: =IF(PRODUCT_CALCULATION!B55="SI";PRODUCT_CALCULATION!E55;"") | M61: =IF(PRODUCT_CALCULATION!C55="";"";VLOOKUP(PRODUCT_CALCULATION!C55;PRODUCT!B:Q;16;FALSE)) | N61: =IF(PRODUCT_CALCULATION!C55="";"";VLOOKUP(PRODUCT_CALCULATION!C55;PRODUCT!B:R;17;FALSE)) | O61: =IF(PRODUCT_CALCULATION!C55="";"";VLOOKUP(PRODUCT_CALCULATION!C55;PRODUCT!B:S;18;FALSE)) | P61: =IF(PRODUCT_CALCULATION!C55="";"";VLOOKUP(PRODUCT_CALCULATION!C55;PRODUCT!B:D;3;FALSE)) | Q61: =IF(PRODUCT_CALCULATION!C55="";"";VLOOKUP(PRODUCT_CALCULATION!C55;PRODUCT!B:E;4;FALSE)) | R61: =IF(PRODUCT_CALCULATION!B55="SI";PRODUCT_CALCULATION!F55;"") | S61: =IF(PRODUCT_CALCULATION!B55="SI";PRODUCT_CALCULATION!K55;"") | T61: =IF(PRODUCT_CALCULATION!B55="SI";PRODUCT_CALCULATION!J55;"") | U61: =IF(PRODUCT_CALCULATION!B55="SI";PRODUCT_CALCULATION!N55;"") | V61: =IF(PRODUCT_CALCULATION!B55="SI";PRODUCT_CALCULATION!L55;"") | W61: =IF(PRODUCT_CALCULATION!B55="SI";PRODUCT_CALCULATION!M55;"") | X61: =IF(R55="";"";CEILING(R55/S55;1)) | Y61: =IF(R55="";"";R55*T55) | Z61: =IF(R55="";"";R55*V55)
A62: =INPUT_PRODUCT!B1 | B62: =INPUT_PRODUCT!B2 | C62: =INPUT_PRODUCT!B6 | D62: Arias Group Caribe SRL | F62: Tarancón, España | G62: =INPUT_PRODUCT!B7 | K62: =IF(PRODUCT_CALCULATION!B56="SI";PRODUCT_CALCULATION!C56;"") | L62: =IF(PRODUCT_CALCULATION!B56="SI";PRODUCT_CALCULATION!E56;"") | M62: =IF(PRODUCT_CALCULATION!C56="";"";VLOOKUP(PRODUCT_CALCULATION!C56;PRODUCT!B:Q;16;FALSE)) | N62: =IF(PRODUCT_CALCULATION!C56="";"";VLOOKUP(PRODUCT_CALCULATION!C56;PRODUCT!B:R;17;FALSE)) | O62: =IF(PRODUCT_CALCULATION!C56="";"";VLOOKUP(PRODUCT_CALCULATION!C56;PRODUCT!B:S;18;FALSE)) | P62: =IF(PRODUCT_CALCULATION!C56="";"";VLOOKUP(PRODUCT_CALCULATION!C56;PRODUCT!B:D;3;FALSE)) | Q62: =IF(PRODUCT_CALCULATION!C56="";"";VLOOKUP(PRODUCT_CALCULATION!C56;PRODUCT!B:E;4;FALSE)) | R62: =IF(PRODUCT_CALCULATION!B56="SI";PRODUCT_CALCULATION!F56;"") | S62: =IF(PRODUCT_CALCULATION!B56="SI";PRODUCT_CALCULATION!K56;"") | T62: =IF(PRODUCT_CALCULATION!B56="SI";PRODUCT_CALCULATION!J56;"") | U62: =IF(PRODUCT_CALCULATION!B56="SI";PRODUCT_CALCULATION!N56;"") | V62: =IF(PRODUCT_CALCULATION!B56="SI";PRODUCT_CALCULATION!L56;"") | W62: =IF(PRODUCT_CALCULATION!B56="SI";PRODUCT_CALCULATION!M56;"") | X62: =IF(R56="";"";CEILING(R56/S56;1)) | Y62: =IF(R56="";"";R56*T56) | Z62: =IF(R56="";"";R56*V56)
A63: =INPUT_PRODUCT!B1 | B63: =INPUT_PRODUCT!B2 | C63: =INPUT_PRODUCT!B6 | D63: Arias Group Caribe SRL | F63: Tarancón, España | G63: =INPUT_PRODUCT!B7 | K63: =IF(PRODUCT_CALCULATION!B57="SI";PRODUCT_CALCULATION!C57;"") | L63: =IF(PRODUCT_CALCULATION!B57="SI";PRODUCT_CALCULATION!E57;"") | M63: =IF(PRODUCT_CALCULATION!C57="";"";VLOOKUP(PRODUCT_CALCULATION!C57;PRODUCT!B:Q;16;FALSE)) | N63: =IF(PRODUCT_CALCULATION!C57="";"";VLOOKUP(PRODUCT_CALCULATION!C57;PRODUCT!B:R;17;FALSE)) | O63: =IF(PRODUCT_CALCULATION!C57="";"";VLOOKUP(PRODUCT_CALCULATION!C57;PRODUCT!B:S;18;FALSE)) | P63: =IF(PRODUCT_CALCULATION!C57="";"";VLOOKUP(PRODUCT_CALCULATION!C57;PRODUCT!B:D;3;FALSE)) | Q63: =IF(PRODUCT_CALCULATION!C57="";"";VLOOKUP(PRODUCT_CALCULATION!C57;PRODUCT!B:E;4;FALSE)) | R63: =IF(PRODUCT_CALCULATION!B57="SI";PRODUCT_CALCULATION!F57;"") | S63: =IF(PRODUCT_CALCULATION!B57="SI";PRODUCT_CALCULATION!K57;"") | T63: =IF(PRODUCT_CALCULATION!B57="SI";PRODUCT_CALCULATION!J57;"") | U63: =IF(PRODUCT_CALCULATION!B57="SI";PRODUCT_CALCULATION!N57;"") | V63: =IF(PRODUCT_CALCULATION!B57="SI";PRODUCT_CALCULATION!L57;"") | W63: =IF(PRODUCT_CALCULATION!B57="SI";PRODUCT_CALCULATION!M57;"") | X63: =IF(R57="";"";CEILING(R57/S57;1)) | Y63: =IF(R57="";"";R57*T57) | Z63: =IF(R57="";"";R57*V57)
A64: =INPUT_PRODUCT!B1 | B64: =INPUT_PRODUCT!B2 | C64: =INPUT_PRODUCT!B6 | D64: Arias Group Caribe SRL | F64: Tarancón, España | G64: =INPUT_PRODUCT!B7 | K64: =IF(PRODUCT_CALCULATION!B58="SI";PRODUCT_CALCULATION!C58;"") | L64: =IF(PRODUCT_CALCULATION!B58="SI";PRODUCT_CALCULATION!E58;"") | M64: =IF(PRODUCT_CALCULATION!C58="";"";VLOOKUP(PRODUCT_CALCULATION!C58;PRODUCT!B:Q;16;FALSE)) | N64: =IF(PRODUCT_CALCULATION!C58="";"";VLOOKUP(PRODUCT_CALCULATION!C58;PRODUCT!B:R;17;FALSE)) | O64: =IF(PRODUCT_CALCULATION!C58="";"";VLOOKUP(PRODUCT_CALCULATION!C58;PRODUCT!B:S;18;FALSE)) | P64: =IF(PRODUCT_CALCULATION!C58="";"";VLOOKUP(PRODUCT_CALCULATION!C58;PRODUCT!B:D;3;FALSE)) | Q64: =IF(PRODUCT_CALCULATION!C58="";"";VLOOKUP(PRODUCT_CALCULATION!C58;PRODUCT!B:E;4;FALSE)) | R64: =IF(PRODUCT_CALCULATION!B58="SI";PRODUCT_CALCULATION!F58;"") | S64: =IF(PRODUCT_CALCULATION!B58="SI";PRODUCT_CALCULATION!K58;"") | T64: =IF(PRODUCT_CALCULATION!B58="SI";PRODUCT_CALCULATION!J58;"") | U64: =IF(PRODUCT_CALCULATION!B58="SI";PRODUCT_CALCULATION!N58;"") | V64: =IF(PRODUCT_CALCULATION!B58="SI";PRODUCT_CALCULATION!L58;"") | W64: =IF(PRODUCT_CALCULATION!B58="SI";PRODUCT_CALCULATION!M58;"") | X64: =IF(R58="";"";CEILING(R58/S58;1)) | Y64: =IF(R58="";"";R58*T58) | Z64: =IF(R58="";"";R58*V58)
A65: =INPUT_PRODUCT!B1 | B65: =INPUT_PRODUCT!B2 | C65: =INPUT_PRODUCT!B6 | D65: Arias Group Caribe SRL | F65: Tarancón, España | G65: =INPUT_PRODUCT!B7 | K65: =IF(PRODUCT_CALCULATION!B59="SI";PRODUCT_CALCULATION!C59;"") | L65: =IF(PRODUCT_CALCULATION!B59="SI";PRODUCT_CALCULATION!E59;"") | M65: =IF(PRODUCT_CALCULATION!C59="";"";VLOOKUP(PRODUCT_CALCULATION!C59;PRODUCT!B:Q;16;FALSE)) | N65: =IF(PRODUCT_CALCULATION!C59="";"";VLOOKUP(PRODUCT_CALCULATION!C59;PRODUCT!B:R;17;FALSE)) | O65: =IF(PRODUCT_CALCULATION!C59="";"";VLOOKUP(PRODUCT_CALCULATION!C59;PRODUCT!B:S;18;FALSE)) | P65: =IF(PRODUCT_CALCULATION!C59="";"";VLOOKUP(PRODUCT_CALCULATION!C59;PRODUCT!B:D;3;FALSE)) | Q65: =IF(PRODUCT_CALCULATION!C59="";"";VLOOKUP(PRODUCT_CALCULATION!C59;PRODUCT!B:E;4;FALSE)) | R65: =IF(PRODUCT_CALCULATION!B59="SI";PRODUCT_CALCULATION!F59;"") | S65: =IF(PRODUCT_CALCULATION!B59="SI";PRODUCT_CALCULATION!K59;"") | T65: =IF(PRODUCT_CALCULATION!B59="SI";PRODUCT_CALCULATION!J59;"") | U65: =IF(PRODUCT_CALCULATION!B59="SI";PRODUCT_CALCULATION!N59;"") | V65: =IF(PRODUCT_CALCULATION!B59="SI";PRODUCT_CALCULATION!L59;"") | W65: =IF(PRODUCT_CALCULATION!B59="SI";PRODUCT_CALCULATION!M59;"") | X65: =IF(R59="";"";CEILING(R59/S59;1)) | Y65: =IF(R59="";"";R59*T59) | Z65: =IF(R59="";"";R59*V59)
A66: =INPUT_PRODUCT!B1 | B66: =INPUT_PRODUCT!B2 | C66: =INPUT_PRODUCT!B6 | D66: Arias Group Caribe SRL | F66: Tarancón, España | G66: =INPUT_PRODUCT!B7 | K66: =IF(PRODUCT_CALCULATION!B60="SI";PRODUCT_CALCULATION!C60;"") | L66: =IF(PRODUCT_CALCULATION!B60="SI";PRODUCT_CALCULATION!E60;"") | M66: =IF(PRODUCT_CALCULATION!C60="";"";VLOOKUP(PRODUCT_CALCULATION!C60;PRODUCT!B:Q;16;FALSE)) | N66: =IF(PRODUCT_CALCULATION!C60="";"";VLOOKUP(PRODUCT_CALCULATION!C60;PRODUCT!B:R;17;FALSE)) | O66: =IF(PRODUCT_CALCULATION!C60="";"";VLOOKUP(PRODUCT_CALCULATION!C60;PRODUCT!B:S;18;FALSE)) | P66: =IF(PRODUCT_CALCULATION!C60="";"";VLOOKUP(PRODUCT_CALCULATION!C60;PRODUCT!B:D;3;FALSE)) | Q66: =IF(PRODUCT_CALCULATION!C60="";"";VLOOKUP(PRODUCT_CALCULATION!C60;PRODUCT!B:E;4;FALSE)) | R66: =IF(PRODUCT_CALCULATION!B60="SI";PRODUCT_CALCULATION!F60;"") | S66: =IF(PRODUCT_CALCULATION!B60="SI";PRODUCT_CALCULATION!K60;"") | T66: =IF(PRODUCT_CALCULATION!B60="SI";PRODUCT_CALCULATION!J60;"") | U66: =IF(PRODUCT_CALCULATION!B60="SI";PRODUCT_CALCULATION!N60;"") | V66: =IF(PRODUCT_CALCULATION!B60="SI";PRODUCT_CALCULATION!L60;"") | W66: =IF(PRODUCT_CALCULATION!B60="SI";PRODUCT_CALCULATION!M60;"") | X66: =IF(R60="";"";CEILING(R60/S60;1)) | Y66: =IF(R60="";"";R60*T60) | Z66: =IF(R60="";"";R60*V60)
A67: =INPUT_PRODUCT!B1 | B67: =INPUT_PRODUCT!B2 | C67: =INPUT_PRODUCT!B6 | D67: Arias Group Caribe SRL | F67: Tarancón, España | G67: =INPUT_PRODUCT!B7 | K67: =IF(PRODUCT_CALCULATION!B61="SI";PRODUCT_CALCULATION!C61;"") | L67: =IF(PRODUCT_CALCULATION!B61="SI";PRODUCT_CALCULATION!E61;"") | M67: =IF(PRODUCT_CALCULATION!C61="";"";VLOOKUP(PRODUCT_CALCULATION!C61;PRODUCT!B:Q;16;FALSE)) | N67: =IF(PRODUCT_CALCULATION!C61="";"";VLOOKUP(PRODUCT_CALCULATION!C61;PRODUCT!B:R;17;FALSE)) | O67: =IF(PRODUCT_CALCULATION!C61="";"";VLOOKUP(PRODUCT_CALCULATION!C61;PRODUCT!B:S;18;FALSE)) | P67: =IF(PRODUCT_CALCULATION!C61="";"";VLOOKUP(PRODUCT_CALCULATION!C61;PRODUCT!B:D;3;FALSE)) | Q67: =IF(PRODUCT_CALCULATION!C61="";"";VLOOKUP(PRODUCT_CALCULATION!C61;PRODUCT!B:E;4;FALSE)) | R67: =IF(PRODUCT_CALCULATION!B61="SI";PRODUCT_CALCULATION!F61;"") | S67: =IF(PRODUCT_CALCULATION!B61="SI";PRODUCT_CALCULATION!K61;"") | T67: =IF(PRODUCT_CALCULATION!B61="SI";PRODUCT_CALCULATION!J61;"") | U67: =IF(PRODUCT_CALCULATION!B61="SI";PRODUCT_CALCULATION!N61;"") | V67: =IF(PRODUCT_CALCULATION!B61="SI";PRODUCT_CALCULATION!L61;"") | W67: =IF(PRODUCT_CALCULATION!B61="SI";PRODUCT_CALCULATION!M61;"") | X67: =IF(R61="";"";CEILING(R61/S61;1)) | Y67: =IF(R61="";"";R61*T61) | Z67: =IF(R61="";"";R61*V61)
A68: =INPUT_PRODUCT!B1 | B68: =INPUT_PRODUCT!B2 | C68: =INPUT_PRODUCT!B6 | D68: Arias Group Caribe SRL | F68: Tarancón, España | G68: =INPUT_PRODUCT!B7 | K68: =IF(PRODUCT_CALCULATION!B62="SI";PRODUCT_CALCULATION!C62;"") | L68: =IF(PRODUCT_CALCULATION!B62="SI";PRODUCT_CALCULATION!E62;"") | M68: =IF(PRODUCT_CALCULATION!C62="";"";VLOOKUP(PRODUCT_CALCULATION!C62;PRODUCT!B:Q;16;FALSE)) | N68: =IF(PRODUCT_CALCULATION!C62="";"";VLOOKUP(PRODUCT_CALCULATION!C62;PRODUCT!B:R;17;FALSE)) | O68: =IF(PRODUCT_CALCULATION!C62="";"";VLOOKUP(PRODUCT_CALCULATION!C62;PRODUCT!B:S;18;FALSE)) | P68: =IF(PRODUCT_CALCULATION!C62="";"";VLOOKUP(PRODUCT_CALCULATION!C62;PRODUCT!B:D;3;FALSE)) | Q68: =IF(PRODUCT_CALCULATION!C62="";"";VLOOKUP(PRODUCT_CALCULATION!C62;PRODUCT!B:E;4;FALSE)) | R68: =IF(PRODUCT_CALCULATION!B62="SI";PRODUCT_CALCULATION!F62;"") | S68: =IF(PRODUCT_CALCULATION!B62="SI";PRODUCT_CALCULATION!K62;"") | T68: =IF(PRODUCT_CALCULATION!B62="SI";PRODUCT_CALCULATION!J62;"") | U68: =IF(PRODUCT_CALCULATION!B62="SI";PRODUCT_CALCULATION!N62;"") | V68: =IF(PRODUCT_CALCULATION!B62="SI";PRODUCT_CALCULATION!L62;"") | W68: =IF(PRODUCT_CALCULATION!B62="SI";PRODUCT_CALCULATION!M62;"") | X68: =IF(R62="";"";CEILING(R62/S62;1)) | Y68: =IF(R62="";"";R62*T62) | Z68: =IF(R62="";"";R62*V62)
A69: =INPUT_PRODUCT!B1 | B69: =INPUT_PRODUCT!B2 | C69: =INPUT_PRODUCT!B6 | D69: Arias Group Caribe SRL | F69: Tarancón, España | G69: =INPUT_PRODUCT!B7 | K69: =IF(PRODUCT_CALCULATION!B63="SI";PRODUCT_CALCULATION!C63;"") | L69: =IF(PRODUCT_CALCULATION!B63="SI";PRODUCT_CALCULATION!E63;"") | M69: =IF(PRODUCT_CALCULATION!C63="";"";VLOOKUP(PRODUCT_CALCULATION!C63;PRODUCT!B:Q;16;FALSE)) | N69: =IF(PRODUCT_CALCULATION!C63="";"";VLOOKUP(PRODUCT_CALCULATION!C63;PRODUCT!B:R;17;FALSE)) | O69: =IF(PRODUCT_CALCULATION!C63="";"";VLOOKUP(PRODUCT_CALCULATION!C63;PRODUCT!B:S;18;FALSE)) | P69: =IF(PRODUCT_CALCULATION!C63="";"";VLOOKUP(PRODUCT_CALCULATION!C63;PRODUCT!B:D;3;FALSE)) | Q69: =IF(PRODUCT_CALCULATION!C63="";"";VLOOKUP(PRODUCT_CALCULATION!C63;PRODUCT!B:E;4;FALSE)) | R69: =IF(PRODUCT_CALCULATION!B63="SI";PRODUCT_CALCULATION!F63;"") | S69: =IF(PRODUCT_CALCULATION!B63="SI";PRODUCT_CALCULATION!K63;"") | T69: =IF(PRODUCT_CALCULATION!B63="SI";PRODUCT_CALCULATION!J63;"") | U69: =IF(PRODUCT_CALCULATION!B63="SI";PRODUCT_CALCULATION!N63;"") | V69: =IF(PRODUCT_CALCULATION!B63="SI";PRODUCT_CALCULATION!L63;"") | W69: =IF(PRODUCT_CALCULATION!B63="SI";PRODUCT_CALCULATION!M63;"") | X69: =IF(R63="";"";CEILING(R63/S63;1)) | Y69: =IF(R63="";"";R63*T63) | Z69: =IF(R63="";"";R63*V63)
A70: =INPUT_PRODUCT!B1 | B70: =INPUT_PRODUCT!B2 | C70: =INPUT_PRODUCT!B6 | D70: Arias Group Caribe SRL | F70: Tarancón, España | G70: =INPUT_PRODUCT!B7 | K70: =IF(PRODUCT_CALCULATION!B64="SI";PRODUCT_CALCULATION!C64;"") | L70: =IF(PRODUCT_CALCULATION!B64="SI";PRODUCT_CALCULATION!E64;"") | M70: =IF(PRODUCT_CALCULATION!C64="";"";VLOOKUP(PRODUCT_CALCULATION!C64;PRODUCT!B:Q;16;FALSE)) | N70: =IF(PRODUCT_CALCULATION!C64="";"";VLOOKUP(PRODUCT_CALCULATION!C64;PRODUCT!B:R;17;FALSE)) | O70: =IF(PRODUCT_CALCULATION!C64="";"";VLOOKUP(PRODUCT_CALCULATION!C64;PRODUCT!B:S;18;FALSE)) | P70: =IF(PRODUCT_CALCULATION!C64="";"";VLOOKUP(PRODUCT_CALCULATION!C64;PRODUCT!B:D;3;FALSE)) | Q70: =IF(PRODUCT_CALCULATION!C64="";"";VLOOKUP(PRODUCT_CALCULATION!C64;PRODUCT!B:E;4;FALSE)) | R70: =IF(PRODUCT_CALCULATION!B64="SI";PRODUCT_CALCULATION!F64;"") | S70: =IF(PRODUCT_CALCULATION!B64="SI";PRODUCT_CALCULATION!K64;"") | T70: =IF(PRODUCT_CALCULATION!B64="SI";PRODUCT_CALCULATION!J64;"") | U70: =IF(PRODUCT_CALCULATION!B64="SI";PRODUCT_CALCULATION!N64;"") | V70: =IF(PRODUCT_CALCULATION!B64="SI";PRODUCT_CALCULATION!L64;"") | W70: =IF(PRODUCT_CALCULATION!B64="SI";PRODUCT_CALCULATION!M64;"") | X70: =IF(R64="";"";CEILING(R64/S64;1)) | Y70: =IF(R64="";"";R64*T64) | Z70: =IF(R64="";"";R64*V64)
A71: =INPUT_PRODUCT!B1 | B71: =INPUT_PRODUCT!B2 | C71: =INPUT_PRODUCT!B6 | D71: Arias Group Caribe SRL | F71: Tarancón, España | G71: =INPUT_PRODUCT!B7 | K71: =IF(PRODUCT_CALCULATION!B65="SI";PRODUCT_CALCULATION!C65;"") | L71: =IF(PRODUCT_CALCULATION!B65="SI";PRODUCT_CALCULATION!E65;"") | M71: =IF(PRODUCT_CALCULATION!C65="";"";VLOOKUP(PRODUCT_CALCULATION!C65;PRODUCT!B:Q;16;FALSE)) | N71: =IF(PRODUCT_CALCULATION!C65="";"";VLOOKUP(PRODUCT_CALCULATION!C65;PRODUCT!B:R;17;FALSE)) | O71: =IF(PRODUCT_CALCULATION!C65="";"";VLOOKUP(PRODUCT_CALCULATION!C65;PRODUCT!B:S;18;FALSE)) | P71: =IF(PRODUCT_CALCULATION!C65="";"";VLOOKUP(PRODUCT_CALCULATION!C65;PRODUCT!B:D;3;FALSE)) | Q71: =IF(PRODUCT_CALCULATION!C65="";"";VLOOKUP(PRODUCT_CALCULATION!C65;PRODUCT!B:E;4;FALSE)) | R71: =IF(PRODUCT_CALCULATION!B65="SI";PRODUCT_CALCULATION!F65;"") | S71: =IF(PRODUCT_CALCULATION!B65="SI";PRODUCT_CALCULATION!K65;"") | T71: =IF(PRODUCT_CALCULATION!B65="SI";PRODUCT_CALCULATION!J65;"") | U71: =IF(PRODUCT_CALCULATION!B65="SI";PRODUCT_CALCULATION!N65;"") | V71: =IF(PRODUCT_CALCULATION!B65="SI";PRODUCT_CALCULATION!L65;"") | W71: =IF(PRODUCT_CALCULATION!B65="SI";PRODUCT_CALCULATION!M65;"") | X71: =IF(R65="";"";CEILING(R65/S65;1)) | Y71: =IF(R65="";"";R65*T65) | Z71: =IF(R65="";"";R65*V65)
A72: =INPUT_PRODUCT!B1 | B72: =INPUT_PRODUCT!B2 | C72: =INPUT_PRODUCT!B6 | D72: Arias Group Caribe SRL | F72: Tarancón, España | G72: =INPUT_PRODUCT!B7 | K72: =IF(PRODUCT_CALCULATION!B66="SI";PRODUCT_CALCULATION!C66;"") | L72: =IF(PRODUCT_CALCULATION!B66="SI";PRODUCT_CALCULATION!E66;"") | M72: =IF(PRODUCT_CALCULATION!C66="";"";VLOOKUP(PRODUCT_CALCULATION!C66;PRODUCT!B:Q;16;FALSE)) | N72: =IF(PRODUCT_CALCULATION!C66="";"";VLOOKUP(PRODUCT_CALCULATION!C66;PRODUCT!B:R;17;FALSE)) | O72: =IF(PRODUCT_CALCULATION!C66="";"";VLOOKUP(PRODUCT_CALCULATION!C66;PRODUCT!B:S;18;FALSE)) | P72: =IF(PRODUCT_CALCULATION!C66="";"";VLOOKUP(PRODUCT_CALCULATION!C66;PRODUCT!B:D;3;FALSE)) | Q72: =IF(PRODUCT_CALCULATION!C66="";"";VLOOKUP(PRODUCT_CALCULATION!C66;PRODUCT!B:E;4;FALSE)) | R72: =IF(PRODUCT_CALCULATION!B66="SI";PRODUCT_CALCULATION!F66;"") | S72: =IF(PRODUCT_CALCULATION!B66="SI";PRODUCT_CALCULATION!K66;"") | T72: =IF(PRODUCT_CALCULATION!B66="SI";PRODUCT_CALCULATION!J66;"") | U72: =IF(PRODUCT_CALCULATION!B66="SI";PRODUCT_CALCULATION!N66;"") | V72: =IF(PRODUCT_CALCULATION!B66="SI";PRODUCT_CALCULATION!L66;"") | W72: =IF(PRODUCT_CALCULATION!B66="SI";PRODUCT_CALCULATION!M66;"") | X72: =IF(R66="";"";CEILING(R66/S66;1)) | Y72: =IF(R66="";"";R66*T66) | Z72: =IF(R66="";"";R66*V66)
A73: =INPUT_PRODUCT!B1 | B73: =INPUT_PRODUCT!B2 | C73: =INPUT_PRODUCT!B6 | D73: Arias Group Caribe SRL | F73: Tarancón, España | G73: =INPUT_PRODUCT!B7 | K73: =IF(PRODUCT_CALCULATION!B67="SI";PRODUCT_CALCULATION!C67;"") | L73: =IF(PRODUCT_CALCULATION!B67="SI";PRODUCT_CALCULATION!E67;"") | M73: =IF(PRODUCT_CALCULATION!C67="";"";VLOOKUP(PRODUCT_CALCULATION!C67;PRODUCT!B:Q;16;FALSE)) | N73: =IF(PRODUCT_CALCULATION!C67="";"";VLOOKUP(PRODUCT_CALCULATION!C67;PRODUCT!B:R;17;FALSE)) | O73: =IF(PRODUCT_CALCULATION!C67="";"";VLOOKUP(PRODUCT_CALCULATION!C67;PRODUCT!B:S;18;FALSE)) | P73: =IF(PRODUCT_CALCULATION!C67="";"";VLOOKUP(PRODUCT_CALCULATION!C67;PRODUCT!B:D;3;FALSE)) | Q73: =IF(PRODUCT_CALCULATION!C67="";"";VLOOKUP(PRODUCT_CALCULATION!C67;PRODUCT!B:E;4;FALSE)) | R73: =IF(PRODUCT_CALCULATION!B67="SI";PRODUCT_CALCULATION!F67;"") | S73: =IF(PRODUCT_CALCULATION!B67="SI";PRODUCT_CALCULATION!K67;"") | T73: =IF(PRODUCT_CALCULATION!B67="SI";PRODUCT_CALCULATION!J67;"") | U73: =IF(PRODUCT_CALCULATION!B67="SI";PRODUCT_CALCULATION!N67;"") | V73: =IF(PRODUCT_CALCULATION!B67="SI";PRODUCT_CALCULATION!L67;"") | W73: =IF(PRODUCT_CALCULATION!B67="SI";PRODUCT_CALCULATION!M67;"") | X73: =IF(R67="";"";CEILING(R67/S67;1)) | Y73: =IF(R67="";"";R67*T67) | Z73: =IF(R67="";"";R67*V67)
